Workbook
Name __xlnm._FilterDatabase_1: CONTROLES_PLANO!$AH$4:$AH$10090
Name __xlnm._FilterDatabase_2: RISCOS_RESIDUAIS!$AW$4:$AW$10090
Name __xlnm._FilterDatabase_3: TRATAMENTO!$AI$4:$AI$10090
Name AMEACAS: AMEACAS!$D$2:$D$45
Name CONSEQ_1: AVALIAR_RISCO!$K$10085:$K$10095
Name CONSEQ_10: CONSEQUENCIAS!$H$10084:$H$10094
Name CONSEQ_2: CALCULO_RISCO!$K$10085:$K$10095
Name CONSEQ_3: CONS_AV_QUALIT_ATIVO!$H$10084:$H$10094
Name CONSEQ_4: CONS_AV_QUALIT_PROBAB!$F$10085:$F$10095
Name CONSEQ_5: #N/A
Name CONSEQ_6: CONTROLES_PLANO!$I$10084:$I$10094
Name CONSEQ_7: RESULT_ESTIMAT_QUALIT!$F$10084:$F$10094
Name CONSEQ_8: RISCOS_RESIDUAIS!$I$10084:$I$10094
Name CONSEQ_9: TRATAMENTO!$K$10084:$K$10094
Name DECISÃO: #N/A
Name EXISTEM_RISCOS_RESIDUAIS?: #N/A
Name impacto: #REF!
Name prio: ESTIMATIVA!$N$53:$N$60
Name prioridade: CRITÉRIOS!$M$78:$M$85
Name probabil: #REF!
Name probabilidade: CRITÉRIOS!$F$25:$F$30
Name rele_ativo: CRITÉRIOS!$F$36:$F$41
Name residual: ACEITAÇÃO_RISCO!$A$11019:$A$11021
Name residual_1: RISCOS_RESIDUAIS!$A$11019:$A$11021
Name Rest_Escopo: Restrições!$B$11096:$B$11102
Name Rest_Escopo1: Restrições!$B$11095:$B$11102
Name Rest_organ: Restrições!$A$11096:$A$11106
Name Rest_Organ1: Restrições!$A$11095:$A$11106
Name severidade: CRITÉRIOS!$F$47:$F$52
Name tratar_1: #N/A
Name tratar_2: #N/A
Name tratar_3: #N/A

Sheet INICIO
B27: Exercício Prático | I27: NOME: GUSTAVO PEREIRA DE FARIA
B28: Sessão 2 | I28: NOME: EMERSON CARLOS BEGUETTO
B29: Sessão 3 | I29: NOME: CARLOS EDUARDO BENTO DA SILVA
B30: Sessão 4
B31: Sessão 5
B32: Sessão 6
B33: Sessão 7
B34: Sessão 8
B35: Sessão 9
B36: Sessão 10

Sheet SESSAO_2
A1: Gestão de Riscos de TI – NBR 27005
A3: Sessão 2
A6: OBJETIVO: Aplicar num exercício os conhecimentos adquiridos na sessão 2. Compreender e desenvolver o início de um processo de análise de risco.
A10: Nas quatro atividades que fazem parte desta sessão, serão vistos os conceitos apreendidos na sessão 2. | J10: Atividades – Sessão 2
J11: 2.1 Defina o Contexto
A13: Lembre-se: estas atividades devem ser feitas na sequência e com o acompanhamento da norma 27005. | J13: 2.2 Identifique Restrições
J15: 2.3 Defina o Escopo
A16: Qualquer dúvida pergunte ao instrutor!!
J17: 2.4 Defina os Critérios

Sheet Definir_Contexto
A4: Propósito principal da organização | E4: Fornecer soluções tecnológicas seguras, modernas e eficientes para proteger dados, otimizar processos e impulsionar o crescimento digital das empresas.
A12: Negócio da organização | E12: Serviços de tecnologia da informação com foco em segurança da informação e soluções em nuvem.
A20: A sua missão | E20: Proteger e fortalecer a infraestrutura tecnológica dos nossos clientes, oferecendo soluções inovadoras, seguras e de alta qualidade que garantam continuidade, confiabilidade e competitividade no ambiente digital.
A27: Seus valores | E27: Integridade e ética Segurança e confidencialidade Inovação contínua Transparência Compromisso com o cliente Qualidade nos serviços Responsabilidade social e ambiental
A35: A estrutura da organização | E35: A NexaTech é estruturada em setores funcionais, cada um com responsabilidades específicas, sob coordenação da Diretoria Executiva: Diretoria Executiva TI e Infraestrutura Segurança da Informação Desenvolvimento de Sistemas Suporte Técnico (Help Desk) Comercial e Marketing Recursos Humanos (RH) Financeiro
A43: Organograma | E43: Diretoria Executiva Gerência de TI e Infraestrutura Equipe de Redes Equipe de Servidores e Cloud Gerência de Segurança da Informação Analistas de SOC Time de Pentest Gerência de Desenvolvimento de Sistemas Desenvolvedores Front-end Desenvolvedores Back-end Gerência de Suporte Técnico Técnicos de Help Desk Gerência Comercial e Marketing Gerência de Recursos Humanos Gerência Financeira
A51: Estratégias | E51: Expansão nacional dos serviços de segurança e nuvem Investimento em tecnologias avançadas de proteção (SIEM, EDR, SOAR) Parcerias com provedores de nuvem (AWS, Azure, Google Cloud) Fortalecimento do SOC (Security Operations Center) Automação de processos internos Crescimento no mercado de pequenas e médias empresas
A59: Qual o setor que solicitou o projeto? Qual o seu nível hierárquico dentro do organograma? A quem esta subordinado? | E59: Setor que solicitou: Segurança da Informação Nível Hierarquico: Analista de Segurança da Informação – Nível Júnior Subordinado: Gerente de Segurança da Informação
A67: Qual ou quais os principais processos de negócio da organização? | E67: Monitoramento de segurança (SOC) Gestão de incidentes Consultoria em segurança Implantação de soluções em nuvem Desenvolvimento de sistemas Suporte técnico ao cliente Testes de invasão (Pentest) Backup e recuperação de dados Comercialização e atendimento ao cliente
A75: Quais os requisitos legais ou regulatórios a que a organização esta sujeita? | E75: A NexaTech segue legislações e normas aplicáveis ao setor de TI: Lei Geral de Proteção de Dados (LGPD – Lei 13.709/2018) Marco Civil da Internet (Lei 12.965/2014) Código de Defesa do Consumidor Normas ISO 27001 e 27002 (boas práticas de segurança) Contratos de confidencialidade (NDA) Regulamentações específicas dos clientes (quando aplicável) Direitos trabalhistas (CLT) Lei do Backup (quando aplicável em setores regulados)
A83: Quais os seus principais produtos | E83: Implantação de Cloud Computing Serviço de Monitoramento (SOC 24/7) Pentest (Web, Rede, Mobile) Consultoria em Segurança Desenvolvimento de sistemas Backup e Disaster Recovery Suporte Técnico
A91: Quais os seus fornecedores principais | E91: Provedores de nuvem: AWS, Microsoft Azure, Google Cloud Fornecedores de software de segurança: Fortinet, Kaspersky, CrowdStrike Fabricantes de infraestrutura: Dell, Cisco, Lenovo Serviços terceirizados de suporte e manutenção
... A107: Quais os requisitos legais ou regulatórios a que a organização esta sujeita? | E107: LGPD Marco Civil Normas ISO 27001 CLT Normas do setor financeiro quando atende fintechs Contratos de confidencialidade com clientes e parceiros

Sheet Restrições
A1: Análise das Restrições
A4: Restrições que afetam a organização | B4: Restrições | J4: Justificativa
B5: advindas da agenda da organização | J5: A NexaTech possui um cronograma interno rígido para implantação de projetos, priorizando contratos já ativos, atividades do SOC 24/7 e demandas críticas de segurança. Isso limita a disponibilidade imediata de equipes e recursos para novos projetos, impactando prazos e priorização
B7: advindas do ambiente economico e político | J7: A empresa depende de tecnologias importadas e de fornecedores estrangeiros (Microsoft, AWS, Google), ficando sujeita à variação cambial e instabilidade econômica. Mudanças na legislação de proteção de dados ou políticas governamentais podem impactar custos, compliance e prazos.
B9: de natureza cultural | J9: A cultura organizacional altamente técnica da NexaTech prioriza segurança, processos formais e validações rigorosas. Isso faz com que mudanças, novas metodologias ou novas práticas precisem de avaliação prévia extensa, dificultando adoções rápidas.
B11: de natureza estratégica | J11: O foco estratégico da empresa é expansão do SOC e fortalecimento em cloud. Projetos que não se alinham diretamente a essa visão podem receber menos recursos, tempo ou prioridade, limitando sua execução rápida ou plena.
B13: relacionadas a métodos | J13: A organização utiliza metodologias específicas (ITIL, ISO 27001, OWASP, métodos formais de análise de risco), exigindo padronização e documentação rígida. Isso pode restringir métodos alternativos, abordagens informais ou práticas não alinhadas ao SGSI.
B15: estruturais | J15: A estrutura organizacional com múltiplos níveis (Diretoria → Gerências → Coordenações Analistas) exige fluxo formal de aprovações. Isso pode prolongar decisões, impactar prazos e limitar mudanças inesperadas nos processos.
B17: funcionais | J17: Algumas áreas funcionam com equipes reduzidas (ex.: Desenvolvimento, Help Desk N3), o que restringe a realocação de profissionais e a disponibilidade simultânea para todos os projetos. Essa limitação afeta escalabilidade interna.
A21: Restrições que afetam o escopo | B21: RESTRIÇÕES | J21: JUSTIFICATIVA
B22: ambientais | J22: Os serviços dependem de infraestrutura em nuvem, links estáveis e ambientes controlados. Qualquer limitação física ou de conectividade no cliente ou na própria NexaTech afeta escopo, testes e atividades de implantação.
B24: derivadas de processos preexistentes | J24: Alguns clientes possuem sistemas legados, documentação desatualizada ou integração limitada, o que exige adaptações e pode limitar escopo, impedindo automações ou integrações completas.
B26: financeiras | J26: A alocação de orçamento é controlada e depende de aprovação do setor financeiro e diretoria. Nem sempre o projeto recebe recursos imediatos para novas ferramentas, treinamentos ou contratação de consultores externos, restringindo escopo e velocidade.
B28: organizacionais | J28: Regras internas de segurança, compliance, LGPD e a certificação ISO 27001 impõem controles obrigatórios, impactando prazos, métodos, ferramentas permitidas e tipos de dados que podem ser manipulados no projeto.
B30: técnicas | J30: A NexaTech depende de tecnologias específicas, como plataformas de nuvem (AWS, Azure, Google Cloud), SIEM corporativo e ferramentas de segurança certificadas. Algumas integrações podem ser limitadas pela arquitetura atual do cliente, por sistemas legados ou por incompatibilidade de versões. Além disso, certos recursos avançados exigem licenças adicionais, o que restringe o escopo técnico possível no projeto.
B32: temporais | J32: O escopo pode ser limitado pela disponibilidade de equipes especializadas (SOC, Pentest, Cloud), que trabalham com agendas cheias e atendem contratos simultâneos. Muitos serviços precisam ser executados fora do horário comercial para evitar indisponibilidade, reduzindo as janelas de execução. Também existem prazos contratuais rígidos e SLAs que impedem prolongamento ou expansão do projeto sem negociação formal
B34: relacionadas a métodos | J34: A empresa segue metodologias formais como ISO 27001, ITIL, COBIT e padrões OWASP. Isso exige processos documentados, análises formais de risco, testes controlados e aprovação de mudanças via Change Management. Por esse motivo, métodos alternativos ou abordagens ágeis demais podem não ser permitidos, restringindo como o escopo pode ser executado e quais técnicas podem ser utilizadas.
A11095: ESCOLHA A OPÇÃO | B11095: ESCOLHA A OPÇÃO
A11096: advindas da agenda da organização | B11096: ambientais
A11097: advindas do ambiente economico e político | B11097: derivadas de processos preexistentes
A11098: de natureza cultural | B11098: financeiras
A11099: de natureza estratégica | B11099: organizacionais
A11100: de natureza política | B11100: relacionadas a métodos
A11101: estruturais | B11101: técnicas
A11102: funcionais | B11102: temporais
A11103: orçamentárias
A11104: relacionadas a métodos
A11105: relativas aos recursos humanos
A11106: territoriais

Sheet Escopo
A1: Definição do Escopo
A4: Descrição do escopo | E4: O escopo abrange todas as atividades relacionadas à prestação de serviços de Segurança da Informação, Infraestrutura em Nuvem e Monitoramento (SOC), incluindo implantação de soluções tecnológicas, desenvolvimento de sistemas personalizados, suporte técnico, gestão de ambientes cloud e execução de testes de segurança. Inclui também todos os processos administrativos e operacionais que dão suporte direto a essas atividades.
A12: Seu entendimento do escopo (da equipe de risco - explique o escopo) | E12: A equipe de gestão de riscos será responsável por: Identificar, analisar e avaliar riscos relacionados aos serviços de segurança e TI. Avaliar vulnerabilidades em processos, sistemas e ativos. Monitorar controles existentes e apontar necessidades de melhoria. Apoiar na tomada de decisão para priorização do tratamento de riscos. Garantir alinhamento com boas práticas (ISO 27001, 27005, LGPD). O foco é proteger dados dos clientes e da própria NexaTech, garantindo confiabilidade, disponibilidade e integridade.
A20: Quais os departamentos (áreas/gerencias) envolvidas / abrangidas pelo escopo? | E20: Os seguintes setores estão dentro do escopo: Departamentos Técnicos Segurança da Informação (SOC, análise, gestão de vulnerabilidades) TI e Infraestrutura Desenvolvimento de Sistemas Suporte Técnico / Help Desk Departamentos de Apoio Comercial (por lidar com dados de clientes) Financeiro (por processar informações sensíveis) Recursos Humanos (por administrar dados pessoais e confidenciais) Diretoria Executiva Incluída por decisões estratégicas e validação de políticas.
A28: Quais os processos e sistemas envolvidos / abrangidos pelo escopo? | E28: Processos envolvidos Monitoramento 24/7 de redes (SOC) Atendimento técnico e suporte Gestão de acessos e identidades Desenvolvimento seguro de software Implantação de soluções em nuvem Gestão de vulnerabilidades Gestão de backups e recuperação de desastres Processos de comunicação interna e gestão documental Gestão de contratos e relacionamento com clientes Sistemas envolvidos Plataforma de Cloud (AWS/Azure/GCP) Sistemas internos de gestão de clientes (CRM) Ferramentas de ticket (Help Desk) Ferramentas SIEM Firewalls, IDS/IPS Servidores internos e banco de dados Repositórios de código (GitLab/GitHub)
A36: Quantas pessoas (Recursos Humanos) envolvidos / abrangidos pelo escopo? | E36: Aproximadamente 85 funcionários, sendo: 70 funcionários próprios 15 terceirizados (suporte, infraestrutura, limpeza e segurança) Todos que lidam com dados, sistemas ou processos críticos estão incluídos. no RH
A44: Quantos ativos envolvidos/abrangidos pelo escopo? Aproximado | E44: Estimativa aproximada: Ativos físicos 90 estações de trabalho 12 servidores cloud 6 switches gerenciáveis 4 firewalls corporativos Ativos de software 15 sistemas e plataformas críticas 8 ferramentas de segurança 5 aplicativos internos Ativos informacionais Documentação técnica Políticas internas Dados de clientes Logs e relatórios do SOC Códigos-fonte de projetos Total aproximado: entre 120 e 150 ativos.
A52: Quais os limites do escopo? | E52: Processos e sistemas que suportam a entrega dos serviços da NexaTech Ambientes internos (nuvem, servidores, redes, estações) Pessoas envolvidas em processos críticos Dados tratados ou armazenados pela empresa Infraestrutura utilizada na operação do SOC e demais serviços Processos administrativos diretamente ligados às operações
A60: O que não faz parte do escopo? JUSTIFIQUE | E60: Estão fora do escopo: Sistemas e ambientes de uso pessoal dos colaboradores Processos terceirizados que não tratem dados da empresa Equipamentos pessoais (BYOD) Atividades externas que a NexaTech NÃO executa diretamente Sistemas de parceiros ou fornecedores que não integram os serviços Ambientes domésticos de colaboradores em home office Serviços fora do portfólio da empresa

Sheet CRITÉRIOS
A1: Critérios para Avaliação de Riscos
C4: Critério de Probabilidade
C5: Nível | F5: Definição
C6: Frequente | F6: Tem ocorrido pelo menos uma vez a cada mês
C7: Provável | F7: É possível de ocorrer a cada 6 meses ou menos. Nos últimos seis meses já ocorreu
C8: Ocasional | F8: Nos último ano já ocorreu pelo menos 1 vezes
C9: Remoto | F9: Nos últimos cinco anos já ocorreu pelo menos 3 vezes
C10: Improvável | F10: Nunca ocorreu.
J11: 2.1 Defina o Contexto
C12: Relevância do Ativo
C13: Nível | F13: Descrição
C14: Insignificante | F14: Ativo não afeta processos essenciais e sua perda não gera impacto
C15: Baixo | F15: Ativo auxilia processos, mas sua causa e impacto são facilmente contornáveis.
C16: Significante | F16: É importante para o negócio pois todos os processos passam por ele.
C17: Importante | F17: Ativo essencial para o funcionamento de áreas relevantes; sua perda provoca prejuízo operacional considerável
C18: Crítico | F18: Ativo funcamental para continuidade do negócio; sua indisponibilidade gera paralisação, perdas financeiras e riscos legais.
C20: Severidade das Consequências
C21: Nível | F21: Descrição
C22: Insignificante | F22: Pequena interrupção sem impacto financeiro ou operacional.
C23: Baixa | F23: Impacto limitado e com recuperação rápida; custos pequenos.
C24: Média | F24: Interrupção moderada; pode gerar retrabalho, atrasos e custos notáveis.
C25: Alta | F25: Prejuízo elevado; conpromete operações principais e gera impacto significativo.
C26: Elevada | F26: Prejuízo extremo, paralisação total, danos legais, perda de clientes e reputação.
C28: Impacto
C29: Nível | F29: Descrição
C30: Desprezível | F30: Impacto mínimo, quase imperceptível; sem prejuízo operacional ou financeiro.
C31: Baixo | F31: Pequeno incômodo operacional; custos pequenos; não afeta processos principais.
C32: Significativo | F32: Gera interrupções moderadas, retrabalho, atrasos e impacto financeiro notável.
C33: Importante | F33: Afetam a imagem da organização e causam interrupção de 12 horas nos negócios. A empresa deixa de funcionar/produzir por 12 horas
C34: Desastre | F34: Grande prejuízo financeiro; paralisação total; danos legais severos e fortes crise de reputação.
C36: Critério de Risco
C37: Nível | F37: Descrição
C38: Extremo | F38: A organização pára totalmente seus serviços por mais de 48 horas, impedindo de executar serviços e produzir, afetando sua imagem pública de forma significativa. Prejuízos finaceiros elevados, ações na justiça.
C39: Alto | F39: Risco grave; exige tratamento prioritário e implementação de controles.
C40: Médio | F40: Risco moderado; requer mitigação planejada e monitoramento contínuo.
C41: Baixo | F41: Risco aceitável; manter controles existentes e monitorar periodicamente
C42: Irrelevante | F42: Risco não crítico, porém importante de ser acompanhado; pode exigir ações leves.
C44: Critério de Risco
C45: Nível | F45: Descrição
C46: Extremo | F46: Representa ameaça severa e imediata à continuidade do negócio; não pode ser aceito de forma alguma.
C47: Alto | F47: Demanda resposta rápida e ações fortes de mitigação; impacto significativo no negócio
C48: Médio | F48: Risco controlável com ações planejadas; acompanhamento frequente.
C49: Baixo | F49: Risco de impacto mínimo; controles atuais normalmente suficientes.
C50: Irrelevante | F50: Risco que não compromete operações essenciais, mas merece atenção para evitar evolução.
C52: Exemplo de Critério de Impacto
C53: Nível de risco | F53: Valor | G53: Descrição
C54: Desprezível | F54: 1 | G54: Não ocorrem lesões/mortes na força de trabalho e /ou de pessoas extra-muro. Podem ocorrer casos de primeiros socorros ou tratamento médico sem afastamento. - Sem danos ou danos insignificantes aos equipamentos ou instalações. - Sistemas de TI ficaram fora de operação por até 05 (cinco) minutos.
C55: Levemente prejudicial | F55: 2 | G55: Lesões leves na força de trabalho. Ausência de lesão extra-muros. - Danos leves aos equipamentos ou instalações , controláveis e/ ou de baixo custo de reparo. - Sistemas de TI ficaram fora de operação por até 30 (trinta) minutos.
C56: Prejudicial | F56: 3 | G56: Lesões de gravidade moderada na força de trabalho ou em pessoas extra-muros. Lesões leves em pessoas extra-muros. - Danos severos a equipamentos ou instalações - Sistemas de TI ficaram fora de operação acima de 30 (trinta) minutos. Emissão de NF por sistema alternativo. Houve necessidade de recuperar backup
C57: Extremamente prejudicial | F57: 5 | G57: Provoca morte ou lesões graves em uma ou mais pessoas (na força de trabalho e /ou em pessoas extra-muros) - Danos irreparáveis a equipamentos ou instalações (reparação lenta ou impossível) - Acionado site alternativo. Houve perda de dados e informações. Clientes sem atendimento total.

Sheet SESSAO_3
A1: Gestão de Riscos de TI – NBR 27005
A3: Sessão 3
A6: OBJETIVO: Compreender e desenvolver o início de um processo de análise de risco e iniciar a identificação dos riscos.
A10: Nas três atividades que fazem parte desta sessão, serão vistos os conceitos apreendidos na sessão 3. | J10: Atividades – Sessão 3
J11: 3.1 Identifique os Ativos
A13: Lembre-se: estas atividades devem ser feitas na sequência e com o acompanhamento da norma 27005. | J13: 3.2 Identifique as Ameaças
J15: 3.3 Identifique os Controles Existentes ou Planejados
A16: Qualquer dúvida pergunte ao instrutor!!

Sheet ATIVOS
A1: Identificação dos Ativos do Escopo
J11: 2.1 Defina o Contexto
K18: Justificativa / Evidências
A20: Ativos Primários | B20: At 01 | C20: Infraestrutura de servidores em nuvem | K20: Essencial para execução dos serviços da empresa. Qualquer indisponibilidade impacta diretamente os clientes.
B21: At 02 | C21: Plataforma de monitoramento SOC 24/7 | K21: Responsável por detectar incidentes de segurança em tempo real. Fundamental para resposta rápida a ameaças.
B22: At 03 | C22: Ferramentas de análise de vulnerabilidades | K22: Utilizadas para identificar falhas nos sistemas dos clientes. São base dos serviços prestados.
B23: At 04 | C23: Sistemas de backup e recuperação de dados | K23: Garantem a continuidade do negócio em caso de falhas ou ataques (ex: ransomware).
B24: At 05 | C24: Código-fonte dos sistemas desenvolvidos | K24: Representa o conhecimento técnico e propriedade intelectual da empresa.
B25: At 06 | C25: Ambientes de desenvolvimento (Dev/Test/Prod) | K25: Separação necessária para garantir qualidade, testes e segurança antes da produção.
B26: At 07 | C26: Banco de dados de clientes corporativos | K26: Contém informações sensíveis e estratégicas, exigindo proteção conforme a LGPD.
B27: At 08 | C27: Logs e registros de segurança (SIEM) | K27: Permitem auditoria, rastreamento de incidentes e investigação de ataques.
B28: At 09 | C28: Ferramentas de pentest (internas e licenciadas) | K28: Essenciais para simulação de ataques e avaliação da segurança dos clientes.
B29: At 10 | C29: Credenciais de acesso (senhas, tokens, chaves API) | K29: Acesso direto a sistemas críticos. Comprometimento pode causar invasões
A32: Ativos de Suporte e Infraestrutura | B32: At 11 | C32: Infraestrutura de rede (firewalls, switches, VPN) | K32: Base da comunicação segura da empresa. Falhas podem expor dados ou interromper serviços
B33: At 12 | C33: Sistemas internos de gestão (ERP/CRM) | K33: Controlam operações administrativas e relacionamento com clientes.
B34: At 13 | C34: Plataforma de atendimento (Help Desk) | K34: Canal direto com clientes para suporte e resolução de incidentes.
B35: At 14 | C35: Contratos e acordos com clientes (SLAs) | K35: Definem responsabilidades, níveis de serviço e obrigações legais.
B36: At 15 | C36: Documentação técnica e procedimentos internos | K36: Padronizam processos e garantem consistência nas operações.
B37: At 16 | C37: Políticas de segurança da informação | K37: Orientam o comportamento dos colaboradores e reduzem riscos de segurança.
B38: At 17 | C38: Ambiente de virtualização (VMs e containers) | K38: Permite escalabilidade e otimização dos recursos computacionais
B39: At 18 | C39: Ferramentas de gestão de projetos (ex: Jira, Trello) | K39: Auxiliam no controle de tarefas, prazos e produtividade das equipes.
B40: At 19 | C40: Dispositivos corporativos (notebooks, desktops) | K40: Utilizados pelos colaboradores, podendo ser ponto de entrada para ataques
B41: At 20 | C41: Sistemas de autenticação (AD, MFA, IAM) | K41: Controlam o acesso aos sistemas, garantindo segurança e rastreabilidade.
B42: At 21 | C42: Repositórios de código (Git, GitHub, GitLab) | K42: Armazenam o código-fonte e histórico de desenvolvimento dos sistemas
B43: At 22 | C43: Plataforma de cloud utilizada (AWS, Azure, etc.) | K43: Base da infraestrutura dos serviços oferecidos pela empresa.
B44: At 23 | C44: Dados sensíveis de clientes (LGPD) | K44: Informações críticas que exigem proteção legal e podem gerar penalidades em caso de vazamento.
... B46: At 25 | C46: Utilizados para troca de informações internas e externas, podendo ser alvo de phishing. | K46: Capital intelectual da empresa, essencial para execução dos serviços e inovação.
B47: At 26
B48: At 27
B49: At 28
B50: At 29
B51: At 30

Sheet LISTA AMEACAS
A1: Identificação das Ameaças aos Ativos
J11: 2.1 Defina o Contexto
B19: Ativos | E19: Ameaça 1 | I19: Ameaças 2 | M19: Justificativa / Evidências
I20: Ameaça 2
A21: =ATIVOS!B20 -> At 01 | B21: =ATIVOS!C20 -> Infraestrutura de servidores em nuvem | E21: Vazamento de informações | I21: Roubo de dados por concorrentes | M21: A empresa lida com dados confidenciais sobre cursos e materiais que são muito importantes para manter o diferencial competitivo. Se não houver controle adequado, pode acontecer vazamento ou até espionagem industrial por parte de concorrentes.
A22: =ATIVOS!B21 -> At 02 | B22: =ATIVOS!C21 -> Plataforma de monitoramento SOC 24/7 | E22: Perda de inovação por acesso indevido | I22: Interferência na produção de novos materiais | M22: As informações sobre tendências de mercado e inovação precisam ser bem protegidas contra acessos não autorizados. Se houver falhas, isso pode atrapalhar o lançamento de novos produtos e afetar a competitividade da empresa.
A23: =ATIVOS!B22 -> At 03 | B23: =ATIVOS!C22 -> Ferramentas de análise de vulnerabilidades | E23: Ataques cibernéticos | I23: Interrupção de serviços críticos | M23: Os sistemas ERP e CRM são fundamentais para o funcionamento da empresa. Se não houver segurança adequada, pode haver paralisação das operações e exposição de dados sensíveis, o que prejudica bastante a organização.
A24: =ATIVOS!B23 -> At 04 | B24: =ATIVOS!C23 -> Sistemas de backup e recuperação de dados | E24: Roubo de informações | I24: Uso indevido por terceiros | M24: Os dados confidenciais dos clientes precisam estar bem protegidos para evitar qualquer violação de privacidade. Isso é importante para seguir leis como a LGPD e manter a confiança dos parceiros e consumidores.
A25: =ATIVOS!B24 -> At 05 | B25: =ATIVOS!C24 -> Código-fonte dos sistemas desenvolvidos | E25: Falhas operacionais | I25: Sabotagem industrial | M25: A produção precisa ser estável. Qualquer ataque ou falha pode comprometer os prazos e a qualidade dos produtos, gerando prejuízos e atrasos.
A26: =ATIVOS!B25 -> At 06 | B26: =ATIVOS!C25 -> Ambientes de desenvolvimento (Dev/Test/Prod) | E26: Interrupção na cadeia logística | I26: Manipulação indevida de entregas | M26: Erros ou atrasos na logística afetam diretamente a satisfação do cliente e podem prejudicar a imagem da empresa KWX.
A27: =ATIVOS!B26 -> At 07 | B27: =ATIVOS!C26 -> Banco de dados de clientes corporativos | E27: Fraudes financeiras | I27: Alteração não autorizada de registros | M27: O setor financeiro lida com transações sensíveis que precisam de segurança contra manipulação ou acessos indevidos.
A28: =ATIVOS!B27 -> At 08 | B28: =ATIVOS!C27 -> Logs e registros de segurança (SIEM) | E28: Falta de conformidade | I28: Desrespeito às normas de segurança | M28: A inexistência de políticas bem estabelecidas pode comprometer a integridade e confidencialidade dos ativos.
A29: =ATIVOS!B28 -> At 09 | B29: =ATIVOS!C28 -> Ferramentas de pentest (internas e licenciadas) | E29: Vazamento de dados pessoais | I29: Uso indevido de informações de colaboradores | M29: Proteção de dados internos é essencial para evitar prejuízos aos funcionários e atender às leis de privacidade.
A30: =ATIVOS!B29 -> At 10 | B30: =ATIVOS!C29 -> Credenciais de acesso (senhas, tokens, chaves API) | E30: Ataques de phishing | I30: Roubo de credenciais | M30: A segurança das comunicações internas e externas é crucial para evitar fraudes e manter a integridade da empresa.
A31: =ATIVOS!B32 -> At 11 | B31: =ATIVOS!C32 -> Infraestrutura de rede (firewalls, switches, VPN) | E31: Falha na infraestrutura | I31: Ataques cibernéticos e invasões | M31: Servidores guardam informações importantes e precisam de proteção contra falhas e acessos não autorizados.
A32: =ATIVOS!B33 -> At 12 | B32: =ATIVOS!C33 -> Sistemas internos de gestão (ERP/CRM) | E32: Malware e ataques de phishing | I32: Uso indevido por funcionários não autorizados | M32: São os principais computadores de trabalho e precisam de proteção contra ataques e perda de dados.
A33: =ATIVOS!B34 -> At 13 | B33: =ATIVOS!C34 -> Plataforma de atendimento (Help Desk) | E33: Acesso indevido a documentos | I33: Sabotagem ou falhas técnicas | M33: Impressoras podem ter documentos secretos e precisam de segurança física e digital.
A34: =ATIVOS!B35 -> At 14 | B34: =ATIVOS!C35 -> Contratos e acordos com clientes (SLAs) | E34: Exploração de vulnerabilidades | I34: Perda de dados por falha sistêmica | M34: São sistemas importantes para a empresa; a segurança deles é vital para evitar problemas e fraudes.
A35: =ATIVOS!B36 -> At 15 | B35: =ATIVOS!C36 -> Documentação técnica e procedimentos internos | E35: Furto de mídia ou documentos | I35: Recuperação de mídia reciclada ou descartada | M35: Pode expor procedimentos internos e informações críticas; Documentos descartados podem ser recuperados indevidamente.
A36: =ATIVOS!B37 -> At 16 | B36: =ATIVOS!C37 -> Políticas de segurança da informação | E36: Violação das condições de uso do sistema de informação que possibilitam sua manutenção | I36: Abuso de direitos | M36: Colaboradores podem descumprir políticas estabelecidas; Usuários com acesso podem agir fora das regras definidas.
A37: =ATIVOS!B38 -> At 17 | B37: =ATIVOS!C38 -> Ambiente de virtualização (VMs e containers) | E37: Falha de equipamento | I37: Alteração do software | M37: Pode derrubar máquinas virtuais e serviços; Pode comprometer o funcionamento das VMs ou containers.
A38: =ATIVOS!B39 -> At 18 | B38: =ATIVOS!C39 -> Ferramentas de gestão de projetos (ex: Jira, Trello) | E38: Saturação do sistema de informação | I38: Processamento ilegal de dados | M38: Pode tornar a ferramenta indisponível; Pode ocorrer uso indevido das informações dos projetos.
A39: =ATIVOS!B40 -> At 19 | B39: =ATIVOS!C40 -> Dispositivos corporativos (notebooks, desktops) | E39: Furto de equipamentos | I39: Uso não autorizado de equipamento | M39: Pode expor dados armazenados nos dispositivos; Terceiros podem acessar informações da empresa.
A40: =ATIVOS!B41 -> At 20 | B40: =ATIVOS!C41 -> Sistemas de autenticação (AD, MFA, IAM) | E40: Abuso de direitos | I40: Comprometimento dos dados | M40: Usuários podem utilizar privilégios de forma indevida
A41: =ATIVOS!B42 -> At 21 | B41: =ATIVOS!C42 -> Repositórios de código (Git, GitHub, GitLab) | E41: Cópia ilegal de software | I41: Alteração do software | M41: Código pode ser copiado sem autorização; Código pode ser modificado de forma maliciosa.
A42: =ATIVOS!B43 -> At 22 | B42: =ATIVOS!C43 -> Plataforma de cloud utilizada (AWS, Azure, etc.) | E42: Interrupção do suprimento de energia | I42: Falha de equipamento | M42: Pode causar indisponibilidade dos serviços; Problemas na infraestrutura podem afetar sistemas hospetados.
... A45: =ATIVOS!B46 -> At 25 | B45: =ATIVOS!C46 -> Utilizados para troca de informações internas e externas, podendo ser alvo de phishing. | E45: Indisponibilidade de recursos humanos | I45: Falha de equipamento | M45: A ausência ou saída de colaboradores pode comprometer atividades críticas, já que o conhecimento técnico está concentrado na equipe; Falhas de equipamento podem causar incidentes de segurança ou operacionais, impactando os serviços da empresa.
A46: =ATIVOS!B47 -> At 26 | B46: =ATIVOS!C47 -> 0 | E46: Identifique uma Ameaça | I46: Identifique uma Ameaça
A47: =ATIVOS!B48 -> At 27 | B47: =ATIVOS!C48 -> 0 | E47: Identifique uma Ameaça | I47: Identifique uma Ameaça
A48: =ATIVOS!B49 -> At 28 | B48: =ATIVOS!C49 -> 0 | E48: Identifique uma Ameaça | I48: Identifique uma Ameaça
A49: =ATIVOS!B50 -> At 29 | B49: =ATIVOS!C50 -> 0 | E49: Identifique uma Ameaça | I49: Identifique uma Ameaça
A50: =ATIVOS!B51 -> At 30 | B50: =ATIVOS!C51 -> 0 | E50: Identifique uma Ameaça | I50: Identifique uma Ameaça

Sheet CONTROLES EXIST
A1: Identificação dos Controles Existentes ou com Implementação Planejada
J11: 2.1 Defina o Contexto
B19: Ativo | E19: Ameaças | J19: Controle Existente ou Planejado | M19: Justificativa/Evidências
A20: ='LISTA AMEACAS'!A21 -> At 01 | B20: ='LISTA AMEACAS'!B21 -> Infraestrutura de servidores em nuvem | E20: ='LISTA AMEACAS'!E21 -> Vazamento de informações | H20: Controle | J20: Planejado | M20: Implementação de controle de acesso e criptografia para proteger dados sensíveis armazenados na nuvem; A criptografia protege os dados armazenados e transmitidos contra acessos não autorizados.
H21: Controle | J21: Planejado | M21: Monitoramento contínuo e auditoria de logs permitem identificar acessos suspeitos e prevenir vazamentos de informações; O monitoramento contínuo permite detectar comportamentos suspeitos e prevenir incidentes de segurança.
E22: ='LISTA AMEACAS'!I21 -> Roubo de dados por concorrentes | H22: Controle | J22: Planejado | M22: Criptografia de dados em trânsito e repouso; A proteção de dados em trânsito e repouso dificulta a interceptação por terceiros.
H23: Controle | J23: Planejado | M23: A implementação de autentitação multifator reduz o risco de acesso indevido; A autenticação multifator reduz o risco de acesso indevido mesmo com credenciais comprometidas.
B25: Ativo | E25: Ameaças | J25: Controle Existente ou Planejado | M25: Justificativa/Evidências
A26: ='LISTA AMEACAS'!A22 -> At 02 | B26: ='LISTA AMEACAS'!B22 -> Plataforma de monitoramento SOC 24/7 | E26: ='LISTA AMEACAS'!E22 -> Perda de inovação por acesso indevido | H26: Controle | J26: Planejado | M26: Restrição de acesso a informações estratégicas; A restrição de acesso protege informações estratégicas da empresa.
H27: Controle | J27: Planejado | M27: A segregação de acessos garante que apenas usuários autorizados manipulem informações; A segregação de funções impede que usuários acessem dados fora de sua responsabilidade.
E28: ='LISTA AMEACAS'!I22 -> Interferência na produção de novos materiais | H28: Controle | J28: Existente | M28: Padronização de processos; A padronização de processos reduz erros operacionais e inconsistências.
H29: Controle | J29: Planejado | M29: Monitoramento de atividades; O monitoramento das atividades permite identificar e corrigir falhas rapidamente.
B31: Ativo | E31: Ameaças | J31: Controle Existente ou Planejado | M31: Justificativa/Evidências
A32: ='LISTA AMEACAS'!A23 -> At 03 | B32: ='LISTA AMEACAS'!B23 -> Ferramentas de análise de vulnerabilidades | E32: ='LISTA AMEACAS'!E23 -> Ataques cibernéticos | H32: Controle | J32: Existente | M32: Uso de ferramentas de segurança; O uso de ferramentas de segurança permite identificar vulnerabilidades e reduzir a exposição a ataques cibernéticos.
H33: Controle | J33: Planejado | M33: Atualização contínua e monitoramento; A atualização contínua e o monitoramento garantem que novas ameaças sejam detectadas e mitigadas rapidamente.
E34: ='LISTA AMEACAS'!I23 -> Interrupção de serviços críticos | H34: Controle | J34: Planejado | M34: Redundância; A implementação de redundância assegura a disponibilidade dos sistemas mesmo em caso de falhas.
H35: Controle | J35: Planejado | M35: Plano de continuidade; O plano de continuidade garante a rápida recuperação dos serviços, reduzindo impactos operacionais.
B37: Ativo | E37: Ameaças | J37: Controle Existente ou Planejado | M37: Justificativa/Evidências
A38: ='LISTA AMEACAS'!A24 -> At 04 | B38: ='LISTA AMEACAS'!B24 -> Sistemas de backup e recuperação de dados | E38: ='LISTA AMEACAS'!E24 -> Roubo de informações | H38: Controle | J38: Existente | M38: Backup de dados; A realização de backups periódicos garante a recuperação dos dados em caso de incidentes de segurança.
H39: Controle | J39: Planejado | M39: Criptografia dos backups; A criptografia dos backups protege as informações contra acesso não autorizado.
E40: ='LISTA AMEACAS'!I24 -> Uso indevido por terceiros | H40: Controle | J40: Planejado | M40: Controle de acesso; Controle de acesso restringe a utilização dos dados apenas a usuários autorizados.
H41: Controle | J41: Planejado | M41: Auditoria de acessos; A auditoria de acessos permite rastrear atividades e identificar possíveis usos indevidos.
B43: Ativo | E43: Ameaças | J43: Controle Existente ou Planejado | M43: Justificativa/Evidências
A44: ='LISTA AMEACAS'!A25 -> At 05 | B44: ='LISTA AMEACAS'!B25 -> Código-fonte dos sistemas desenvolvidos | E44: ='LISTA AMEACAS'!E25 -> Falhas operacionais | H44: Controle | J44: Existente | M44: Testes básicos; A realização de testes básicos permite identificar erros no sistema antes da implantação em produção.
H45: Controle | J45: Planejado | M45: Revisão formal de código; A revisão formal de código garante maior qualidade e reduz a ocorrência de falhas operacionais.
E46: ='LISTA AMEACAS'!I25 -> Sabotagem industrial | H46: Controle | J46: Planejado | M46: Controle de acesso ao repositório; O controle de acesso ao repositório restringe alterações apenas a usuários autorizados.
H47: Controle | J47: Planejado | M47: Monitoramento de alterações; O monitoramento de alterações permite identificar modificações suspeitas no código-fonte.
B49: Ativo | E49: Ameaças | J49: Controle Existente ou Planejado | M49: Justificativa/Evidências
A50: ='LISTA AMEACAS'!A26 -> At 06 | B50: ='LISTA AMEACAS'!B26 -> Ambientes de desenvolvimento (Dev/Test/Prod) | E50: ='LISTA AMEACAS'!E26 -> Interrupção na cadeia logística | H50: Controle | J50: Planejado | M50: Plano de continuidade; O plano de continuidade garante a manutenção das operações mesmo em caso de falhas nos ambientes.
H51: Controle | J51: Planejado | M51: Monitoramento; O monitoramento contínuo permite identificar problemas rapidamente e reduzir impactos no fluxo de desenvolvimento.
E52: ='LISTA AMEACAS'!I26 -> Manipulação indevida de entregas | H52: Controle | J52: Existente | M52: Controle de versionamento; O controle de versionamento garante a integridade das versões e evita alterações não autorizadas.
H53: Controle | J53: Planejado | M53: Rastreamento de alterações; O rastreamento de alterações permite a identificar responsáveis por modificações indevidas.
B55: Ativo | E55: Ameaças | J55: Controle Existente ou Planejado | M55: Justificativa/Evidências
A56: ='LISTA AMEACAS'!A27 -> At 07 | B56: ='LISTA AMEACAS'!B27 -> Banco de dados de clientes corporativos | E56: ='LISTA AMEACAS'!E27 -> Fraudes financeiras | H56: Controle | J56: Planejado | M56: Auditoria; A realização de auditorias permite identificar inconsistências e previnir fraudes nos dados financeiros.
H57: Controle | J57: Planejado | M57: Segregação de funções; A segregação de funções reduz o risco de ações maliciosas ao limitar o acesso conforme responsabilidades.
E58: ='LISTA AMEACAS'!I27 -> Alteração não autorizada de registros | H58: Controle | J58: Existente | M58: Controle de acesso; controle de acesso garante que apenas usuários autorizados possam modificar os dados.
H59: Controle | J59: Planejado | M59: Logs e monitoramento; O uso de logs e monitoramento permite rastrear alterações e identificar atividades suspeitas.
B61: Ativo | E61: Ameaças | J61: Controle Existente ou Planejado | M61: Justificativa/Evidências
A62: ='LISTA AMEACAS'!A28 -> At 08 | B62: ='LISTA AMEACAS'!B28 -> Logs e registros de segurança (SIEM) | E62: ='LISTA AMEACAS'!E28 -> Falta de conformidade | H62: Controle | J62: Planejado | M62: Políticas de segurança; A definição de políticas de segurança assegura que os processos estejam alinhados às normas e regulamentações.
H63: Controle | J63: Planejado | M63: Auditorias; A realização de auditorias periódicas garante o cumprimento das exigências de conformidade.
E64: ='LISTA AMEACAS'!I28 -> Desrespeito às normas de segurança | H64: Controle | J64: Planejado | M64: Monitoramento; O monitoramento contínuo permite identificar o comportamentos fora dos padrões estabelecidos.
H65: Controle | J65: Planejado | M65: Treinamento; O treinamento dos colaboradores reforça a importância das normas e reduz falhas humanos.
B67: Ativo | E67: Ameaças | J67: Controle Existente ou Planejado | M67: Justificativa/Evidências
A68: ='LISTA AMEACAS'!A29 -> At 09 | B68: ='LISTA AMEACAS'!B29 -> Ferramentas de pentest (internas e licenciadas) | E68: ='LISTA AMEACAS'!E29 -> Vazamento de dados pessoais | H68: Controle | J68: Planejado | M68: Controle de permissões; O controle de permissões garante que apenas usuários autorizaods tenham acesso às informações sensíveis.
H69: Controle | J69: Planejado | M69: Monitoramento; O monitoramento contínuo permite identificar acessos indevidos e prevenir vazamentos de dados.
E70: ='LISTA AMEACAS'!I29 -> Uso indevido de informações de colaboradores | H70: Controle | J70: Planejado | M70: Auditoria; A realização de auditorias permite rastrear o uso das informações e identificar irregularidades.
H71: Controle | J71: Planejado | M71: Supervisão; A supervisão das atividades garante que as ferramentas sejam utilizadas de forma adequada e conforme as políticas da empresa.
B73: Ativo | E73: Ameaças | J73: Controle Existente ou Planejado | M73: Justificativa/Evidências
A74: ='LISTA AMEACAS'!A30 -> At 10 | B74: ='LISTA AMEACAS'!B30 -> Credenciais de acesso (senhas, tokens, chaves API) | E74: ='LISTA AMEACAS'!E30 -> Ataques de phishing | H74: Controle | J74: Existente | M74: Filtros de e-mail; A utilização de filtros de e-mail reduz a entrada de mensagens maliciosas e tantativas de phishing.
H75: Controle | J75: Planejado | M75: Treinamento; O treinamento dos colaboradores aumenta a conscientização e reduz o risco da exposição a ataques.
E76: ='LISTA AMEACAS'!I30 -> Roubo de credenciais | H76: Controle | J76: Planejado | M76: MFA; A implementação de autenticação multifator (MFA) adiciona uma camada extra de segurança contra acessos indevidos.
H77: Controle | J77: Planejado | M77: Monitoramento; O monitoramento contínuo permite identificar tentativas suspeitas de acesso agir rapidamente.
B79: Ativo | E79: Ameaças | J79: Controle Existente ou Planejado | M79: Justificativa/Evidências
A80: ='LISTA AMEACAS'!A31 -> At 11 | B80: ='LISTA AMEACAS'!B31 -> Infraestrutura de rede (firewalls, switches, VPN) | E80: ='LISTA AMEACAS'!E31 -> Falha na infraestrutura | H80: Controle | J80: Existente | M80: Manutenção básica; A manutenção preventiva reduz a probabilidade de falhas na infraestrutura de rede.
H81: Controle | J81: Planejado | M81: Monitoramento avançado; O monitoramento avançado permite identificar problemas em tempo real, possibilidade ações rápidas para evitar indisponibilidade.
E82: ='LISTA AMEACAS'!I31 -> Ataques cibernéticos e invasões | H82: Controle | J82: Existente | M82: Firewall; A utilização de firewalls permite controlar o tráfego de rede, bloqueando acessos não autorizados e protegendo os sistemas internos.
H83: Controle | J83: Planejado | M83: IDS/IPS; A implantação de sistemas IDS/IPS possibilita detectar e prevenir ataques em tempo real, aumentando a segurança da infraestrutura.
B85: Ativo | E85: Ameaças | J85: Controle Existente ou Planejado | M85: Justificativa/Evidências
A86: ='LISTA AMEACAS'!A32 -> At 12 | B86: ='LISTA AMEACAS'!B32 -> Sistemas internos de gestão (ERP/CRM) | E86: ='LISTA AMEACAS'!E32 -> Malware e ataques de phishing | H86: Controle | J86: Existente | M86: Antívirus; A utilização de antivírus protege os sistemas contra a execução de softwares maliciosas, reduzindo risco de infecções.
H87: Controle | J87: Planejado | M87: Proteções avançadas; A implementação de proteções avançadas aumenta a segurança ao detectar ameaças mais sofisticadas e vulnerabilidades.
E88: ='LISTA AMEACAS'!I32 -> Uso indevido por funcionários não autorizados | H88: Controle | J88: Existente | M88: Login/senha; Uso de login e senha garante que apenas usuários autenticados tenham acesso ao sistema.
H89: Controle | J89: Planejado | M89: Controle por perfil; Controle de acesso por perfil limita as permissões de cada usuário conforme sua função, reduzindo abusos.
B91: Ativo | E91: Ameaças | J91: Controle Existente ou Planejado | M91: Justificativa/Evidências
A92: ='LISTA AMEACAS'!A33 -> At 13 | B92: ='LISTA AMEACAS'!B33 -> Plataforma de atendimento (Help Desk) | E92: ='LISTA AMEACAS'!E33 -> Acesso indevido a documentos | H92: Controle | J92: Existente | M92: Autenticação básica; A autenticação básica garante que apenas usuários identificados tenham acesso ao sistema.
H93: Controle | J93: Planejado | M93: Restrição por perfil; A restrição por perfil limita o acesso às informações conforme a função de cada colaborador, reduzindo riscos de exposição indevida.
E94: ='LISTA AMEACAS'!I33 -> Sabotagem ou falhas técnicas | H94: Controle | J94: Planejado | M94: Plano de contingência; O plano de contingência aliado ao monitoramento contínuo permite identificar falhas rapidamente e garantir a continuidade do serviço.
H95: Controle | J95: Planejado | M95: Monitoramento; A implementação de monitoramento reduz vulnerabilidades e protege o sistema contra ações maliciosas.
B97: Ativo | E97: Ameaças | J97: Controle Existente ou Planejado | M97: Justificativa/Evidências
A98: ='LISTA AMEACAS'!A34 -> At 14 | B98: ='LISTA AMEACAS'!B34 -> Contratos e acordos com clientes (SLAs) | E98: ='LISTA AMEACAS'!E34 -> Exploração de vulnerabilidades | H98: Controle | J98: Planejado | M98: Revisão periódica; revisão periódica reduz as chances de ocorrer erros os falhas.
H99: Controle | J99: Planejado | M99: Políticas de segurança; Ajusta os padrões de segurança da empresa para evitar vulnerabilidades.
E100: ='LISTA AMEACAS'!I34 -> Perda de dados por falha sistêmica | H100: Controle | J100: Existente | M100: Armazenamento de documentos; Reduz a chance de perda dos documentos ou acesso por pessoas indevidas.
H101: Controle | J101: Planejado | M101: Backup estruturado; O backup estruturado garante segurança dos dados para que não sejam acessados indevidamente ou perdidos.
B103: Ativo | E103: Ameaças | J103: Controle Existente ou Planejado | M103: Justificativa/Evidências
A104: ='LISTA AMEACAS'!A35 -> At 15 | B104: ='LISTA AMEACAS'!B35 -> Documentação técnica e procedimentos internos | E104: ='LISTA AMEACAS'!E35 -> Furto de mídia ou documentos | H104: Controle | J104: Existente | M104: Armazenamento em local restrito com ascesso controlado; Reduz as chances de acesso por pessoas indevidas ou maliciosas.
H105: Controle | J105: Planejado | M105: Implementação de controle acesso mais rigoroso com acesso controlado;
E106: ='LISTA AMEACAS'!I35 -> Recuperação de mídia reciclada ou descartada | H106: Controle | J106: Planejado | M106: Será implementado o processo de descarte seguro de mídias como destruição fisica ou limpeza de dados.
H107: Controle | J107: Não existe
B109: Ativo | E109: Ameaças | J109: Controle Existente ou Planejado | M109: Justificativa/Evidências
A110: ='LISTA AMEACAS'!A36 -> At 16 | B110: ='LISTA AMEACAS'!B36 -> Políticas de segurança da informação | E110: ='LISTA AMEACAS'!E36 -> Violação das condições de uso do sistema de informação que possibilitam sua manutenção | H110: Controle | J110: Planejado | M110: Será implemntado politica formal de segurança da informção
H111: Controle | J111: Planejado | M111: Existe orientação basica aos funcionários, porem sem formalização dxocumentada.
E112: ='LISTA AMEACAS'!I36 -> Abuso de direitos | H112: Controle | J112: Planejado | M112: Impçl.ementaçãol de acesso baseados em perfis (RBAC), garantindo que usuários tenham apenas os privilégios nescessários.
H113: Controle | J113: Planejado | M113: Auditorioas periódicas de acessos serão realizadas para identificar abusos ou acessos indevidos.
B115: Ativo | E115: Ameaças | J115: Controle Existente ou Planejado | M115: Justificativa/Evidências
A116: ='LISTA AMEACAS'!A37 -> At 17 | B116: ='LISTA AMEACAS'!B37 -> Ambiente de virtualização (VMs e containers) | E116: ='LISTA AMEACAS'!E37 -> Falha de equipamento | H116: Controle | J116: Existente | M116: Uso de virtualização para isolamento de falhas entre ambientes; A virtualização permite que falhas em uma máquina não afetem outras, garantindo maior disponibilidade.
H117: Controle | J117: Planejado | M117: Monitoramento contínuo dos recursos e desempenho das VMs; O monitoramento permite identificar falhas antecipadamente e reduzir impactos operacionais.
E118: ='LISTA AMEACAS'!I37 -> Alteração do software | H118: Controle | J118: Existente | M118: Uso de imagens padronizadas e controladas pela criação de VMs; A padronização evita modificações não autorizadas nos ambientes virtualizados.
H119: Controle | J119: Planejado | M119: Controle de versões e gestão de mudanças nos ambientes virtualizados; A gestão de mudanças garante rastreabilidade e impede alterações indevidas nos sistemas.
B121: Ativo | E121: Ameaças | J121: Controle Existente ou Planejado | M121: Justificativa/Evidências
A122: ='LISTA AMEACAS'!A38 -> At 18 | B122: ='LISTA AMEACAS'!B38 -> Ferramentas de gestão de projetos (ex: Jira, Trello) | E122: ='LISTA AMEACAS'!E38 -> Saturação do sistema de informação | H122: Controle | J122: Existente | M122: Utilização de ferramentas em nuvem com estabilidade automática; A escalabilidade permite suportar aumento de usuários e demandas sem comprometer o desempenho.
H123: Controle | J123: Planejado | M123: Monitoramento de desempenho e uso do sistema; O monitoramento permite identificar sobrecargas e agir antes que o sistema fique indisponível.
E124: ='LISTA AMEACAS'!I38 -> Processamento ilegal de dados | H124: Controle | J124: Planejado | M124: Implementação de controle de acesso por perfil de usuário; Garante que apenas usuários autorizados tenham acesso às informações do sistema.
H125: Controle | J125: Planejado | M125: Adequação às normas de proteção de dados (LGPD); Assegura que o tratamento de dados esteja em conformidade com a legislação vigente.
B127: Ativo | E127: Ameaças | J127: Controle Existente ou Planejado | M127: Justificativa/Evidências
A128: ='LISTA AMEACAS'!A39 -> At 19 | B128: ='LISTA AMEACAS'!B39 -> Dispositivos corporativos (notebooks, desktops) | E128: ='LISTA AMEACAS'!E39 -> Furto de equipamentos | H128: Controle | J128: Existente | M128: Registro e controle de inventários dos dispositivos corporativos; O inventário permite rastrear os equipamentos e identificar rapidamente perdas ou furtos.
H129: Controle | J129: Planejado | M129: Implementação de criptografia nos dispositivos; A criptografia nos dispositivos; A criptografia protege os dados armazenados mesmo em caso de furto do equipamento.
E130: ='LISTA AMEACAS'!I39 -> Uso não autorizado de equipamento | H130: Controle | J130: Existente | M130: Autenticação por login e senhas nos dispositivos; Impede que usuários não autorizados acessem o sistema diretamente.
H131: Controle | J131: Planejado | M131: Bloqueio automático de tela e controle de acesso por perfil; Reduz risco de acesso indevido em caso de ausência do usuário ou uso indevido do equipamento.
B133: Ativo | E133: Ameaças | J133: Controle Existente ou Planejado | M133: Justificativa/Evidências
A134: ='LISTA AMEACAS'!A40 -> At 20 | B134: ='LISTA AMEACAS'!B40 -> Sistemas de autenticação (AD, MFA, IAM) | E134: ='LISTA AMEACAS'!E40 -> Abuso de direitos | H134: Controle | J134: Existente | M134: Controle de acesso baseado em perfis de usuário (RBAC); Limita os privilégios de cada usuário apenas ao necessário para sua função, reduzindo abusos.
H135: Controle | J135: Planejado | M135: Revisão periódica de permissões e privilégios; Garante que acessos indevidos sejam identificados e removidos ao longo do tempo.
...

Sheet SESSAO_4
A1: Gestão de Riscos de TI – NBR 27005
A3: Sessão 4
A6: OBJETIVO: Aplicar num exercício os conhecimentos adquiridos na sessão 4. Compreender e desenvolver a identificação dos riscos.
A10: Nas duas atividades que fazem parte desta sessão, serão vistos os conceitos apreendidos na sessão 4. | J10: Atividades – Sessão 4
J11: 4.1 Identifique as Vulnerabilidades
A13: Lembre-se: estas atividades devem ser feitas na sequência e com o acompanhamento da norma 27005. | J13: 4.2 Identifique as Consequencias
A16: Qualquer dúvida pergunte ao instrutor!!

Sheet VULNERABILIDADES
A1: Identificação das Vulnerabilidades NÃO Atendidas pelos Controles Existentes
J11: 2.1 Defina o Contexto
B19: Ativo | D19: Ameaças | I19: Controle existente | K19: Nr. | L19: Vulnerabilidades Encontradas | S19: Justificativa/Evidências
A20: At 01 | B20: ='LISTA AMEACAS'!B21 -> Infraestrutura de servidores em nuvem | D20: ='LISTA AMEACAS'!E21 -> Vazamento de informações | G20: Controle | I20: ='CONTROLES EXIST'!J20 -> Planejado | K20: 1 | L20: Falta de classificação da informação | S20: Não há política de classificação de dados implementada, evidenciado pela ausência de identificação de níveis de criticidade nos documentos.
K21: 2 | L21: Dados armazenados sem criptografia. | S21: Arquivos e bases de dados estão acessíveis sem mecanismos de criptografia em repouso, permitindo leitura direta em caso de acesso indevido.
G22: Controle | I22: ='CONTROLES EXIST'!J21 -> Planejado | K22: 3 | L22: Armazenamento inseguro | S22: Dados armazenados em locais sem controle de acesso.conforme estruturas de diretórios compartilhados.
K23: 4 | L23: Falta de monitoramento de acesso. | S23: Não há registro ou análise de logs de acesso aos dados armazenados.
D24: ='LISTA AMEACAS'!I21 -> Roubo de dados por concorrentes | G24: Controle | I24: ='CONTROLES EXIST'!J22 -> Planejado | K24: 5 | L24: Falta de backup adequado | S24: Existe backup porém sem validação periódica de restauração
G25: Controle | K25: 6 | L25: Logs de auditoria incompletos. | S25: Atividades críticas não são registradas de forma detalhada, dificultando rastreabilidade.
G26: Controle | I26: ='CONTROLES EXIST'!J23 -> Planejado | K26: 7 | L26: Acesso indevido | S26: Permissões amplas sem segregação,evidenciado por ausência de controle por perfil.
K27: 8 | L27: Armazenamento de credenciais em texto simples. | S27: Credenciais são armazenadas sem criptografia, facilitando comprometimento.
B29: Ativo | D29: Ameaças | I29: Controle existente | K29: Nr. | L29: Vulnerabilidades Encontradas | S29: Justificativa/Evidências
A30: ='LISTA AMEACAS'!A22 -> At 02 | B30: ='LISTA AMEACAS'!B22 -> Plataforma de monitoramento SOC 24/7 | D30: ='LISTA AMEACAS'!E22 -> Perda de inovação por acesso indevido | G30: Controle | I30: ='CONTROLES EXIST'!J26 -> Planejado | K30: 1 | L30: Documentos técnicos e projetos podem ser acessados sem restrições adequadas. | S30: Não há sistema de rastreamento de acessos que registre todas as interações com documentos.
K31: 2 | L31: Sistemas desatualizados. | S31: A plataforma utiliza versões antigas sem atualizações frequentes.
G32: Controle | I32: ='CONTROLES EXIST'!J27 -> Planejado | K32: 3 | L32: Dependência de tecnologias obsoletas. | S32: Ferramentas utilizadas não acompanham padrões atuais de mercado.
K33: 4 | L33: Falta de capacitação da equipe. | S33: Equipe não recebe treinamentos periódicos em novas tecnologias.
D34: ='LISTA AMEACAS'!I22 -> Interferência na produção de novos materiais | G34: Controle | I34: ='CONTROLES EXIST'!J28 -> Existente | K34: 5 | L34: Acesso indevido à plataforma. | S34: Falta de mecanismos de controle que garantam que apenas usuários autorizados possam modificar materiais de pesquisa.
G35: Controle | K35: 6 | L35: Configuração inadequada dos sensores. | S35: Sensores não detectam ameaças por configuração incorreta.
G36: Controle | I36: ='CONTROLES EXIST'!J29 -> Planejado | K36: 7 | L36: Alertas não tratados adequadamente. | S36: Eventos críticos não são analisados em tempo hábil.
K37: 8 | L37: Falta de segregação de ambientes | S37: Ambientes de teste e produção utilizam os mesmos recursos e permissões.
B39: Ativo | D39: Ameaças | I39: Controle existente | K39: Nr. | L39: Vulnerabilidades Encontradas | S39: Justificativa/Evidências
A40: ='LISTA AMEACAS'!A23 -> At 03 | B40: ='LISTA AMEACAS'!B23 -> Ferramentas de análise de vulnerabilidades | D40: ='LISTA AMEACAS'!E23 -> Ataques cibernéticos | G40: Controle | I40: ='CONTROLES EXIST'!J32 -> Existente | K40: 1 | L40: Falta de proteção robusta contra ameaças externas, como hackers e malware. | S40: Empresas do setor já sofreram ataques que comprometeram dados financeiros e operacionais.
K41: 2 | L41: Ferramentas desatualizadas. | S41: Base de vulnerabilidades não é atualizada regularmente.
G42: Controle | I42: ='CONTROLES EXIST'!J33 -> Planejado | K42: 3 | L42: Execução sem autenticação forte. | S42: Acesso administrativo sem MFA.
K43: 4 | L43: Resultados armazenados sem proteção. | S43: Relatórios ficam acessíveis sem controle.
D44: ='LISTA AMEACAS'!I23 -> Interrupção de serviços críticos | G44: Controle | I44: ='CONTROLES EXIST'!J34 -> Planejado | K44: 5 | L44: Falhas nos servidores podem levar à indisponibilidade dos sistemas empresariais. | S44: Registros de incidentes mostram tempos de indisponibilidade que afetaram operações internas.
G45: Controle | K45: 6 | L45: Dependência de único servidor. | S45: Ferramenta roda em apenas um ambiente sem redundância.
G46: Controle | I46: ='CONTROLES EXIST'!J35 -> Planejado | K46: 7 | L46: Falta de redundância. | S46: Não há sistema de contingência.
K47: 8 | L47: Acesso administrativo compartilhado. | S47: Várias pessoas utilizam a mesma conta administrativa.
B49: Ativo | D49: Ameaças | I49: Controle existente | K49: Nr. | L49: Vulnerabilidades Encontradas | S49: Justificativa/Evidências
A50: ='LISTA AMEACAS'!A24 -> At 04 | B50: ='LISTA AMEACAS'!B24 -> Sistemas de backup e recuperação de dados | D50: ='LISTA AMEACAS'!E24 -> Roubo de informações | G50: Controle | I50: ='CONTROLES EXIST'!J38 -> Existente | K50: 1 | L50: Acesso não autorizado pode comprometer dados sensíveis dos clientes. | S50: Empresas do setor já sofreram vazamentos de dados, causando danos à reputação e penalidades legais.
K51: 2 | L51: Falta de logs de acesso. | S51: Não há rastreamento de quem acessa os backups.
G52: Controle | I52: ='CONTROLES EXIST'!J39 -> Planejado | K52: 3 | L52: Armazenamento inadequado. | S52: Backups ficam em locais sem proteção adequada.
K53: 4 | L53: Acesso amplo aos backups. | S53: Vários usuários possuem acesso sem necessidade.
D54: ='LISTA AMEACAS'!I24 -> Uso indevido por terceiros | G54: Controle | I54: ='CONTROLES EXIST'!J40 -> Planejado | K54: 5 | L54: Parceiros ou funcionários podem acessar e utilizar dados de clientes sem autorização adequada. | S54: Não há um sistema claro de rastreamento de uso de dados por terceiros.
G55: Controle | K55: 6 | L55: Ausência de trilhas de auditoria sobre restaurações e consultas. | S55: O sistema não registra quem acessou, restaurou ou fez download de backups, impossibilitando identificar uso indevido.
G56: Controle | I56: ='CONTROLES EXIST'!J41 -> Planejado | K56: 7 | L56: Ausência de mecanismos eficazes de autenticação forte (MFA). | S56: O acesso aos sistemas ocorre apenas por login e senha, sem autenticação multifator, aumentando significativamente o risco de comprometimento por credenciais vazadas ou ataques de força bruta.
K57: 8 | L57: Falta de políticas formais de uso e proteção da informação. | S57: Não existem diretrizes claras e formalizadas sobre o uso, compartilhamento e proteção dos dados, o que aumenta o risco de exposição indevida por usuários internos ou terceiros com acesso ao ambiente.
B59: Ativo | D59: Ameaças | I59: Controle existente | K59: Nr. | L59: Vulnerabilidades Encontradas | S59: Justificativa/Evidências
A60: ='LISTA AMEACAS'!A25 -> At 05 | B60: ='LISTA AMEACAS'!B25 -> Código-fonte dos sistemas desenvolvidos | D60: ='LISTA AMEACAS'!E25 -> Falhas operacionais | G60: Controle | I60: ='CONTROLES EXIST'!J44 -> Existente | K60: 1 | L60: Erros mecânicos ou falhas humanas podem interromper o fluxo produtivo. | S60: Registros internos mostram tempos de inatividade devido a falhas técnicas.
K61: 2 | L61: Ausência de revisão de código (code review). | S61: Não há processo formal de revisão, o que permite que erros lógicos e práticas inseguras sejam incorporadas ao código sem detecção prévia.
G62: Controle | I62: ='CONTROLES EXIST'!J45 -> Planejado | K62: 3 | L62: Falta de padrões de desenvolvimento. | S62: A equipe utiliza estilos e práticas distintas, dificultando manutenção, aumentando risco de bugs e reduzindo confiabilidade operacional.
K63: 4 | L63: Falta de testes automatizados. | S63: A ausência de testes unitários e integrados impede que problemas sejam identificados antes da implantação.
D64: ='LISTA AMEACAS'!I25 -> Sabotagem industrial | G64: Controle | I64: ='CONTROLES EXIST'!J46 -> Planejado | K64: 5 | L64: Possibilidade de funcionários ou terceiros manipularem equipamentos ou processos de produção. | S64: Histórico do setor inclui casos de sabotagem que resultaram em prejuízos financeiros e perda de clientes.
G65: Controle | K65: 6 | L65: Exposição de credenciais dentro do código. | S65: Chaves de API, tokens ou senhas aparecem hardcoded, podendo ser capturados e usados indevidamente por terceiros mal-intencionados.
G66: Controle | I66: ='CONTROLES EXIST'!J47 -> Planejado | K66: 7 | L66: Repositório com acesso permissivo. | S66: Repositórios não implementam controle de acesso granular, permitindo acesso amplo a usuários que não necessitam.
K67: 8 | L67: Histórico de commits não auditado. | S67: Não há verificação de autoria e propósito das alterações, dificultando a descoberta de modificações maliciosas.
B69: Ativo | D69: Ameaças | I69: Controle existente | K69: Nr. | L69: Vulnerabilidades Encontradas | S69: Justificativa/Evidências
A70: ='LISTA AMEACAS'!A26 -> At 06 | B70: ='LISTA AMEACAS'!B26 -> Ambientes de desenvolvimento (Dev/Test/Prod) | D70: ='LISTA AMEACAS'!E26 -> Interrupção na cadeia logística | G70: Controle | I70: ='CONTROLES EXIST'!J50 -> Planejado | K70: 1 | L70: Problemas com fornecedores podem atrasar ou interromper entregas essenciais. | S70: Histórico de falhas no setor revela impactos financeiros causados por interrupções logísticas.
K71: 2 | L71: Falta de segregação entre ambientes (DEV/TEST/PROD). | S71: Ambientes compartilham recursos, aumentando probabilidades de falha cruzada e indisponibilidade.
G72: Controle | I72: ='CONTROLES EXIST'!J51 -> Planejado | K72: 3 | L72: Ausência de redundância de servidores de desenvolvimento. | S72: Uma falha simples em infraestrutura pode paralisar toda a operação de desenvolvimento.
K73: 4 | L73: Falta de monitoramento do ambiente. | S73: Eventos críticos como queda de serviço ou saturação de recursos não são detectados proativamente.
D74: ='LISTA AMEACAS'!I26 -> Manipulação indevida de entregas | G74: Controle | I74: ='CONTROLES EXIST'!J52 -> Existente | K74: 5 | L74: Possibilidade de adulteração ou redirecionamento não autorizado de produtos. | S74: Casos no setor mostram prejuízos devido a entregas incorretas ou manipuladas indevidamente.
G75: Controle | K75: 6 | L75: Versionamento sem controle adequado. | S75: Branches criadas e mergeadas sem processo formal podem permitir inserção acidental ou maliciosa de código.
G76: Controle | I76: ='CONTROLES EXIST'!J53 -> Planejado | K76: 7 | L76: Uso de dados reais em testes. | S76: Exposição desnecessária de dados sensíveis em ambientes sem segurança reforçada.
K77: 8 | L77: Ausência de trilhas de auditoria. | S77: Alterações não são registradas, impedindo identificação de manipulações por usuários internos.
B79: Ativo | D79: Ameaças | I79: Controle existente | K79: Nr. | L79: Vulnerabilidades Encontradas | S79: Justificativa/Evidências
A80: ='LISTA AMEACAS'!A27 -> At 07 | B80: ='LISTA AMEACAS'!B27 -> Banco de dados de clientes corporativos | D80: ='LISTA AMEACAS'!E27 -> Fraudes financeiras | G80: Controle | I80: ='CONTROLES EXIST'!J56 -> Planejado | K80: 1 | L80: Possibilidade de manipulação indevida de transações financeiras. | S80: Casos do setor demonstram impactos financeiros graves causados por fraudes não detectadas a tempo.
K81: 2 | L81: Controle de acesso insuficiente. | S81: Perfis de acesso concedem privilégios além do necessário, permitindo manipulação de dados financeiros.
G82: Controle | I82: ='CONTROLES EXIST'!J57 -> Planejado | K82: 3 | L82: Ausência de segregação de contas privilegiadas. | S82: Administradores utilizam contas de alto privilégio para tarefas rotineiras, aumentando risco de abuso.
K83: 4 | L83: Falta de validação transacional. | S83: Processos não garantem integridade entre operações financeiras encadeadas.
D84: ='LISTA AMEACAS'!I27 -> Alteração não autorizada de registros | G84: Controle | I84: ='CONTROLES EXIST'!J58 -> Existente | K84: 5 | L84: Dados financeiros podem ser alterados indevidamente por usuários sem permissão adequada. | S84: Ausência de trilhas de auditoria detalhadas pode comprometer a confiabilidade das informações financeiras.
G85: Controle | K85: 6 | L85: Vulnerabilidade de SQL Injection. | S85: Aplicações que consultam o banco não tratam parâmetros de entrada de forma segura.
G86: Controle | I86: ='CONTROLES EXIST'!J59 -> Planejado | K86: 7 | L86: Falta de logs de integridade. | S86: Alterações em dados críticos não têm registros detalhados de origem e finalidade.
K87: 8 | L87: Contas de serviço com privilégios excessivos. | S87: Aplicações acessam o banco com permissões totais em vez de permissões mínimas.
B89: Ativo | D89: Ameaças | I89: Controle existente | K89: Nr. | L89: Vulnerabilidades Encontradas | S89: Justificativa/Evidências
A90: ='LISTA AMEACAS'!A28 -> At 08 | B90: ='LISTA AMEACAS'!B28 -> Logs e registros de segurança (SIEM) | D90: ='LISTA AMEACAS'!E28 -> Falta de conformidade | G90: Controle | I90: ='CONTROLES EXIST'!J62 -> Planejado | K90: 1 | L90: Falta de adesão às diretrizes de segurança estabelecidas pela empresa e normas externas, como ISO 27001. | S90: Registros internos indicam que nem todas as áreas seguem práticas padronizadas de segurança.
K91: 2 | L91: Ausência de integridade dos registros. | S91: Logs podem ser alterados manualmente sem gerar alertas.
G92: Controle | I92: ='CONTROLES EXIST'!J63 -> Planejado | K92: 3 | L92: Falta de retenção mínima exigida. | S92: Período de armazenamento não cumpre normas internas ou legais.
K93: 4 | L93: Inconsistência nas fontes de log. | S93: Sistemas distintos enviam informações com formatação e padrão diferentes, dificultando correlação.
D94: ='LISTA AMEACAS'!I28 -> Desrespeito às normas de segurança | G94: Controle | I94: ='CONTROLES EXIST'!J64 -> Planejado | K94: 5 | L94: Possibilidade de funcionários ignorarem ou não aplicarem corretamente as políticas de segurança. | S94: Registros indicam que falhas humanas foram responsáveis por incidentes de segurança.
G95: Controle | K95: 6 | L95: Falta de controle de acesso aos logs. | S95: Qualquer usuário técnico consegue acessar registros sem justificativa formal.
G96: Controle | I96: ='CONTROLES EXIST'!J65 -> Planejado | K96: 7 | L96: Ausência de SIEM consolidado. | S96: Logs estão dispersos em vários sistemas sem centralização.
K97: 8 | L97: Armazenamento inadequado. | S97: Servidores de log operam sem redundância, aumentando risco de perda de evidências.
B99: Ativo | D99: Ameaças | I99: Controle existente | K99: Nr. | L99: Vulnerabilidades Encontradas | S99: Justificativa/Evidências
A100: ='LISTA AMEACAS'!A29 -> At 09 | B100: ='LISTA AMEACAS'!B29 -> Ferramentas de pentest (internas e licenciadas) | D100: ='LISTA AMEACAS'!E29 -> Vazamento de dados pessoais | G100: Controle | I100: Existe | K100: 1 | L100: Exposição de dados sensíveis dos funcionários por acessos não autorizados. | S100: Regulamentações como LGPD exigem proteção rigorosa para dados pessoais.
K101: 2 | L101: Armazenamento de resultados em locais públicos. | S101: Relatórios sensíveis ficam acessíveis a terceiros internos.
G102: Controle | I102: ='CONTROLES EXIST'!J69 -> Planejado | K102: 3 | L102: Logs de execução não protegidos. | S102: Informações capturadas durante o teste ficam registradas sem proteção adequada
K103: 4 | L103: Transporte inseguro dos relatórios. | S103: Relatórios são encaminhados por e-mail comum, sem criptografia.
D104: ='LISTA AMEACAS'!I29 -> Uso indevido de informações de colaboradores | G104: Controle | I104: ='CONTROLES EXIST'!J70 -> Planejado | K104: 5 | L104: Dados de funcionários podem ser acessados e utilizados sem consentimento. | S104: Regulamentações exigem transparência e controle sobre o uso de dados pessoais.
G105: Controle | K105: 6 | L105: Execução sem autorização formal. | S105: Ferramentas podem ser utilizadas por usuários sem aprovação, gerando riscos de interrupção indevida.
G106: Controle | I106: ='CONTROLES EXIST'!J71 -> Planejado | K106: 7 | L106: Ferramentas instaladas em máquinas pessoais. | S106: Ambiente fora do controle corporativo aumenta risco de uso contra a própria empresa.
K107: 8 | L107: Falta de segregação de perfis de pentest. | S107: Todos os analistas têm acesso a funcionalidades ofensivas sem restrição.
B109: Ativo | D109: Ameaças | I109: Controle existente | K109: Nr. | L109: Vulnerabilidades Encontradas | S109: Justificativa/Evidências
A110: ='LISTA AMEACAS'!A30 -> At 10 | B110: ='LISTA AMEACAS'!B30 -> Credenciais de acesso (senhas, tokens, chaves API) | D110: ='LISTA AMEACAS'!E30 -> Ataques de phishing | G110: Controle | I110: ='CONTROLES EXIST'!J74 -> Existente | K110: 1 | L110: Funcionários podem ser induzidos a compartilhar credenciais por e-mails fraudulentos. | S110: Setores que lidam com dados sensíveis são alvos frequentes de phishing.
K111: 2 | L111: Falta de treinamento dos usuários. | S111: Colaboradores não recebem orientações periódicas sobre golpes.
G112: Controle | I112: ='CONTROLES EXIST'!J75 -> Planejado | K112: 3 | L112: E-mail sem filtro de segurança. | S112: Links maliciosos chegam diretamente ao usuário final.
K113: 4 | L113: Falta de política formal de credenciais. | S113: Não há normas claras sobre criação, troca e uso seguro das senhas.
D114: ='LISTA AMEACAS'!I30 -> Roubo de credenciais | G114: Controle | I114: ='CONTROLES EXIST'!J76 -> Planejado | K114: 5 | L114: Senhas fracas ou reutilizadas podem ser comprometidas por invasores. | S114: Ataques recentes no setor exploraram credenciais para acesso indevido.
G115: Controle | K115: 6 | L115: Senhas fracas ou padrão. | S115: Credenciais não seguem política de complexidade, facilitando adivinhação.
G116: Controle | I116: ='CONTROLES EXIST'!J77 -> Planejado | K116: 7 | L116: Reutilização de senhas. | S116: Usuários utilizam a mesma senha em vários sistemas internos.
K117: 8 | L117: Armazenamento de senhas em texto simples. | S117: Anotações de senhas aparecem em arquivos ou aplicativos sem proteção.
B119: Ativo | D119: Ameaças | I119: Controle existente | K119: Nr. | L119: Vulnerabilidades Encontradas | S119: Justificativa/Evidências
A120: ='LISTA AMEACAS'!A31 -> At 11 | B120: ='LISTA AMEACAS'!B31 -> Infraestrutura de rede (firewalls, switches, VPN) | D120: ='LISTA AMEACAS'!E31 -> Falha na infraestrutura | G120: Controle | I120: ='CONTROLES EXIST'!J80 -> Existente | K120: 1 | L120: Problemas técnicos podem causar indisponibilidade dos sistemas. | S120: Empresas que não investem em infraestrutura robusta sofrem com paralisações.
K121: 2 | L121: Falta de segmentação de rede. | S121: A rede opera em um único segmento, permitindo que falhas ou ataques em um ponto afetem todo o ambiente.
G122: Controle | I122: ='CONTROLES EXIST'!J81 -> Planejado | K122: 3 | L122: Equipamentos sem redundância. | S122: Switches, roteadores e firewalls críticos não possuem dispositivos de backup, aumentando o impacto de falhas físicas.
K123: 4 | L123: Firmware desatualizado. | S123: Equipamentos de rede operam com versões antigas de firmware sujeitas a bugs e problemas de estabilidade.
D124: ='LISTA AMEACAS'!I31 -> Ataques cibernéticos e invasões | G124: Controle | I124: ='CONTROLES EXIST'!J82 -> Existente | K124: 5 | L124: Sistemas sem proteção adequada podem ser alvo de hackers. | S124: Casos recentes mostraram prejuízos financeiros por ataques cibernéticos.
G125: Controle | K125: 6 | L125: VPN sem autenticação forte. | S125: Acesso remoto é permitido com credenciais simples, sem MFA ou certificados.
G126: Controle | I126: ='CONTROLES EXIST'!J83 -> Planejado | K126: 7 | L126: Portas abertas sem necessidade. | S126: Serviços desnecessários permanecem acessíveis externamente.
...

Sheet CONSEQUENCIAS
A1: Identificação das Consequências das Vulnerabilidades Levantadas
J11: 2.1 Defina o Contexto
B19: Ativo | D19: Ameaças | I19: Controle existente | L19: Nr. | M19: Vulnerabilidades Encontradas | P19: Consequências | T19: Justificativa/Evidências | AC19: Defina uma consequência:
A20: ='LISTA AMEACAS'!A21 -> At 01 | B20: ='LISTA AMEACAS'!B21 -> Infraestrutura de servidores em nuvem | D20: ='LISTA AMEACAS'!E21 -> Vazamento de informações | G20: Controle | I20: ='CONTROLES EXIST'!J20 -> Planejado | L20: 1 | M20: =VULNERABILIDADES!L20 -> Falta de classificação da informação | P20: Perda de Autenticidade | T20: A ausência de classificação adequada dos dados pode levar ao tratamento indevido de informações sensíveis, resultando em exposição não autorizada, vazamentos acidentais e utilização inadequada dos documentos, comprometendo a confidencialidade e a integridade das informações institucionais. | AC20: Perda de Confidencialidade
L21: 2 | M21: =VULNERABILIDADES!L21 -> Dados armazenados sem criptografia. | P21: Perda de Integridade | T21: A falta de criptografia possibilita que qualquer acesso não autorizado resulte na leitura integral dos dados, aumentando o risco de vazamento de informações sensíveis, comprometimento da privacidade, incidentes de segurança e danos institucionais decorrentes da exposição de conteúdo confidencial. | AC21: Perda de Integridade
G22: Controle | I22: ='CONTROLES EXIST'!J21 -> Planejado | L22: 3 | M22: =VULNERABILIDADES!L22 -> Armazenamento inseguro | P22: Perda de confidencialidade | T22: O armazenamento inadequado permite que usuários sem autorização acessem, alterem ou excluam informações, causando risco de perda de dados, manipulação indevida e exposição de conteúdo sensível, comprometendo a integridade e a confidencialidade das informações institucionais. | AC22: Perda de Disponibilidade
L23: 4 | M23: =VULNERABILIDADES!L23 -> Falta de monitoramento de acesso. | P23: Perda de Autenticidade | T23: Impossibilidade de rastrear e identificar ações realizadas sobre os dados armazenados, dificultando a detecção de acessos não autorizados e comprometendo a resposta a incidentes de segurança, além de aumentar o risco de vazamento ou manipulação indevida das informações sem responsabilização dos autores. | AC23: Perda de Autenticidade
D24: ='LISTA AMEACAS'!I21 -> Roubo de dados por concorrentes | G24: Controle | I24: ='CONTROLES EXIST'!J22 -> Planejado | L24: 5 | M24: =VULNERABILIDADES!L24 -> Falta de backup adequado | P24: Perda de Disponibilidade | T24: Risco de indisponibilidade ou perda definitiva de dados em caso de falhas, ataques ou corrupção de arquivos, uma vez que a ausência de testes de restauração impede a garantia de que os backups são realmente recuperáveis, podendo comprometer a continuidade das operações e a recuperação dos sistemas dentro do tempo necessário. | AC24: Prejuizo financeiro por retrabalho
L25: 6 | M25: =VULNERABILIDADES!L25 -> Logs de auditoria incompletos. | P25: Perda de Autenticidade | T25: Comprometimento da capacidade de auditoria e investigação de incidentes, pois a ausência de registros completos impede a reconstrução precisa das ações realizadas em sistemas críticos, dificultando a identificação de responsáveis por falhas, acessos indevidos ou alterações não autorizadas, além de enfraquecer o controle interno e a conformidade com normas de segurança da informação. | AC25: Afeta imagem e reputação
G26: Controle | I26: ='CONTROLES EXIST'!J23 -> Planejado | L26: 7 | M26: =VULNERABILIDADES!L26 -> Acesso indevido | P26: Perda de Integridade | T26: Aumento significativo do risco de acesso não autorizado a dados e sistemas críticos, permitindo que usuários executem funções além de suas responsabilidades, o que pode levar a alterações indevidas, vazamento de informações sensíveis e comprometimento da integridade e confidencialidade dos dados, além de dificultar a responsabilização em caso de incidentes de segurança.
L27: 8 | M27: =VULNERABILIDADES!L27 -> Armazenamento de credenciais em texto simples. | P27: Perda de confidencialidade | T27: Possibilidade de exposição direta de senhas e credenciais em caso de acesso indevido aos sistemas ou bases de dados, facilitando o comprometimento de contas e sistemas.
B29: Ativo | D29: Ameaças | I29: Controle existente | L29: Nr. | M29: Vulnerabilidades Encontradas | P29: Consequências | T29: Justificativa/Evidências
A30: ='LISTA AMEACAS'!A22 -> At 02 | B30: ='LISTA AMEACAS'!B22 -> Plataforma de monitoramento SOC 24/7 | D30: ='LISTA AMEACAS'!E22 -> Perda de inovação por acesso indevido | G30: Controle | I30: Insuficiente | L30: 1 | M30: Documentos técnicos e projetos podem ser acessados sem restrições adequadas. | P30: Perda de confidencialidade | T30: Exposição de informações técnicas e estratégicas a usuários não autorizados, aumentando o risco de cópia, uso indevido ou vazamento de dados sensíveis, além de impossibilitar a identificação de quem acessou ou alterou os documentos
L31: 2 | M31: Sistemas desatualizados. | P31: Perda de Disponibilidade | T31: Aumento da exposição a falhas conhecidas e vulnerabilidades já corrigidas em versões mais recentes, facilitando ataques, invasões e exploração de brechas de segurança, podendo causar indisponibilidade dos sistemas ou comprometimento de dados
G32: Controle | I32: Insuficiente | L32: 3 | M32: Dependência de tecnologias obsoletas. | P32: Perda de Disponibilidade | T32: Limitação na manutenção, atualização e integração dos sistemas, aumentando a probabilidade de falhas operacionais e dificuldades na correção de vulnerabilidades, o que pode levar à interrupção dos serviços e falhas no funcionamento das aplicações
L33: 4 | M33: Falta de capacitação da equipe. | P33: Prejuizo financeiro por retrabalho | T33: Maior probabilidade de erros operacionais, uso incorreto de sistemas e falhas na aplicação de boas práticas de segurança, o que pode gerar retrabalho, atrasos nas atividades e redução da eficiência dos processos
D34: ='LISTA AMEACAS'!I22 -> Interferência na produção de novos materiais | G34: Controle | I34: Insuficiente | L34: 5 | M34: Acesso indevido à plataforma. | P34: Perda de Integridade | T34: Possibilidade de alterações não autorizadas nos materiais de pesquisa durante sua produção, comprometendo a qualidade, a consistência e a confiabilidade dos conteúdos desenvolvidos, o que pode gerar retrabalho, atrasos nos projetos e perda de credibilidade das informações
L35: 6 | M35: Configuração inadequada dos sensores. | P35: Perda de Disponibilidade | T35: Falha na detecção de eventos ou atividades suspeitas devido à configuração incorreta dos sensores, permitindo que ameaças não sejam identificadas em tempo hábil e impactem a operação dos sistemas,
G36: Controle | I36: Existente, porém desatualizado | L36: 7 | M36: Alertas não tratados adequadamente. | P36: Perda de Disponibilidade | T36: traso na identificação e resposta a incidentes de segurança, permitindo que ameaças evoluam e causem impactos maiores nos sistemas e operações, comprometendo a continuidade dos serviços.
L37: 8 | M37: Falta de segregação de ambientes | P37: Perda de Disponibilidade | T37: Possibilidade de alterações ou falhas em ambiente de teste impactarem diretamente o ambiente de produção, causando interrupções nos serviços e instabilidade dos sistemas.
B39: Ativo | D39: Ameaças | I39: Controle existente | L39: Nr. | M39: Vulnerabilidades Encontradas | P39: Consequências | T39: Justificativa/Evidências
A40: ='LISTA AMEACAS'!A23 -> At 03 | B40: ='LISTA AMEACAS'!B23 -> Ferramentas de análise de vulnerabilidades | D40: ='LISTA AMEACAS'!E23 -> Ataques cibernéticos | G40: Controle | I40: ='CONTROLES EXIST'!J32 -> Existente | L40: 1 | M40: =VULNERABILIDADES!L40 -> Falta de proteção robusta contra ameaças externas, como hackers e malware. | P40: Perda de confidencialidade | T40: Possibilidade de invasões aos sistemas com acesso não autorizado a dados financeiros e operacionais, além de interrupção de serviços e vazamento de informações sensíveis.
L41: 2 | M41: =VULNERABILIDADES!L41 -> Ferramentas desatualizadas. | P41: Perda de Disponibilidade | T41: Incapacidade de identificar novas ameaças e falhas conhecidas, permitindo que atacantes explorem vulnerabilidades já corrigidas em atualizações recentes, aumentando o risco de invasão e comprometimento dos sistemas
G42: Controle | I42: ='CONTROLES EXIST'!J33 -> Planejado | L42: 3 | M42: =VULNERABILIDADES!L42 -> Execução sem autenticação forte. | P42: Perda de confidencialidade | T42: Facilitação de invasões por meio de credenciais comprometidas, permitindo que atacantes assumam contas administrativas e executem ações críticas nos sistemas sem barreiras adicionais de segurança.
L43: 4 | M43: =VULNERABILIDADES!L43 -> Resultados armazenados sem proteção. | P43: Perda de confidencialidade | T43: Exposição de relatórios e informações sensíveis a usuários não autorizados ou atacantes, facilitando vazamento de dados estratégicos e operacionais
D44: ='LISTA AMEACAS'!I23 -> Interrupção de serviços críticos | G44: Controle | I44: ='CONTROLES EXIST'!J34 -> Planejado | L44: 5 | M44: =VULNERABILIDADES!L44 -> Falhas nos servidores podem levar à indisponibilidade dos sistemas empresariais. | P44: Perda de Disponibilidade | T44: Paralisação total ou parcial dos sistemas empresariais devido a falhas em servidores, impactando diretamente a continuidade das operações internas e causando atrasos em processos essenciais
L45: 6 | M45: =VULNERABILIDADES!L45 -> Dependência de único servidor. | P45: Perda de Disponibilidade | T45: Indisponibilidade total dos sistemas em caso de falha do servidor principal, pois não há ambiente redundante para continuidade das operações, causando paralisação dos serviços críticos
G46: Controle | I46: ='CONTROLES EXIST'!J35 -> Planejado | L46: 7 | M46: =VULNERABILIDADES!L46 -> Falta de redundância. | P46: Perda de Disponibilidade | T46: Impossibilidade de continuidade dos serviços em caso de falhas ou indisponibilidade do ambiente principal, já que não existe sistema de contingência para assumir as operações, causando paralisação das atividades essenciais
L47: 8 | M47: =VULNERABILIDADES!L47 -> Acesso administrativo compartilhado. | P47: Perda de Disponibilidade | T47: Dificuldade de rastrear ações realizadas no sistema e identificar a origem de alterações ou falhas, aumentando o risco de erros operacionais que podem causar indisponibilidade dos serviços críticos
B49: Ativo | D49: Ameaças | I49: Controle existente | L49: Nr. | M49: Vulnerabilidades Encontradas | P49: Consequências | T49: Justificativa/Evidências
A50: ='LISTA AMEACAS'!A24 -> At 04 | B50: ='LISTA AMEACAS'!B24 -> Sistemas de backup e recuperação de dados | D50: ='LISTA AMEACAS'!E24 -> Roubo de informações | G50: Controle | I50: ='CONTROLES EXIST'!J38 -> Existente | L50: 1 | M50: =VULNERABILIDADES!L50 -> Acesso não autorizado pode comprometer dados sensíveis dos clientes. | P50: Perda de confidencialidade | T50: Exposição e vazamento de dados sensíveis de clientes por acessos não autorizados, comprometendo a confidencialidade das informações e podendo gerar impactos legais e reputacionais para a organização
L51: 2 | M51: =VULNERABILIDADES!L51 -> Falta de logs de acesso. | P51: Perda de confidencialidade | T51: Impossibilidade de identificar quem acessou ou manipulou os backups, facilitando acessos indevidos e possíveis vazamentos de dados sem detecção ou responsabilização
G52: Controle | I52: ='CONTROLES EXIST'!J39 -> Planejado | L52: 3 | M52: =VULNERABILIDADES!L52 -> Armazenamento inadequado. | P52: Perda de confidencialidade | T52: Exposição dos backups a acessos não autorizados ou extração indevida de dados sensíveis devido à falta de proteção no armazenamento, facilitando vazamentos de informações críticas
L53: 4 | M53: =VULNERABILIDADES!L53 -> Acesso amplo aos backups. | P53: Perda de confidencialidade | T53: Aumento do risco de acesso indevido e extração de dados sensíveis armazenados em backups por usuários não autorizados ou desnecessariamente privilegiados, facilitando vazamentos de informações críticas
D54: ='LISTA AMEACAS'!I24 -> Uso indevido por terceiros | G54: Controle | I54: ='CONTROLES EXIST'!J40 -> Planejado | L54: 5 | M54: =VULNERABILIDADES!L54 -> Parceiros ou funcionários podem acessar e utilizar dados de clientes sem autorização adequada. | P54: Perda de confidencialidade | T54: Possibilidade de utilização indevida de dados de clientes por terceiros sem autorização ou controle, dificultando a identificação de quem acessou e como os dados foram utilizados
L55: 6 | M55: =VULNERABILIDADES!L55 -> Ausência de trilhas de auditoria sobre restaurações e consultas. | P55: Perda de confidencialidade | T55: Impossibilidade de rastrear ações realizadas sobre os backups, como acessos, restaurações ou downloads, dificultando a detecção de uso indevido por terceiros e comprometendo o controle sobre dados sensíveis
G56: Controle | I56: ='CONTROLES EXIST'!J41 -> Planejado | L56: 7 | M56: =VULNERABILIDADES!L56 -> Ausência de mecanismos eficazes de autenticação forte (MFA). | P56: Perda de confidencialidade | T56: Facilitação do acesso não autorizado aos sistemas por terceiros mediante uso de credenciais comprometidas ou ataques de força bruta, permitindo a utilização indevida de dados e recursos sem camadas adicionais de verificação
L57: 8 | M57: =VULNERABILIDADES!L57 -> Falta de políticas formais de uso e proteção da informação. | P57: Perda de confidencialidade | T57: Uso inadequado ou não autorizado de informações sensíveis por falta de regras e controle definidos, facilitando o compartilhamento indevido de dados por usuários internos ou terceiros com acesso ao ambiente
B59: Ativo | D59: Ameaças | I59: Controle existente | L59: Nr. | M59: Vulnerabilidades Encontradas | P59: Consequências | T59: Justificativa/Evidências
A60: ='LISTA AMEACAS'!A25 -> At 05 | B60: ='LISTA AMEACAS'!B25 -> Código-fonte dos sistemas desenvolvidos | D60: ='LISTA AMEACAS'!E25 -> Falhas operacionais | G60: Controle | I60: ='CONTROLES EXIST'!J44 -> Existente | L60: 1 | M60: =VULNERABILIDADES!L60 -> Erros mecânicos ou falhas humanas podem interromper o fluxo produtivo. | P60: Perda de Disponibilidade | T60: Interrupção do fluxo produtivo e indisponibilidade dos sistemas devido a erros humanos ou falhas técnicas, impactando diretamente a continuidade das operações e gerando períodos de inatividade nos serviços
L61: 2 | M61: =VULNERABILIDADES!L61 -> Ausência de revisão de código (code review). | P61: Perda de Disponibilidade | T61: Inserção de erros lógicos e falhas no código sem detecção prévia, o que pode gerar mau funcionamento dos sistemas, interrupções nos processos e aumento de falhas operacionais durante a execução das aplicações.
G62: Controle | I62: ='CONTROLES EXIST'!J45 -> Planejado | L62: 3 | M62: =VULNERABILIDADES!L62 -> Falta de padrões de desenvolvimento. | P62: Perda de Disponibilidade | T62: Aumento da ocorrência de erros e inconsistências no sistema devido à falta de padronização no desenvolvimento, dificultando a manutenção e correção de falhas, o que pode gerar instabilidade e interrupções nos serviços.
L63: 4 | M63: =VULNERABILIDADES!L63 -> Falta de testes automatizados. | P63: Perda de Disponibilidade | T63: Implantação de código com defeitos não detectados previamente, aumentando a probabilidade de falhas em produção, instabilidade do sistema e interrupções nos serviços durante a operação
D64: ='LISTA AMEACAS'!I25 -> Sabotagem industrial | G64: Controle | I64: ='CONTROLES EXIST'!J46 -> Planejado | L64: 5 | M64: =VULNERABILIDADES!L64 -> Possibilidade de funcionários ou terceiros manipularem equipamentos ou processos de produção. | P64: Prejuizo financeiro por retrabalho | T64: Manipulação indevida de equipamentos ou processos produtivos por funcionários ou terceiros, podendo gerar falhas operacionais, danos a sistemas e interrupção da produção, além de prejuízos financeiros e impacto na confiança dos clientes
L65: 6 | M65: =VULNERABILIDADES!L65 -> Exposição de credenciais dentro do código. | P65: Perda de confidencialidade | T65: Comprometimento de sistemas e serviços por uso indevido de credenciais expostas no código, permitindo acesso não autorizado a recursos críticos e manipulação de processos industriais
G66: Controle | I66: ='CONTROLES EXIST'!J47 -> Planejado | L66: 7 | M66: =VULNERABILIDADES!L66 -> Repositório com acesso permissivo. | P66: Perda de Integridade | T66: Possibilidade de alterações indevidas no código-fonte ou exclusão de componentes críticos por usuários não autorizados ou sem necessidade de acesso, podendo comprometer o funcionamento dos sistemas e processos industriais
L67: 8 | M67: =VULNERABILIDADES!L67 -> Histórico de commits não auditado. | P67: Perda de Integridade | T67: Dificuldade de identificar alterações maliciosas ou não autorizadas no código-fonte, permitindo que modificações indevidas passem despercebidas e comprometam o funcionamento dos sistemas e processos industriais
B69: Ativo | D69: Ameaças | I69: Controle existente | L69: Nr. | M69: Vulnerabilidades Encontradas | P69: Consequências | T69: Justificativa/Evidências
A70: ='LISTA AMEACAS'!A26 -> At 06 | B70: ='LISTA AMEACAS'!B26 -> Ambientes de desenvolvimento (Dev/Test/Prod) | D70: ='LISTA AMEACAS'!E26 -> Interrupção na cadeia logística | G70: Controle | I70: ='CONTROLES EXIST'!J50 -> Planejado | L70: 1 | M70: =VULNERABILIDADES!L70 -> Problemas com fornecedores podem atrasar ou interromper entregas essenciais. | P70: Perda de Disponibilidade | T70: Falhas em hardware causam indisponibilidade — evidência: ausência de redundância.
L71: 2 | M71: =VULNERABILIDADES!L71 -> Falta de segregação entre ambientes (DEV/TEST/PROD). | P71: Interrupção de serviços | T71: Paradas afetam sistemas — evidência: falta de monitoramento.
G72: Controle | I72: ='CONTROLES EXIST'!J51 -> Planejado | L72: 3 | M72: =VULNERABILIDADES!L72 -> Ausência de redundância de servidores de desenvolvimento. | P72: Impacto operacional | T72: Operação comprometida — evidência: sistemas críticos dependentes.
L73: 4 | M73: =VULNERABILIDADES!L73 -> Falta de monitoramento do ambiente. | P73: Atrasos em processos internos | T73: Processos atrasam — evidência: ausência de plano de contingência.
D74: ='LISTA AMEACAS'!I26 -> Manipulação indevida de entregas | G74: Controle | I74: ='CONTROLES EXIST'!J52 -> Existente | L74: 5 | M74: =VULNERABILIDADES!L74 -> Possibilidade de adulteração ou redirecionamento não autorizado de produtos. | P74: Insatisfação de usuários | T74: Usuários impactados — evidência: registros de indisponibilidade.
L75: 6 | M75: =VULNERABILIDADES!L75 -> Versionamento sem controle adequado. | P75: Perda de produtividade | T75: Equipe ociosa — evidência: dependência total do sistema.
G76: Controle | I76: ='CONTROLES EXIST'!J53 -> Planejado | L76: 7 | M76: =VULNERABILIDADES!L76 -> Uso de dados reais em testes. | P76: Impacto financeiro | T76: Custos elevados — evidência: manutenção corretiva frequente.
L77: 8 | M77: =VULNERABILIDADES!L77 -> Ausência de trilhas de auditoria. | P77: Dependência de suporte emergencial | T77: Suporte emergencial necessário-evidência falta de prevenção.
B79: Ativo | D79: Ameaças | I79: Controle existente | L79: Nr. | M79: Vulnerabilidades Encontradas | P79: Consequências | T79: Justificativa/Evidências
A80: ='LISTA AMEACAS'!A27 -> At 07 | B80: ='LISTA AMEACAS'!B27 -> Banco de dados de clientes corporativos | D80: ='LISTA AMEACAS'!E27 -> Fraudes financeiras | G80: Controle | I80: ='CONTROLES EXIST'!J56 -> Planejado | L80: 1 | M80: =VULNERABILIDADES!L80 -> Possibilidade de manipulação indevida de transações financeiras. | P80: Perda de confidenciabilidade | T80: Acesso indevido — evidência: falta de controle de acesso.
L81: 2 | M81: =VULNERABILIDADES!L81 -> Controle de acesso insuficiente. | P81: Vazamento dec dados | T81: Vazamento — evidência: ausência de criptografia.
G82: Controle | I82: ='CONTROLES EXIST'!J57 -> Planejado | L82: 3 | M82: =VULNERABILIDADES!L82 -> Ausência de segregação de contas privilegiadas. | P82: Impacto legal ( LGPD) | T82: Não conformidade LGPD — evidência: falta de políticas.
L83: 4 | M83: =VULNERABILIDADES!L83 -> Falta de validação transacional. | P83: Danos a reputação | T83: Imagem afetada — evidência: histórico de incidentes.
D84: ='LISTA AMEACAS'!I27 -> Alteração não autorizada de registros | G84: Controle | I84: ='CONTROLES EXIST'!J58 -> Existente | L84: 5 | M84: =VULNERABILIDADES!L84 -> Dados financeiros podem ser alterados indevidamente por usuários sem permissão adequada. | P84: Perda da confiança | T84: Clientes desconfiados — evidência: falhas de segurança.
L85: 6 | M85: =VULNERABILIDADES!L85 -> Vulnerabilidade de SQL Injection. | P85: Multas e penalidades | T85: Multas — evidência: descumprimento legal.
G86: Controle | I86: ='CONTROLES EXIST'!J59 -> Planejado | L86: 7 | M86: =VULNERABILIDADES!L86 -> Falta de logs de integridade. | P86: Uso indevido de dados | T86: Uso indevido — evidência: privilégios excessivos.
L87: 8 | M87: =VULNERABILIDADES!L87 -> Contas de serviço com privilégios excessivos. | P87: Exposição dce informações | T87: Dados expostos — evidência: falta de classificação.
B89: Ativo | D89: Ameaças | I89: Controle existente | L89: Nr. | M89: Vulnerabilidades Encontradas | P89: Consequencias | T89: Justificativa/Evidências
A90: ='LISTA AMEACAS'!A28 -> At 08 | B90: ='LISTA AMEACAS'!B28 -> Logs e registros de segurança (SIEM) | D90: ='LISTA AMEACAS'!E28 -> Falta de conformidade | G90: Controle | I90: ='CONTROLES EXIST'!J62 -> Planejado | L90: 1 | M90: =VULNERABILIDADES!L90 -> Falta de adesão às diretrizes de segurança estabelecidas pela empresa e normas externas, como ISO 27001. | P90: Perda de Integridade | T90: Dados expostos — evidência: falta de classificação.
L91: 2 | M91: =VULNERABILIDADES!L91 -> Ausência de integridade dos registros. | P91: Dados inconsistentes | T91: Dados divergentes entre sistemas — evidência: falta de integração e consistência.
G92: Controle | I92: ='CONTROLES EXIST'!J63 -> Planejado | L92: 3 | M92: =VULNERABILIDADES!L92 -> Falta de retenção mínima exigida. | P92: Retrabalho operacional | T92: Necessidade de correções manuais — evidência: alto índice de erros operacionais.
L93: 4 | M93: =VULNERABILIDADES!L93 -> Inconsistência nas fontes de log. | P93: Falhas em relatórios | T93: Relatórios inconsistentes — evidência: base de dados não confiável.
D94: ='LISTA AMEACAS'!I28 -> Desrespeito às normas de segurança | G94: Controle | I94: ='CONTROLES EXIST'!J64 -> Planejado | L94: 5 | M94: =VULNERABILIDADES!L94 -> Possibilidade de funcionários ignorarem ou não aplicarem corretamente as políticas de segurança. | P94: Decisões incorretas | T94: Decisões baseadas em dados incorretos — evidência: ausência de governança de dados.
L95: 6 | M95: =VULNERABILIDADES!L95 -> Falta de controle de acesso aos logs. | P95: Atrasos em processos | T95: Processos atrasados — evidência: tempo gasto com ajustes e correções.
G96: Controle | I96: ='CONTROLES EXIST'!J65 -> Planejado | L96: 7 | M96: =VULNERABILIDADES!L96 -> Ausência de SIEM consolidado. | P96: arga de equipes | T96: Baixa qualidade da informação — evidência: inexistência de políticas de qualidade de dados.
L97: 8 | M97: =VULNERABILIDADES!L97 -> Armazenamento inadequado. | P97: Perda de confidencialidade | T97: Perda de confiança nos sistemas — evidência: histórico de inconsistências.
B99: Ativo | D99: Ameaças | I99: Controle existente | L99: Nr. | M99: Vulnerabilidades Encontradas | P99: Consequências | T99: Justificativa/Evidências
A100: ='LISTA AMEACAS'!A29 -> At 09 | B100: ='LISTA AMEACAS'!B29 -> Ferramentas de pentest (internas e licenciadas) | D100: ='LISTA AMEACAS'!E29 -> Vazamento de dados pessoais | G100: Controle | I100: ='CONTROLES EXIST'!J68 -> Planejado | L100: 1 | M100: =VULNERABILIDADES!L100 -> Exposição de dados sensíveis dos funcionários por acessos não autorizados. | P100: Interupção de serviço | T100: Ataques de negação de serviço , ausência de proteção contra DoS/DDoS.
L101: 2 | M101: =VULNERABILIDADES!L101 -> Armazenamento de resultados em locais públicos. | P101: Perda de Disponibilidade | T101: Ataques de negação de serviço, ausência de proteção contra DoS/DDoS.
G102: Controle | I102: ='CONTROLES EXIST'!J69 -> Planejado | L102: 3 | M102: =VULNERABILIDADES!L102 -> Logs de execução não protegidos. | P102: Impacto operacional | T102: Operação comprometida, dependência de sistemas críticos.
L103: 4 | M103: =VULNERABILIDADES!L103 -> Transporte inseguro dos relatórios. | P103: Insatisfação de usuários | T103: Usuários prejudicados ,registros de reclamações.
D104: ='LISTA AMEACAS'!I29 -> Uso indevido de informações de colaboradores | G104: Controle | I104: ='CONTROLES EXIST'!J70 -> Planejado | L104: 5 | M104: =VULNERABILIDADES!L104 -> Dados de funcionários podem ser acessados e utilizados sem consentimento. | P104: Perda de produtividade | T104: Paralisação de atividades, indisponibilidade frequente.
L105: 6 | M105: =VULNERABILIDADES!L105 -> Execução sem autorização formal. | P105: Impacto financeiro | T105: Custos com recuperação, ações corretivas emergenciais.
G106: Controle | I106: ='CONTROLES EXIST'!J71 -> Planejado | L106: 7 | M106: =VULNERABILIDADES!L106 -> Ferramentas instaladas em máquinas pessoais. | P106: Sobrecarga de equipe | T106: Equipe sobrecarregada , aumento de chamados técnicos.
L107: 8 | M107: =VULNERABILIDADES!L107 -> Falta de segregação de perfis de pentest. | P107: Queda de desempenho | T107: Desempenho degradado, infraestrutura limitada.
B109: Ativo | D109: Ameaças | I109: Controle existente | L109: Nr. | M109: Vulnerabilidades Encontradas | P109: Consequências | T109: Justificativa/Evidências
A110: ='LISTA AMEACAS'!A30 -> At 10 | B110: ='LISTA AMEACAS'!B30 -> Credenciais de acesso (senhas, tokens, chaves API) | D110: ='LISTA AMEACAS'!E30 -> Ataques de phishing | G110: Controle | I110: ='CONTROLES EXIST'!J74 -> Existente | L110: 1 | M110: =VULNERABILIDADES!L110 -> Funcionários podem ser induzidos a compartilhar credenciais por e-mails fraudulentos. | P110: Perda de confidencialidade | T110: Comunicação sem criptografia ,uso de protocolos inseguros.
L111: 2 | M111: =VULNERABILIDADES!L111 -> Falta de treinamento dos usuários. | P111: Vazamento de informções | T111: Dados interceptados , tráfego em texto claro.
G112: Controle | I112: ='CONTROLES EXIST'!J75 -> Planejado | L112: 3 | M112: =VULNERABILIDADES!L112 -> E-mail sem filtro de segurança. | P112: Danos a reputação | T112: Imagem institucional afetada ,incidentes de segurança.
L113: 4 | M113: =VULNERABILIDADES!L113 -> Falta de política formal de credenciais. | P113: Impacto legal | T113: Não conformidade com LGPD , ausência de proteção de dados.
D114: ='LISTA AMEACAS'!I30 -> Roubo de credenciais | G114: Controle | I114: ='CONTROLES EXIST'!J76 -> Planejado | L114: 5 | M114: =VULNERABILIDADES!L114 -> Senhas fracas ou reutilizadas podem ser comprometidas por invasores. | P114: Perda de confiaça | T114: Perda de credibilidade, falhas recorrentes.
L115: 6 | M115: =VULNERABILIDADES!L115 -> Senhas fracas ou padrão. | P115: Exposição de dados sensíveis | T115: Exposição de dados, ausência de controle de transmissão.
G116: Controle | I116: ='CONTROLES EXIST'!J77 -> Planejado | L116: 7 | M116: =VULNERABILIDADES!L116 -> Reutilização de senhas. | P116: Uso indevido da infolrmação | T116: Uso indevido, falta de controle de acesso.
L117: 8 | M117: =VULNERABILIDADES!L117 -> Armazenamento de senhas em texto simples. | P117: Impacto financeiro | T117: Custos com mitigação , necessidade de correção pós-incidente.
B119: Ativo | D119: Ameaças | I119: Controle existente | L119: Nr. | M119: Vulnerabilidades Encontradas | P119: Consequências | T119: Justificativa/Evidências
A120: ='LISTA AMEACAS'!A31 -> At 11 | B120: ='LISTA AMEACAS'!B31 -> Infraestrutura de rede (firewalls, switches, VPN) | D120: ='LISTA AMEACAS'!E31 -> Falha na infraestrutura | G120: Controle | I120: ='CONTROLES EXIST'!J80 -> Existente | L120: 1 | M120: =VULNERABILIDADES!L120 -> Problemas técnicos podem causar indisponibilidade dos sistemas. | P120: Perda de confidencialidade | T120: Falta de manutenção preventiva ,inexistência de cronograma.
L121: 2 | M121: =VULNERABILIDADES!L121 -> Falta de segmentação de rede. | P121: Parada operacional | T121: Sistemas apresentam falhas ,histórico de indisponibilidade
G122: Controle | I122: ='CONTROLES EXIST'!J81 -> Planejado | L122: 3 | M122: =VULNERABILIDADES!L122 -> Equipamentos sem redundância. | P122: Impacto finacenceiro | T122: Custos elevados ,manutenção corretiva frequente.
L123: 4 | M123: =VULNERABILIDADES!L123 -> Firmware desatualizado. | P123: Atraso em atividades | T123: Processos atrados ,paradas inesperadas.
D124: ='LISTA AMEACAS'!I31 -> Ataques cibernéticos e invasões | G124: Controle | I124: ='CONTROLES EXIST'!J82 -> Existente | L124: 5 | M124: =VULNERABILIDADES!L124 -> Sistemas sem proteção adequada podem ser alvo de hackers. | P124: Insatisfação dos usuários | T124: Usuários nimpactados ,registros de chamados
L125: 6 | M125: =VULNERABILIDADES!L125 -> VPN sem autenticação forte. | P125: Redução de produtividade | T125: Produtividade reduzida,tempo ocioso.
G126: Controle | I126: ='CONTROLES EXIST'!J83 -> Planejado | L126: 7 | M126: =VULNERABILIDADES!L126 -> Portas abertas sem necessidade. | P126: Dependência de suporte técnico | T126: Dependência externa ,necessidadede suporte externo.
...

Sheet SESSAO_5
A1: Gestão de Riscos de TI – NBR 27005
A3: Sessão 5
A6: OBJETIVO: Aplicar num exercício os conhecimentos adquiridos na sessão 5. Compreender e desenvolver um processo de avaliação QUALITATIVA de risco.
A10: Nas duas atividades que fazem parte desta sessão, serão vistos os conceitos apreendidos na sessão 5. | J10: Atividades – Sessão 5
J11: 5.1 Avaliação Qualitativa dos Ativos
A13: Lembre-se: estas atividades devem ser feitas na sequência e com o acompanhamento da norma 27005 | J13: 5.2 Avaliação Qualitativa Severidade das Consequencias
A16: Qualquer dúvida pergunte ao instrutor!!

Sheet CONS_AV_QUALIT_ATIVO
A1: Avaliação das Consequências - Relevância dos Ativos
B19: Ativo | D19: Ameaças | G19: Nr. | H19: Vulnerabilidades Encontradas | K19: Consequências | O19: Relevancia do Ativo para o Negócio | R19: Justificativa/Evidências
A20: ='LISTA AMEACAS'!A21 -> At 01 | B20: ='LISTA AMEACAS'!B21 -> Infraestrutura de servidores em nuvem | D20: ='LISTA AMEACAS'!E21 -> Vazamento de informações | G20: 1 | H20: =VULNERABILIDADES!L20 -> Falta de classificação da informação | K20: =CONSEQUENCIAS!P20 -> Perda de Autenticidade | O20: Crítico | R20: Como o ativo é crítico para continuidade e atendimento, a ausência de classificação permite tratamento inadequado de dados sensíveis, ampliando risco de vazamento com impacto direto em operação, clientes e conformidade.
G21: 2 | H21: =VULNERABILIDADES!L21 -> Dados armazenados sem criptografia. | K21: =CONSEQUENCIAS!P21 -> Perda de Integridade | R21: Em ativo crítico, dados sem criptografia podem ser lidos em caso de acesso indevido, comprometendo confidencialidade de informações essenciais ao negócio.
G22: 3 | H22: =VULNERABILIDADES!L22 -> Armazenamento inseguro | K22: =CONSEQUENCIAS!P22 -> Perda de confidencialidade | R22: A relevância crítica exige proteção forte; armazenamento inseguro aumenta exposição de conteúdo estratégico e pode interromper serviços por incidente de segurança.
G23: 4 | H23: =VULNERABILIDADES!L23 -> Falta de monitoramento de acesso. | K23: =CONSEQUENCIAS!P23 -> Perda de Autenticidade | R23: Sem rastreabilidade em ativo crítico, acessos anômalos podem passar despercebidos, elevando risco de fraude, vazamento e indisponibilidade operacional.
D24: ='LISTA AMEACAS'!I21 -> Roubo de dados por concorrentes | G24: 5 | H24: =VULNERABILIDADES!L24 -> Falta de backup adequado | K24: =CONSEQUENCIAS!P24 -> Perda de Disponibilidade | R24: Para ativo crítico, backup insuficiente reduz capacidade de recuperação após incidente e ameaça diretamente continuidade do negócio.
G25: 6 | H25: =VULNERABILIDADES!L25 -> Logs de auditoria incompletos. | K25: =CONSEQUENCIAS!P25 -> Perda de Autenticidade | R25: Sem evidências confiáveis em ativo crítico, investigação e resposta ficam limitadas, aumentando impacto financeiro e reputacional.
G26: 7 | H26: =VULNERABILIDADES!L26 -> Acesso indevido | K26: =CONSEQUENCIAS!P26 -> Perda de Integridade | R26: A relevância crítica torna qualquer acesso não autorizado um risco de alto impacto, com potencial de extração de dados estratégicos.
G27: 8 | H27: =VULNERABILIDADES!L27 -> Armazenamento de credenciais em texto simples. | K27: =CONSEQUENCIAS!P27 -> Perda de confidencialidade | R27: Em ativo crítico, credenciais expostas facilitam comprometimento total do ambiente e paralisação de serviços essenciais.
B29: Ativo | D29: Ameaças | G29: Nr. | H29: Vulnerabilidades Encontradas | K29: Consequências | O29: Relevancia do Ativo para o Negócio | R29: Justificativa/Evidências
A30: ='LISTA AMEACAS'!A22 -> At 02 | B30: ='LISTA AMEACAS'!B22 -> Plataforma de monitoramento SOC 24/7 | D30: ='LISTA AMEACAS'!E22 -> Perda de inovação por acesso indevido | G30: 1 | H30: =VULNERABILIDADES!L30 -> Documentos técnicos e projetos podem ser acessados sem restrições adequadas. | K30: =CONSEQUENCIAS!P30 -> Perda de confidencialidade | O30: Crítico | R30: Como o ativo é crítico para monitoramento e inteligência de segurança, exposição de documentos reduz vantagem operacional e fragiliza decisões.
G31: 2 | H31: =VULNERABILIDADES!L31 -> Sistemas desatualizados. | K31: =CONSEQUENCIAS!P31 -> Perda de Disponibilidade | R31: Em ativo crítico, defasagem tecnológica aumenta indisponibilidade e falhas de detecção de incidentes.
G32: 3 | H32: =VULNERABILIDADES!L32 -> Dependência de tecnologias obsoletas. | K32: =CONSEQUENCIAS!P32 -> Perda de Disponibilidade | R32: A relevância crítica exige resiliência; obsolescência limita resposta rápida e compromete continuidade de monitoramento.
G33: 4 | H33: =VULNERABILIDADES!L33 -> Falta de capacitação da equipe. | K33: =CONSEQUENCIAS!P33 -> Prejuizo financeiro por retrabalho | R33: Para ativo crítico, baixa maturidade operacional gera erros de análise e retrabalho em eventos de segurança.
D34: ='LISTA AMEACAS'!I22 -> Interferência na produção de novos materiais | G34: 5 | H34: =VULNERABILIDADES!L34 -> Acesso indevido à plataforma. | K34: =CONSEQUENCIAS!P34 -> Perda de Integridade | R34: Em ativo crítico, acesso não autorizado permite manipulação de configuração e degrada detecção.
G35: 6 | H35: =VULNERABILIDADES!L35 -> Configuração inadequada dos sensores. | K35: =CONSEQUENCIAS!P35 -> Perda de Disponibilidade | R35: Sensor mal ajustado em ativo crítico gera cegueira operacional e aumenta tempo de exposição ao ataque.
G36: 7 | H36: =VULNERABILIDADES!L36 -> Alertas não tratados adequadamente. | K36: =CONSEQUENCIAS!P36 -> Perda de Disponibilidade | R36: Em ambiente crítico, alerta ignorado pode evoluir para incidente grave sem contenção.
G37: 8 | H37: =VULNERABILIDADES!L37 -> Falta de segregação de ambientes | K37: =CONSEQUENCIAS!P37 -> Perda de Disponibilidade | R37: A criticidade do ativo exige isolamento; sem segregação, falha em um ambiente contamina outros e impacta operação 24/7.
B39: Ativo | D39: Ameaças | G39: Nr. | H39: Vulnerabilidades Encontradas | K39: Consequências | O39: Relevancia do Ativo para o Negócio | R39: Justificativa/Evidências
A40: ='LISTA AMEACAS'!A23 -> At 03 | B40: ='LISTA AMEACAS'!B23 -> Ferramentas de análise de vulnerabilidades | D40: ='LISTA AMEACAS'!E23 -> Ataques cibernéticos | G40: 1 | H40: =VULNERABILIDADES!L40 -> Falta de proteção robusta contra ameaças externas, como hackers e malware. | K40: =CONSEQUENCIAS!P40 -> Perda de confidencialidade | O40: Importante | R40: Ativo importante para prevenção; baixa proteção aumenta superfície de ataque e compromete qualidade das análises.
G41: 2 | H41: =VULNERABILIDADES!L41 -> Ferramentas desatualizadas. | K41: =CONSEQUENCIAS!P41 -> Perda de Disponibilidade | R41: Em ativo importante, atualização deficiente reduz capacidade de identificar vulnerabilidades atuais.
G42: 3 | H42: =VULNERABILIDADES!L42 -> Execução sem autenticação forte. | K42: =CONSEQUENCIAS!P42 -> Perda de confidencialidade | R42: A relevância do ativo requer controle rígido; autenticação fraca facilita uso indevido da ferramenta.
G43: 4 | H43: =VULNERABILIDADES!L43 -> Resultados armazenados sem proteção. | K43: =CONSEQUENCIAS!P43 -> Perda de confidencialidade | R43: Relatórios de vulnerabilidade em ativo importante contêm dados críticos de segurança; exposição aumenta risco de exploração.
D44: ='LISTA AMEACAS'!I23 -> Interrupção de serviços críticos | G44: 5 | H44: =VULNERABILIDADES!L44 -> Falhas nos servidores podem levar à indisponibilidade dos sistemas empresariais. | K44: =CONSEQUENCIAS!P44 -> Perda de Disponibilidade | R44: Como o ativo é importante para gestão de risco, indisponibilidade reduz capacidade de prevenção contínua.
G45: 6 | H45: =VULNERABILIDADES!L45 -> Dependência de único servidor. | K45: =CONSEQUENCIAS!P45 -> Perda de Disponibilidade | R45: Sem redundância, a falha pontual afeta diretamente suporte técnico ao negócio.
G46: 7 | H46: =VULNERABILIDADES!L46 -> Falta de redundância. | K46: =CONSEQUENCIAS!P46 -> Perda de Disponibilidade | R46: Em ativo importante, ausência de alta disponibilidade amplia impacto operacional em incidentes.
G47: 8 | H47: =VULNERABILIDADES!L47 -> Acesso administrativo compartilhado. | K47: =CONSEQUENCIAS!P47 -> Perda de Disponibilidade | R47: Reduz rastreabilidade em ativo relevante, dificultando governança e correção
B49: Ativo | D49: Ameaças | G49: Nr. | H49: Vulnerabilidades Encontradas | K49: Consequências | O49: Relevancia do Ativo para o Negócio | R49: Justificativa/Evidências
A50: ='LISTA AMEACAS'!A24 -> At 04 | B50: ='LISTA AMEACAS'!B24 -> Sistemas de backup e recuperação de dados | D50: ='LISTA AMEACAS'!E24 -> Roubo de informações | G50: 1 | H50: =VULNERABILIDADES!L50 -> Acesso não autorizado pode comprometer dados sensíveis dos clientes. | K50: =CONSEQUENCIAS!P50 -> Perda de confidencialidade | O50: Crítico | R50: Como o ativo é crítico para recuperação e continuidade, vazamento afeta confiança e conformidade legal.
G51: 2 | H51: =VULNERABILIDADES!L51 -> Falta de logs de acesso. | K51: =CONSEQUENCIAS!P51 -> Perda de confidencialidade | R51: Em ativo crítico, ausência de trilha de auditoria impede resposta eficaz a incidentes.
G52: 3 | H52: =VULNERABILIDADES!L52 -> Armazenamento inadequado. | K52: =CONSEQUENCIAS!P52 -> Perda de confidencialidade | R52: Relevância crítica exige proteção robusta; armazenamento frágil aumenta risco de exposição massiva.
G53: 4 | H53: =VULNERABILIDADES!L53 -> Acesso amplo aos backups. | K53: =CONSEQUENCIAS!P53 -> Perda de confidencialidade | R53: Em ativo crítico, permissões excessivas ampliam risco de leitura/cópia indevida de dados estratégicos.
D54: ='LISTA AMEACAS'!I24 -> Uso indevido por terceiros | G54: 5 | H54: =VULNERABILIDADES!L54 -> Parceiros ou funcionários podem acessar e utilizar dados de clientes sem autorização adequada. | K54: =CONSEQUENCIAS!P54 -> Perda de confidencialidade | R54: A criticidade do ativo torna qualquer desvio de uso um risco alto para continuidade e imagem.
G55: 6 | H55: =VULNERABILIDADES!L55 -> Ausência de trilhas de auditoria sobre restaurações e consultas. | K55: =CONSEQUENCIAS!P55 -> Perda de confidencialidade | R55: Em ativo crítico, falta de controle impede identificar abuso e fraude.
G56: 7 | H56: =VULNERABILIDADES!L56 -> Ausência de mecanismos eficazes de autenticação forte (MFA). | K56: =CONSEQUENCIAS!P56 -> Perda de confidencialidade | R56: Controle fraco em ativo crítico facilita comprometimento de contas privilegiadas.
G57: 8 | H57: =VULNERABILIDADES!L57 -> Falta de políticas formais de uso e proteção da informação. | K57: =CONSEQUENCIAS!P57 -> Perda de confidencialidade | R57: Para ativo crítico, ausência de diretrizes padronizadas aumenta erro operacional e exposição de dados.
B59: Ativo | D59: Ameaças | G59: Nr. | H59: Vulnerabilidades Encontradas | K59: Consequências | O59: Relevancia do Ativo para o Negócio | R59: Justificativa/Evidências
A60: ='LISTA AMEACAS'!A25 -> At 05 | B60: ='LISTA AMEACAS'!B25 -> Código-fonte dos sistemas desenvolvidos | D60: ='LISTA AMEACAS'!E25 -> Falhas operacionais | G60: 1 | H60: =VULNERABILIDADES!L60 -> Erros mecânicos ou falhas humanas podem interromper o fluxo produtivo. | K60: =CONSEQUENCIAS!P60 -> Perda de Disponibilidade | O60: Crítico | R60: Código-fonte é base do negócio; falha operacional compromete entregas e continuidade.
G61: 2 | H61: =VULNERABILIDADES!L61 -> Ausência de revisão de código (code review). | K61: =CONSEQUENCIAS!P61 -> Perda de Disponibilidade | R61: Em ativo crítico, revisão ausente aumenta chance de defeitos em produção e retrabalho.
G62: 3 | H62: =VULNERABILIDADES!L62 -> Falta de padrões de desenvolvimento. | K62: =CONSEQUENCIAS!P62 -> Perda de Disponibilidade | R62: Criticidade exige consistência técnica; sem padrão, cresce risco de falha e manutenção cara.
G63: 4 | H63: =VULNERABILIDADES!L63 -> Falta de testes automatizados. | K63: =CONSEQUENCIAS!P63 -> Perda de Disponibilidade | R63: Ativo crítico sem validação automática eleva risco de indisponibilidade e erro recorrente.
D64: ='LISTA AMEACAS'!I25 -> Sabotagem industrial | G64: 5 | H64: =VULNERABILIDADES!L64 -> Possibilidade de funcionários ou terceiros manipularem equipamentos ou processos de produção. | K64: =CONSEQUENCIAS!P64 -> Prejuizo financeiro por retrabalho | R64: A criticidade do código torna sabotagem um risco direto ao serviço e receita.
G65: 6 | H65: =VULNERABILIDADES!L65 -> Exposição de credenciais dentro do código. | K65: =CONSEQUENCIAS!P65 -> Perda de confidencialidade | R65: Em ativo crítico, vazamento de segredo facilita invasão em cadeia.
G66: 7 | H66: =VULNERABILIDADES!L66 -> Repositório com acesso permissivo. | K66: =CONSEQUENCIAS!P66 -> Perda de Integridade | R66: Excesso de privilégio compromete integridade e confiabilidade do produto.
G67: 8 | H67: =VULNERABILIDADES!L67 -> Histórico de commits não auditado. | K67: =CONSEQUENCIAS!P67 -> Perda de Integridade | R67: Em ativo crítico, falta de rastreabilidade dificulta detectar alteração maliciosa.
B69: Ativo | D69: Ameaças | G69: Nr. | H69: Vulnerabilidades Encontradas | K69: Consequências | O69: Relevancia do Ativo para o Negócio | R69: Justificativa/Evidências
A70: ='LISTA AMEACAS'!A26 -> At 06 | B70: ='LISTA AMEACAS'!B26 -> Ambientes de desenvolvimento (Dev/Test/Prod) | D70: ='LISTA AMEACAS'!E26 -> Interrupção na cadeia logística | G70: 1 | H70: =VULNERABILIDADES!L70 -> Problemas com fornecedores podem atrasar ou interromper entregas essenciais. | K70: =CONSEQUENCIAS!P70 -> Perda de Disponibilidade | O70: Importante | R70: Como o ativo suporta o fluxo de desenvolvimento e publicação, atrasos em componentes/serviços impactam cronograma e continuidade operacional.
G71: 2 | H71: =VULNERABILIDADES!L71 -> Falta de segregação entre ambientes (DEV/TEST/PROD). | K71: =CONSEQUENCIAS!P71 -> Interrupção de serviços | R71: Em ativo importante, ausência de separação aumenta risco de erro de mudança atingir produção e gerar indisponibilidade.
G72: 3 | H72: =VULNERABILIDADES!L72 -> Ausência de redundância de servidores de desenvolvimento. | K72: =CONSEQUENCIAS!P72 -> Impacto operacional | R72: A relevância do ativo exige resiliência mínima; sem redundância, falha única interrompe atividades técnicas críticas.
G73: 4 | H73: =VULNERABILIDADES!L73 -> Falta de monitoramento do ambiente. | K73: =CONSEQUENCIAS!P73 -> Atrasos em processos internos | R73: Sem visibilidade contínua em ativo importante, incidentes demoram a ser detectados, elevando tempo de parada e retrabalho.
D74: ='LISTA AMEACAS'!I26 -> Manipulação indevida de entregas | G74: 5 | H74: =VULNERABILIDADES!L74 -> Possibilidade de adulteração ou redirecionamento não autorizado de produtos. | K74: =CONSEQUENCIAS!P74 -> Insatisfação de usuários | R74: A relevância do ativo para qualidade de release torna manipulação um risco direto à integridade e confiança do serviço.
G75: 6 | H75: =VULNERABILIDADES!L75 -> Versionamento sem controle adequado. | K75: =CONSEQUENCIAS!P75 -> Perda de produtividade | R75: Em ativo importante, controle fraco de versões favorece implantação incorreta e retorno de vulnerabilidades corrigidas.
G76: 7 | H76: =VULNERABILIDADES!L76 -> Uso de dados reais em testes. | K76: =CONSEQUENCIAS!P76 -> Impacto financeiro | R76: Como o ativo participa do ciclo de entrega, uso indevido de dados reais amplia risco de vazamento e não conformidade.
G77: 8 | H77: =VULNERABILIDADES!L77 -> Ausência de trilhas de auditoria. | K77: =CONSEQUENCIAS!P77 -> Dependência de suporte emergencial | R77: Sem rastreabilidade em ativo importante, torna-se difícil provar conformidade e investigar falhas de entrega.
B79: Ativo | D79: Ameaças | G79: Nr. | H79: Vulnerabilidades Encontradas | K79: Consequências | O79: Relevancia do Ativo para o Negócio | R79: Justificativa/Evidências
A80: ='LISTA AMEACAS'!A27 -> At 07 | B80: ='LISTA AMEACAS'!B27 -> Banco de dados de clientes corporativos | D80: ='LISTA AMEACAS'!E27 -> Fraudes financeiras | G80: 1 | H80: =VULNERABILIDADES!L80 -> Possibilidade de manipulação indevida de transações financeiras. | K80: =CONSEQUENCIAS!P80 -> Perda de confidenciabilidade | O80: Crítico | R80: O banco de dados de clientes é crítico; fraude afeta receita, compliance e credibilidade institucional.
G81: 2 | H81: =VULNERABILIDADES!L81 -> Controle de acesso insuficiente. | K81: =CONSEQUENCIAS!P81 -> Vazamento dec dados | R81: Em ativo crítico com dados sensíveis, permissões fracas ampliam risco de alteração e exfiltração.
G82: 3 | H82: =VULNERABILIDADES!L82 -> Ausência de segregação de contas privilegiadas. | K82: =CONSEQUENCIAS!P82 -> Impacto legal ( LGPD) | R82: A criticidade exige segregação rígida; sem isso, abuso de privilégio pode comprometer toda a base.
G83: 4 | H83: =VULNERABILIDADES!L83 -> Falta de validação transacional. | K83: =CONSEQUENCIAS!P83 -> Danos a reputação | R83: Em ativo crítico, validação insuficiente permite inconsistência de registros com impacto financeiro e operacional.
D84: ='LISTA AMEACAS'!I27 -> Alteração não autorizada de registros | G84: 5 | H84: =VULNERABILIDADES!L84 -> Dados financeiros podem ser alterados indevidamente por usuários sem permissão adequada. | K84: =CONSEQUENCIAS!P84 -> Perda da confiança | R84: Como o ativo é crítico ao negócio, alteração indevida prejudica decisões, faturamento e relação com clientes.
G85: 6 | H85: =VULNERABILIDADES!L85 -> Vulnerabilidade de SQL Injection. | K85: =CONSEQUENCIAS!P85 -> Multas e penalidades | R85: Em ativo crítico, exploração pode permitir leitura/alteração massiva de dados estratégicos.
G86: 7 | H86: =VULNERABILIDADES!L86 -> Falta de logs de integridade. | K86: =CONSEQUENCIAS!P86 -> Uso indevido de dados | R86: Sem controle de integridade, não há evidência confiável de adulteração em base crítica.
G87: 8 | H87: =VULNERABILIDADES!L87 -> Contas de serviço com privilégios excessivos. | K87: =CONSEQUENCIAS!P87 -> Exposição dce informações | R87: Em ativo crítico, privilégios amplos elevam impacto de comprometimento de credenciais técnicas.
B89: Ativo | D89: Ameaças | G89: Nr. | H89: Vulnerabilidades Encontradas | K89: Consequências | O89: Relevancia do Ativo para o Negócio | R89: Justificativa/Evidências
A90: ='LISTA AMEACAS'!A28 -> At 08 | B90: ='LISTA AMEACAS'!B28 -> Logs e registros de segurança (SIEM) | D90: ='LISTA AMEACAS'!E28 -> Falta de conformidade | G90: 1 | H90: =VULNERABILIDADES!L90 -> Falta de adesão às diretrizes de segurança estabelecidas pela empresa e normas externas, como ISO 27001. | K90: =CONSEQUENCIAS!P90 -> Perda de Integridade | O90: Importante | R90: O ativo é importante para governança; não conformidade reduz eficácia do programa de segurança.
G91: 2 | H91: =VULNERABILIDADES!L91 -> Ausência de integridade dos registros. | K91: =CONSEQUENCIAS!P91 -> Dados inconsistentes | R91: Em ativo importante, logs alteráveis comprometem auditoria e tomada de decisão baseada em evidências.
G92: 3 | H92: =VULNERABILIDADES!L92 -> Falta de retenção mínima exigida. | K92: =CONSEQUENCIAS!P92 -> Retrabalho operacional | R92: Sem retenção adequada, perde-se histórico necessário para investigação e requisitos regulatórios.
G93: 4 | H93: =VULNERABILIDADES!L93 -> Inconsistência nas fontes de log. | K93: =CONSEQUENCIAS!P93 -> Falhas em relatórios | R93: Relevância do ativo exige correlação confiável; inconsistência aumenta falso positivo/negativo e retrabalho.
D94: ='LISTA AMEACAS'!I28 -> Desrespeito às normas de segurança | G94: 5 | H94: =VULNERABILIDADES!L94 -> Possibilidade de funcionários ignorarem ou não aplicarem corretamente as políticas de segurança. | K94: =CONSEQUENCIAS!P94 -> Decisões incorretas | R94: Em ativo importante, descumprimento normativo amplia risco operacional e de incidentes recorrentes.
G95: 6 | H95: =VULNERABILIDADES!L95 -> Falta de controle de acesso aos logs. | K95: =CONSEQUENCIAS!P95 -> Atrasos em processos | R95: Logs sensíveis exigem acesso restrito; falha nisso compromete confidencialidade e confiabilidade.
G96: 7 | H96: =VULNERABILIDADES!L96 -> Ausência de SIEM consolidado. | K96: =CONSEQUENCIAS!P96 -> arga de equipes | R96: Sem centralização adequada em ativo importante, a capacidade de resposta fica fragmentada.
G97: 8 | H97: =VULNERABILIDADES!L97 -> Armazenamento inadequado. | K97: =CONSEQUENCIAS!P97 -> Perda de confidencialidade | R97: Em ativo importante, armazenamento fraco aumenta risco de perda de evidências e exposição indevida.
B99: Ativo | D99: Ameaças | G99: Nr. | H99: Vulnerabilidades Encontradas | K99: Consequências | O99: Relevancia do Ativo para o Negócio | R99: Justificativa/Evidências
A100: ='LISTA AMEACAS'!A29 -> At 09 | B100: ='LISTA AMEACAS'!B29 -> Ferramentas de pentest (internas e licenciadas) | D100: ='LISTA AMEACAS'!E29 -> Vazamento de dados pessoais | G100: 1 | H100: =VULNERABILIDADES!L100 -> Exposição de dados sensíveis dos funcionários por acessos não autorizados. | K100: =CONSEQUENCIAS!P100 -> Interupção de serviço | O100: Significante | R100: Como o ativo é significante para validação de segurança, vazamento afeta confiança e conformidade.
G101: 2 | H101: =VULNERABILIDADES!L101 -> Armazenamento de resultados em locais públicos. | K101: =CONSEQUENCIAS!P101 -> Perda de Disponibilidade | R101: Em ativo relevante, exposição de achados técnicos facilita exploração por terceiros.
G102: 3 | H102: =VULNERABILIDADES!L102 -> Logs de execução não protegidos. | K102: =CONSEQUENCIAS!P102 -> Impacto operacional | R102: Falha de proteção em ativo significante aumenta risco de acesso a evidências técnicas sensíveis.
G103: 4 | H103: =VULNERABILIDADES!L103 -> Transporte inseguro dos relatórios. | K103: =CONSEQUENCIAS!P103 -> Insatisfação de usuários | R103: Relatórios de teste carregam vulnerabilidades; envio inseguro amplia risco de uso malicioso.
D104: ='LISTA AMEACAS'!I29 -> Uso indevido de informações de colaboradores | G104: 5 | H104: =VULNERABILIDADES!L104 -> Dados de funcionários podem ser acessados e utilizados sem consentimento. | K104: =CONSEQUENCIAS!P104 -> Perda de produtividade | R104: Em ativo significante, uso indevido impacta privacidade e pode gerar passivo regulatório.
G105: 6 | H105: =VULNERABILIDADES!L105 -> Execução sem autorização formal. | K105: =CONSEQUENCIAS!P105 -> Impacto financeiro | R105: Falta de governança em ativo relevante compromete rastreabilidade e legitimidade dos testes.
G106: 7 | H106: =VULNERABILIDADES!L106 -> Ferramentas instaladas em máquinas pessoais. | K106: =CONSEQUENCIAS!P106 -> Sobrecarga de equipe | R106: Em ativo significante, ambiente não controlado amplia risco de perda de dados e contaminação.
G107: 8 | H107: =VULNERABILIDADES!L107 -> Falta de segregação de perfis de pentest. | K107: =CONSEQUENCIAS!P107 -> Queda de desempenho | R107: Sem segregação, usuários podem extrapolar escopo e comprometer integridade de sistemas.
B109: Ativo | D109: Ameaças | G109: Nr. | H109: Vulnerabilidades Encontradas | K109: Consequências | O109: Relevancia do Ativo para o Negócio | R109: Justificativa/Evidências
A110: ='LISTA AMEACAS'!A30 -> At 10 | B110: ='LISTA AMEACAS'!B30 -> Credenciais de acesso (senhas, tokens, chaves API) | D110: ='LISTA AMEACAS'!E30 -> Ataques de phishing | G110: 1 | H110: =VULNERABILIDADES!L110 -> Funcionários podem ser induzidos a compartilhar credenciais por e-mails fraudulentos. | K110: =CONSEQUENCIAS!P110 -> Perda de confidencialidade | O110: Crítico | R110: Como o ativo é crítico de acesso, phishing pode abrir porta para comprometimento amplo.
G111: 2 | H111: =VULNERABILIDADES!L111 -> Falta de treinamento dos usuários. | K111: =CONSEQUENCIAS!P111 -> Vazamento de informções | R111: Em ativo crítico, baixa conscientização aumenta taxa de sucesso de engenharia social.
G112: 3 | H112: =VULNERABILIDADES!L112 -> E-mail sem filtro de segurança. | K112: =CONSEQUENCIAS!P112 -> Danos a reputação | R112: Controle insuficiente em canal de entrada crítico eleva risco de captura de credenciais.
G113: 4 | H113: =VULNERABILIDADES!L113 -> Falta de política formal de credenciais. | K113: =CONSEQUENCIAS!P113 -> Impacto legal | R113: Em ativo crítico, falta de diretriz unificada favorece práticas inseguras.
D114: ='LISTA AMEACAS'!I30 -> Roubo de credenciais | G114: 5 | H114: =VULNERABILIDADES!L114 -> Senhas fracas ou reutilizadas podem ser comprometidas por invasores. | K114: =CONSEQUENCIAS!P114 -> Perda de confiaça | R114: A criticidade do ativo torna senhas frágeis um risco sistêmico de invasão em cascata.
G115: 6 | H115: =VULNERABILIDADES!L115 -> Senhas fracas ou padrão. | K115: =CONSEQUENCIAS!P115 -> Exposição de dados sensíveis | R115: Em ativo crítico, credenciais previsíveis aumentam probabilidade de acesso não autorizado
G116: 7 | H116: =VULNERABILIDADES!L116 -> Reutilização de senhas. | K116: =CONSEQUENCIAS!P116 -> Uso indevido da infolrmação | R116: Mesmo comprometimento local pode escalar para múltiplos sistemas críticos.
G117: 8 | H117: =VULNERABILIDADES!L117 -> Armazenamento de senhas em texto simples. | K117: =CONSEQUENCIAS!P117 -> Impacto financeiro | R117: Em ativo crítico, armazenamento inseguro permite comprometimento imediato de contas privilegiadas.
B119: Ativo | D119: Ameaças | G119: Nr. | H119: Vulnerabilidades Encontradas | K119: Consequências | O119: Relevancia do Ativo para o Negócio | R119: Justificativa/Evidências
A120: ='LISTA AMEACAS'!A31 -> At 11 | B120: ='LISTA AMEACAS'!B31 -> Infraestrutura de rede (firewalls, switches, VPN) | D120: ='LISTA AMEACAS'!E31 -> Falha na infraestrutura | G120: 1 | H120: =VULNERABILIDADES!L120 -> Problemas técnicos podem causar indisponibilidade dos sistemas. | K120: =CONSEQUENCIAS!P120 -> Perda de confidencialidade | O120: Crítico | R120: Rede é base operacional; falha impacta serviços essenciais e produtividade geral.
G121: 2 | H121: =VULNERABILIDADES!L121 -> Falta de segmentação de rede. | K121: =CONSEQUENCIAS!P121 -> Parada operacional | R121: Em ativo crítico, ausência de segmentação facilita propagação de ataque lateral.
G122: 3 | H122: =VULNERABILIDADES!L122 -> Equipamentos sem redundância. | K122: =CONSEQUENCIAS!P122 -> Impacto finacenceiro | R122: Criticidade exige alta disponibilidade; sem redundância, falha única causa parada ampla.
G123: 4 | H123: =VULNERABILIDADES!L123 -> Firmware desatualizado. | K123: =CONSEQUENCIAS!P123 -> Atraso em atividades | R123: Em ativo crítico, atualização deficiente expõe vulnerabilidades conhecidas exploráveis.
D124: ='LISTA AMEACAS'!I31 -> Ataques cibernéticos e invasões | G124: 5 | H124: =VULNERABILIDADES!L124 -> Sistemas sem proteção adequada podem ser alvo de hackers. | K124: =CONSEQUENCIAS!P124 -> Insatisfação dos usuários | R124: Relevância crítica requer defesa ativa; proteção fraca amplia chance de intrusão bem-sucedida.
G125: 6 | H125: =VULNERABILIDADES!L125 -> VPN sem autenticação forte. | K125: =CONSEQUENCIAS!P125 -> Redução de produtividade | R125: Em ativo crítico, acesso remoto frágil facilita comprometimento da borda de segurança.
G126: 7 | H126: =VULNERABILIDADES!L126 -> Portas abertas sem necessidade. | K126: =CONSEQUENCIAS!P126 -> Dependência de suporte técnico | R126: Superfície de ataque ampliada em ativo crítico aumenta risco de exploração automatizada.
G127: 8 | H127: =VULNERABILIDADES!L127 -> Falta de IDS/IPS efetivo. | K127: =CONSEQUENCIAS!P127 -> Aumento de custos de manutenção | R127: Sem detecção/prevenção robusta, incidentes em rede crítica escalam rapidamente.
...

Sheet CONS_AV_QUALIT_SEVER
A1: Avaliação das Consequências – Severidade
B19: Ativo | D19: Ameaças | G19: Nr. | H19: Vulnerabilidades Encontradas | K19: Consequências | O19: Relevancia do Ativo para o Negócio | R19: Severidade das Consequências | U19: Justificativa/Evidências
A20: ='LISTA AMEACAS'!A21 -> At 01 | B20: ='LISTA AMEACAS'!B21 -> Infraestrutura de servidores em nuvem | D20: ='LISTA AMEACAS'!E21 -> Vazamento de informações | G20: 1 | H20: =VULNERABILIDADES!L20 -> Falta de classificação da informação | K20: =CONSEQUENCIAS!P20 -> Perda de Autenticidade | O20: =CONS_AV_QUALIT_ATIVO!O20 -> Crítico | R20: Elevada | U20: Falta de classificação causa uso indevido sem rastreabilidade clara. Evidências: política de classificação inexistente/desatualizada; amostras de arquivos sem rótulo; logs sem identificação do proprietário da informação.
G21: 2 | H21: =VULNERABILIDADES!L21 -> Dados armazenados sem criptografia. | K21: =CONSEQUENCIAS!P21 -> Perda de Integridade | R21: Alta | U21: Dados sem criptografia podem ser alterados/expostos. Evidências: inventário de buckets/volumes sem criptografia ativa; relatório CSPM; configuração KMS ausente.
G22: 3 | H22: =VULNERABILIDADES!L22 -> Armazenamento inseguro | K22: =CONSEQUENCIAS!P22 -> Perda de confidencialidade | R22: Alta | U22: Armazenamento inseguro facilita acesso não autorizado. Evidências: ACL pública indevida; portas expostas em SG/NACL; achados de varredura externa.
G23: 4 | H23: =VULNERABILIDADES!L23 -> Falta de monitoramento de acesso. | K23: =CONSEQUENCIAS!P23 -> Perda de Autenticidade | R23: Elevada | U23: Sem monitoramento, autoria das ações fica comprometida. Evidências: trilhas CloudTrail/Activity Logs incompletas; ausência de alertas SIEM; lacunas de retenção de log.
D24: ='LISTA AMEACAS'!I21 -> Roubo de dados por concorrentes | G24: 5 | H24: =VULNERABILIDADES!L24 -> Falta de backup adequado | K24: =CONSEQUENCIAS!P24 -> Perda de Disponibilidade | R24: Elevada | U24: Backup inadequado prejudica recuperação e continuidade. Evidências: testes de restore reprovados; RPO/RTO fora da meta; ausência de cópia imutável/offsite.
G25: 6 | H25: =VULNERABILIDADES!L25 -> Logs de auditoria incompletos. | K25: =CONSEQUENCIAS!P25 -> Perda de Autenticidade | R25: Elevada | U25: Logs incompletos impedem investigação confiável. Evidências: eventos sem usuário/IP; gaps de coleta; falha de integração com SIEM.
G26: 7 | H26: =VULNERABILIDADES!L26 -> Acesso indevido | K26: =CONSEQUENCIAS!P26 -> Perda de Integridade | R26: Alta | U26: Acesso indevido permite manipulação de dados. Evidências: permissões excessivas (IAM); ausência de segregação de funções; alterações sem aprovação em change log.
G27: 8 | H27: =VULNERABILIDADES!L27 -> Armazenamento de credenciais em texto simples. | K27: =CONSEQUENCIAS!P27 -> Perda de confidencialidade | R27: Alta | U27: Credenciais em texto simples expõem informação crítica. Evidências: secrets hardcoded em repositório; ausência de cofre de segredos; alertas de secret scanning.
B29: Ativo | D29: Ameaças | G29: Nr. | H29: Vulnerabilidades Encontradas | K29: Consequências | O29: Relevancia do Ativo para o Negócio | R29: Severidade das Consequências | U29: Justificativa/Evidências
A30: ='LISTA AMEACAS'!A22 -> At 02 | B30: ='LISTA AMEACAS'!B22 -> Plataforma de monitoramento SOC 24/7 | D30: ='LISTA AMEACAS'!E22 -> Perda de inovação por acesso indevido | G30: 1 | H30: =VULNERABILIDADES!L30 -> Documentos técnicos e projetos podem ser acessados sem restrições adequadas. | K30: =CONSEQUENCIAS!P30 -> Perda de confidencialidade | O30: =CONS_AV_QUALIT_ATIVO!O30 -> Crítico | R30: Alta | U30: Documentos/projetos expostos comprometem vantagem competitiva. Evidências: controles de acesso amplos; compartilhamentos indevidos; histórico de download/exportação sem necessidade.
G31: 2 | H31: =VULNERABILIDADES!L31 -> Sistemas desatualizados. | K31: =CONSEQUENCIAS!P31 -> Perda de Disponibilidade | R31: Elevada | U31: Sistemas desatualizados aumentam falhas e indisponibilidade. Evidências: inventário de versões EOL; backlog de patches críticos; incidentes por falha conhecida.
G32: 3 | H32: =VULNERABILIDADES!L32 -> Dependência de tecnologias obsoletas. | K32: =CONSEQUENCIAS!P32 -> Perda de Disponibilidade | R32: Média | U32: Tecnologia obsoleta reduz eficiência e continuidade. Evidências: alertas de performance; MTTR elevado; capacidade próxima do limite.
G33: 4 | H33: =VULNERABILIDADES!L33 -> Falta de capacitação da equipe. | K33: =CONSEQUENCIAS!P33 -> Prejuizo financeiro por retrabalho | R33: Média | U33: Falta de capacitação eleva erro e retrabalho. Evidências: registros de treinamento vencidos; tickets reabertos; retrabalho recorrente em pós-incidente
D34: ='LISTA AMEACAS'!I22 -> Interferência na produção de novos materiais | G34: 5 | H34: =VULNERABILIDADES!L34 -> Acesso indevido à plataforma. | K34: =CONSEQUENCIAS!P34 -> Perda de Integridade | R34: Alta | U34: Acesso indevido permite alteração de parâmetros críticos. Evidências: mudanças sem workflow de aprovação; contas genéricas; ausência de trilha de auditoria completa.
G35: 6 | H35: =VULNERABILIDADES!L35 -> Configuração inadequada dos sensores. | K35: =CONSEQUENCIAS!P35 -> Perda de Disponibilidade | R35: Elevada | U35: Sensores mal configurados geram falha operacional. Evidências: baseline de configuração divergente; alarmes falsos/ausentes; incidentes correlatos.
G36: 7 | H36: =VULNERABILIDADES!L36 -> Alertas não tratados adequadamente. | K36: =CONSEQUENCIAS!P36 -> Perda de Disponibilidade | R36: Elevada | U36: Alertas ignorados atrasam reação a incidentes. Evidências: SLA de resposta violado; backlog de alertas; tempo médio de reconhecimento elevado.
G37: 8 | H37: =VULNERABILIDADES!L37 -> Falta de segregação de ambientes | K37: =CONSEQUENCIAS!P37 -> Perda de Disponibilidade | R37: Elevada | U37: Sem segregação, incidentes se propagam mais rápido. Evidências: rede plana; ausência de microsegmentação; testes de contenção reprovados.
B39: Ativo | D39: Ameaças | G39: Nr. | H39: Vulnerabilidades Encontradas | K39: Consequências | O39: Relevancia do Ativo para o Negócio | R39: Severidade das Consequências | U39: Justificativa/Evidências
A40: ='LISTA AMEACAS'!A23 -> At 03 | B40: ='LISTA AMEACAS'!B23 -> Ferramentas de análise de vulnerabilidades | D40: ='LISTA AMEACAS'!E23 -> Ataques cibernéticos | G40: 1 | H40: =VULNERABILIDADES!L40 -> Falta de proteção robusta contra ameaças externas, como hackers e malware. | K40: =CONSEQUENCIAS!P40 -> Perda de confidencialidade | O40: =CONS_AV_QUALIT_ATIVO!O40 -> Importante | R40: Alta | U40: Ferramenta sem proteção robusta pode ser comprometida. Evidências: hardening ausente; CVEs abertas; autenticação fraca no console.
G41: 2 | H41: =VULNERABILIDADES!L41 -> Ferramentas desatualizadas. | K41: =CONSEQUENCIAS!P41 -> Perda de Disponibilidade | R41: Elevada | U41: Ferramentas desatualizadas falham em varreduras críticas. Evidências: versão descontinuada; scans incompletos; assinaturas desatualizadas.
G42: 3 | H42: =VULNERABILIDADES!L42 -> Execução sem autenticação forte. | K42: =CONSEQUENCIAS!P42 -> Perda de confidencialidade | R42: Alta | U42: Execução sem autenticação forte permite uso indevido. Evidências: MFA desabilitado; contas compartilhadas; logs de login suspeitos.
G43: 4 | H43: =VULNERABILIDADES!L43 -> Resultados armazenados sem proteção. | K43: =CONSEQUENCIAS!P43 -> Perda de confidencialidade | R43: Alta | U43: Resultados sem proteção expõem brechas internas. Evidências: relatórios em pastas abertas; envio sem criptografia; ausência de DLP.
D44: ='LISTA AMEACAS'!I23 -> Interrupção de serviços críticos | G44: 5 | H44: =VULNERABILIDADES!L44 -> Falhas nos servidores podem levar à indisponibilidade dos sistemas empresariais. | K44: =CONSEQUENCIAS!P44 -> Perda de Disponibilidade | R44: Alta | U44: Falha de servidor interrompe processos de segurança. Evidências: ausência de cluster/HA; incidentes de indisponibilidade; sem failover testado.
G45: 6 | H45: =VULNERABILIDADES!L45 -> Dependência de único servidor. | K45: =CONSEQUENCIAS!P45 -> Perda de Disponibilidade | R45: Elevada | U45: Dependência de servidor único cria ponto único de falha. Evidências: arquitetura SPOF; inventário sem redundância; DR não validado.
G46: 7 | H46: =VULNERABILIDADES!L46 -> Falta de redundância. | K46: =CONSEQUENCIAS!P46 -> Perda de Disponibilidade | R46: Elevada | U46: Sem redundância, recuperação é lenta. Evidências: RTO excedido em simulado; runbook incompleto; restauração manual demorada.
G47: 8 | H47: =VULNERABILIDADES!L47 -> Acesso administrativo compartilhado. | K47: =CONSEQUENCIAS!P47 -> Perda de Disponibilidade | R47: Média | U47: Acesso administrativo compartilhado eleva risco operacional. Evidências: contas coletivas; ausência de PAM; ações administrativas sem atribuição individual. administrativo compartilhado eleva risco operacional.
B49: Ativo | D49: Ameaças | G49: Nr. | H49: Vulnerabilidades Encontradas | K49: Consequências | O49: Relevancia do Ativo para o Negócio | R49: Severidade das Consequências | U49: Justificativa/Evidências
A50: ='LISTA AMEACAS'!A24 -> At 04 | B50: ='LISTA AMEACAS'!B24 -> Sistemas de backup e recuperação de dados | D50: ='LISTA AMEACAS'!E24 -> Roubo de informações | G50: 1 | H50: =VULNERABILIDADES!L50 -> Acesso não autorizado pode comprometer dados sensíveis dos clientes. | K50: =CONSEQUENCIAS!P50 -> Perda de confidencialidade | O50: =CONS_AV_QUALIT_ATIVO!O50 -> Crítico | R50: Alta | U50: Acesso não autorizado expõe dados sensíveis. Evidências: permissões amplas em repositório de backup; auditoria de acesso falha; cópias sem criptografia.
G51: 2 | H51: =VULNERABILIDADES!L51 -> Falta de logs de acesso. | K51: =CONSEQUENCIAS!P51 -> Perda de confidencialidade | R51: Elevada | U51: Falta de logs impede detectar vazamento. Evidências: logging de restore/download desabilitado; lacunas de trilha; retenção insuficiente.
G52: 3 | H52: =VULNERABILIDADES!L52 -> Armazenamento inadequado. | K52: =CONSEQUENCIAS!P52 -> Perda de confidencialidade | R52: Alta | U52: Armazenamento inadequado facilita exfiltração. Evidências: mídia sem proteção física/lógica; transporte sem cifragem; controles de cofre ausentes.
G53: 4 | H53: =VULNERABILIDADES!L53 -> Acesso amplo aos backups. | K53: =CONSEQUENCIAS!P53 -> Perda de confidencialidade | R53: Alta | U53: Acesso amplo aos backups aumenta exposição. Evidências: grupos com privilégios excessivos; ausência de revisão periódica de acesso.
D54: ='LISTA AMEACAS'!I24 -> Uso indevido por terceiros | G54: 5 | H54: =VULNERABILIDADES!L54 -> Parceiros ou funcionários podem acessar e utilizar dados de clientes sem autorização adequada. | K54: =CONSEQUENCIAS!P54 -> Perda de confidencialidade | R54: Alta | U54: Parceiros podem acessar dados sem controle forte. Evidências: acessos terceirizados sem MFA/VPN restrita; contratos sem cláusula de segurança.
G55: 6 | H55: =VULNERABILIDADES!L55 -> Ausência de trilhas de auditoria sobre restaurações e consultas. | K55: =CONSEQUENCIAS!P55 -> Perda de confidencialidade | R55: Elevada | U55: Sem auditoria, abuso passa despercebido. Evidências: ausência de trilha de sessão; não conformidades em auditorias internas.
G56: 7 | H56: =VULNERABILIDADES!L56 -> Ausência de mecanismos eficazes de autenticação forte (MFA). | K56: =CONSEQUENCIAS!P56 -> Perda de confidencialidade | R56: Alta | U56: Ausência de MFA facilita invasão. Evidências: relatório de identidade com MFA off; tentativas de login suspeitas.
G57: 8 | H57: =VULNERABILIDADES!L57 -> Falta de políticas formais de uso e proteção da informação. | K57: =CONSEQUENCIAS!P57 -> Perda de confidencialidade | R57: Elevada | U57: Falta de política formal reduz governança. Evidências: política inexistente/não aprovada; ausência de evidência de ciência dos usuários.
B59: Ativo | D59: Ameaças | G59: Nr. | H59: Vulnerabilidades Encontradas | K59: Consequências | O59: Relevancia do Ativo para o Negócio | R59: Severidade das Consequências | U59: Justificativa/Evidências
A60: ='LISTA AMEACAS'!A25 -> At 05 | B60: ='LISTA AMEACAS'!B25 -> Código-fonte dos sistemas desenvolvidos | D60: ='LISTA AMEACAS'!E25 -> Falhas operacionais | G60: 1 | H60: =VULNERABILIDADES!L60 -> Erros mecânicos ou falhas humanas podem interromper o fluxo produtivo. | K60: =CONSEQUENCIAS!P60 -> Perda de Disponibilidade | O60: =CONS_AV_QUALIT_ATIVO!O60 -> Crítico | R60: Média | U60: Falhas humanas interrompem fluxo de entrega. Evidências: incidentes por erro de deploy; rollback frequente; pós-mortem recorrente.
G61: 2 | H61: =VULNERABILIDADES!L61 -> Ausência de revisão de código (code review). | K61: =CONSEQUENCIAS!P61 -> Perda de Disponibilidade | R61: Média | U61: Sem code review, erros vão à produção. Evidências: PRs aprovadas sem revisão; bugs críticos pós-release; cobertura de revisão baixa.
G62: 3 | H62: =VULNERABILIDADES!L62 -> Falta de padrões de desenvolvimento. | K62: =CONSEQUENCIAS!P62 -> Perda de Disponibilidade | R62: Média | U62: Falta de padrão aumenta retrabalho técnico. Evidências: ausência de guideline; alta taxa de refatoração corretiva; divergência arquitetural.
G63: 4 | H63: =VULNERABILIDADES!L63 -> Falta de testes automatizados. | K63: =CONSEQUENCIAS!P63 -> Perda de Disponibilidade | R63: Elevada | U63: Sem testes, chance de incidente cresce. Evidências: cobertura de testes baixa; pipeline sem gates; falhas em produção após release
D64: ='LISTA AMEACAS'!I25 -> Sabotagem industrial | G64: 5 | H64: =VULNERABILIDADES!L64 -> Possibilidade de funcionários ou terceiros manipularem equipamentos ou processos de produção. | K64: =CONSEQUENCIAS!P64 -> Prejuizo financeiro por retrabalho | R64: Nível | U64: Manipulação de processos gera perdas diretas. Evidências: mudanças não autorizadas; hotfixes emergenciais; horas extras para correção.
G65: 6 | H65: =VULNERABILIDADES!L65 -> Exposição de credenciais dentro do código. | K65: =CONSEQUENCIAS!P65 -> Perda de confidencialidade | R65: Nível | U65: Credenciais no código facilitam invasão. Evidências: achados de secret scanning; tokens expostos no histórico Git.
G66: 7 | H66: =VULNERABILIDADES!L66 -> Repositório com acesso permissivo. | K66: =CONSEQUENCIAS!P66 -> Perda de Integridade | R66: Nível | U66: Repositório permissivo permite alteração indevida. Evidências: branch protection desativada; escrita ampla em branch principal.
G67: 8 | H67: =VULNERABILIDADES!L67 -> Histórico de commits não auditado. | K67: =CONSEQUENCIAS!P67 -> Perda de Integridade | R67: Nível | U67: Commits sem auditoria reduzem confiança no histórico. Evidências: ausência de assinatura de commit; trilha de revisão incompleta.
B69: Ativo | D69: Ameaças | G69: Nr. | H69: Vulnerabilidades Encontradas | K69: Consequências | O69: Relevancia do Ativo para o Negócio | R69: Severidade das Consequências | U69: Justificativa/Evidências
A70: ='LISTA AMEACAS'!A26 -> At 06 | B70: ='LISTA AMEACAS'!B26 -> Ambientes de desenvolvimento (Dev/Test/Prod) | D70: ='LISTA AMEACAS'!E26 -> Interrupção na cadeia logística | G70: 1 | H70: =VULNERABILIDADES!L70 -> Problemas com fornecedores podem atrasar ou interromper entregas essenciais. | K70: =CONSEQUENCIAS!P70 -> Perda de Disponibilidade | O70: =CONS_AV_QUALIT_ATIVO!O70 -> Importante | R70: Média | U70: Dependência de fornecedores afeta cronogramas. Evidências: SLA de fornecedor violado; incidentes por atraso de insumos/licenças.
G71: 2 | H71: =VULNERABILIDADES!L71 -> Falta de segregação entre ambientes (DEV/TEST/PROD). | K71: =CONSEQUENCIAS!P71 -> Interrupção de serviços | R71: Elevada | U71: Falta segregação entre ambientes críticos. Evidências: acessos cruzados Dev - Prod; incidentes causados por mudança em ambiente errado.
G72: 3 | H72: =VULNERABILIDADES!L72 -> Ausência de redundância de servidores de desenvolvimento. | K72: =CONSEQUENCIAS!P72 -> Impacto operacional | R72: Média | U72: Sem redundância, falha paralisa entregas. Evidências: ausência de nós redundantes; janela de indisponibilidade acima do tolerado.
G73: 4 | H73: =VULNERABILIDADES!L73 -> Falta de monitoramento do ambiente. | K73: =CONSEQUENCIAS!P73 -> Atrasos em processos internos | R73: Média | U73: Sem monitoramento, incidentes demoram a ser tratados. Evidências: MTTD alto; dashboards ausentes; alertas não acionados.
D74: ='LISTA AMEACAS'!I26 -> Manipulação indevida de entregas | G74: 5 | H74: =VULNERABILIDADES!L74 -> Possibilidade de adulteração ou redirecionamento não autorizado de produtos. | K74: =CONSEQUENCIAS!P74 -> Insatisfação de usuários | R74: Média | U74: Entregas adulteradas comprometem confiança. Evidências: chamados de qualidade; reprovação de release por usuário-chave.
G75: 6 | H75: =VULNERABILIDADES!L75 -> Versionamento sem controle adequado. | K75: =CONSEQUENCIAS!P75 -> Perda de produtividade | R75: Média | U75: Versionamento fraco aumenta retrabalho. Evidências: conflitos de merge recorrentes; rollback por versão incorreta.
G76: 7 | H76: =VULNERABILIDADES!L76 -> Uso de dados reais em testes. | K76: =CONSEQUENCIAS!P76 -> Impacto financeiro | R76: Alta | U76: Uso de dados reais em teste pode gerar sanção. Evidências: presença de PII em base de teste; não conformidade LGPD registrada.
G77: 8 | H77: =VULNERABILIDADES!L77 -> Ausência de trilhas de auditoria. | K77: =CONSEQUENCIAS!P77 -> Dependência de suporte emergencial | R77: Elevada | U77: Sem trilha de auditoria, resposta é lenta. Evidências: investigação inconclusiva; runbook de resposta sem evidência suficiente.
B79: Ativo | D79: Ameaças | G79: Nr. | H79: Vulnerabilidades Encontradas | K79: Consequências | O79: Relevancia do Ativo para o Negócio | R79: Severidade das Consequências | U79: Justificativa/Evidências
A80: ='LISTA AMEACAS'!A27 -> At 07 | B80: ='LISTA AMEACAS'!B27 -> Banco de dados de clientes corporativos | D80: ='LISTA AMEACAS'!E27 -> Fraudes financeiras | G80: 1 | H80: =VULNERABILIDADES!L80 -> Possibilidade de manipulação indevida de transações financeiras. | K80: =CONSEQUENCIAS!P80 -> Perda de confidenciabilidade | O80: =CONS_AV_QUALIT_ATIVO!O80 -> Crítico | R80: Alta | U80: Manipulação de transações expõe e compromete dados. Evidências: alertas de transação anômala; acessos fora de perfil.
G81: 2 | H81: =VULNERABILIDADES!L81 -> Controle de acesso insuficiente. | K81: =CONSEQUENCIAS!P81 -> Vazamento dec dados | R81: Alta | U81: Acesso insuficientemente controlado facilita exfiltração. Evidências: privilégios excessivos; exportações massivas sem justificativa.
G82: 3 | H82: =VULNERABILIDADES!L82 -> Ausência de segregação de contas privilegiadas. | K82: =CONSEQUENCIAS!P82 -> Impacto legal ( LGPD) | R82: Alta | U82: Sem segregação privilegiada há risco regulatório severo. Evidências: contas DBA compartilhadas; ausência de SoD.
G83: 4 | H83: =VULNERABILIDADES!L83 -> Falta de validação transacional. | K83: =CONSEQUENCIAS!P83 -> Danos a reputação | R83: Elevada | U83: Falhas transacionais afetam confiança dos clientes. Evidências: reclamações formais; aumento de churn; incidentes públicos.
D84: ='LISTA AMEACAS'!I27 -> Alteração não autorizada de registros | G84: 5 | H84: =VULNERABILIDADES!L84 -> Dados financeiros podem ser alterados indevidamente por usuários sem permissão adequada. | K84: =CONSEQUENCIAS!P84 -> Perda da confiança | R84: Elevada | U84: Dados alterados sem autorização prejudicam credibilidade. Evidências: divergência entre sistemas; trilha de alteração inconsistente.
G85: 6 | H85: =VULNERABILIDADES!L85 -> Vulnerabilidade de SQL Injection. | K85: =CONSEQUENCIAS!P85 -> Multas e penalidades | R85: Alta | U85: SQL injection pode gerar incidente grave e sanções. Evidências: findings de pentest; WAF em modo monitor; queries maliciosas em log.
G86: 7 | H86: =VULNERABILIDADES!L86 -> Falta de logs de integridade. | K86: =CONSEQUENCIAS!P86 -> Uso indevido de dados | R86: Elevada | U86: Sem logs de integridade não há controle efetivo. Evidências: checksum/CDC ausente; auditoria de linha desabilitada.
G87: 8 | H87: =VULNERABILIDADES!L87 -> Contas de serviço com privilégios excessivos. | K87: =CONSEQUENCIAS!P87 -> Exposição dce informações | R87: Alta | U87: Contas de serviço excessivas ampliam superfície de risco. Evidências: service accounts com privilégios administrativos indevidos.
B89: Ativo | D89: Ameaças | G89: Nr. | H89: Vulnerabilidades Encontradas | K89: Consequências | O89: Relevancia do Ativo para o Negócio | R89: Severidade das Consequências | U89: Justificativa/Evidências
A90: ='LISTA AMEACAS'!A28 -> At 08 | B90: ='LISTA AMEACAS'!B28 -> Logs e registros de segurança (SIEM) | D90: ='LISTA AMEACAS'!E28 -> Falta de conformidade | G90: 1 | H90: =VULNERABILIDADES!L90 -> Falta de adesão às diretrizes de segurança estabelecidas pela empresa e normas externas, como ISO 27001. | K90: =CONSEQUENCIAS!P90 -> Perda de Integridade | O90: =CONS_AV_QUALIT_ATIVO!O90 -> Importante | R90: Elevada | U90: Não conformidade compromete governança de segurança. Evidências: auditoria com não conformidades; controles obrigatórios não implementados.
G91: 2 | H91: =VULNERABILIDADES!L91 -> Ausência de integridade dos registros. | K91: =CONSEQUENCIAS!P91 -> Dados inconsistentes | R91: Média | U91: Sem integridade de registros decisões ficam prejudicadas. Evidências: eventos duplicados/incompletos; clock sem NTP uniforme.
G92: 3 | H92: =VULNERABILIDADES!L92 -> Falta de retenção mínima exigida. | K92: =CONSEQUENCIAS!P92 -> Retrabalho operacional | R92: Média | U92: Retenção inadequada gera ajustes e reprocessos. Evidências: expurgo prematuro; necessidade de coleta retroativa manual.
G93: 4 | H93: =VULNERABILIDADES!L93 -> Inconsistência nas fontes de log. | K93: =CONSEQUENCIAS!P93 -> Falhas em relatórios | R93: Média | U93: Fontes incoerentes reduzem qualidade analítica. Evidências: KPI divergente entre ferramentas; erro de parser/conector.
D94: ='LISTA AMEACAS'!I28 -> Desrespeito às normas de segurança | G94: 5 | H94: =VULNERABILIDADES!L94 -> Possibilidade de funcionários ignorarem ou não aplicarem corretamente as políticas de segurança. | K94: =CONSEQUENCIAS!P94 -> Decisões incorretas | R94: Média | U94: Políticas ignoradas geram visão distorcida de risco. Evidências: desvios de processo não tratados; exceções sem aprovação.
G95: 6 | H95: =VULNERABILIDADES!L95 -> Falta de controle de acesso aos logs. | K95: =CONSEQUENCIAS!P95 -> Atrasos em processos | R95: Média | U95: Sem controle de acesso há incidentes recorrentes. Evidências: usuários com acesso além da função; revisões de acesso vencidas.
G96: 7 | H96: =VULNERABILIDADES!L96 -> Ausência de SIEM consolidado. | K96: =CONSEQUENCIAS!P96 -> arga de equipes | R96: Média | U96: Ausência de SIEM consolidado aumenta esforço manual. Evidências: múltiplos consoles; correlação manual de eventos.
G97: 8 | H97: =VULNERABILIDADES!L97 -> Armazenamento inadequado. | K97: =CONSEQUENCIAS!P97 -> Perda de confidencialidade | R97: Elevada | U97: Armazenamento inadequado expõe logs sensíveis. Evidências: logs com dados pessoais sem mascaramento; acesso aberto ao datastore.
B99: Ativo | D99: Ameaças | G99: Nr. | H99: Vulnerabilidades Encontradas | K99: Consequências | O99: Relevancia do Ativo para o Negócio | R99: Severidade das Consequências | U99: Justificativa/Evidências
A100: ='LISTA AMEACAS'!A29 -> At 09 | B100: ='LISTA AMEACAS'!B29 -> Ferramentas de pentest (internas e licenciadas) | D100: ='LISTA AMEACAS'!E29 -> Vazamento de dados pessoais | G100: 1 | H100: =VULNERABILIDADES!L100 -> Exposição de dados sensíveis dos funcionários por acessos não autorizados. | K100: =CONSEQUENCIAS!P100 -> Interupção de serviço | O100: =CONS_AV_QUALIT_ATIVO!O100 -> Significante | R100: Média | U100: Exposição de dados pode exigir bloqueios emergenciais. Evidências: playbook de contenção com suspensão de serviço; incidente prévio similar.
G101: 2 | H101: =VULNERABILIDADES!L101 -> Armazenamento de resultados em locais públicos. | K101: =CONSEQUENCIAS!P101 -> Perda de Disponibilidade | R101: Média | U101: Resultados em locais públicos causam incidentes e suspensão. Evidências: relatórios em compartilhamento aberto; remediação com bloqueio temporário.
G102: 3 | H102: =VULNERABILIDADES!L102 -> Logs de execução não protegidos. | K102: =CONSEQUENCIAS!P102 -> Impacto operacional | R102: Média | U102: Logs sem proteção dificultam investigação. Evidências: eventos sem trilha; impossibilidade de reconstruir timeline.
G103: 4 | H103: =VULNERABILIDADES!L103 -> Transporte inseguro dos relatórios. | K103: =CONSEQUENCIAS!P103 -> Insatisfação de usuários | R103: Média | U103: Transporte inseguro compromete confiança interna. Evidências: envio de relatório por canal não seguro; reclamações de áreas auditadas.
D104: ='LISTA AMEACAS'!I29 -> Uso indevido de informações de colaboradores | G104: 5 | H104: =VULNERABILIDADES!L104 -> Dados de funcionários podem ser acessados e utilizados sem consentimento. | K104: =CONSEQUENCIAS!P104 -> Perda de produtividade | R104: Média | U104: Incidentes com dados pessoais afetam operação. Evidências: aumento de chamados de RH/TI; tempo de resposta elevado.
G105: 6 | H105: =VULNERABILIDADES!L105 -> Execução sem autorização formal. | K105: =CONSEQUENCIAS!P105 -> Impacto financeiro | R105: Elevada | U105: Execução sem autorização pode gerar sanção. Evidências: pentest sem carta de autorização; risco contratual/jurídico documentado.
G106: 7 | H106: =VULNERABILIDADES!L106 -> Ferramentas instaladas em máquinas pessoais. | K106: =CONSEQUENCIAS!P106 -> Sobrecarga de equipe | R106: Média | U106: Ferramentas em máquina pessoal elevam suporte corretivo. Evidências: incidentes por endpoint não gerenciado; retrabalho de contenção.
G107: 8 | H107: =VULNERABILIDADES!L107 -> Falta de segregação de perfis de pentest. | K107: =CONSEQUENCIAS!P107 -> Queda de desempenho | R107: Média | U107: Sem segregação de perfis há conflitos e erros. Evidências: permissões sobrepostas; mudanças não rastreadas entre times.
B109: Ativo | D109: Ameaças | G109: Nr. | H109: Vulnerabilidades Encontradas | K109: Consequências | O109: Relevancia do Ativo para o Negócio | R109: Severidade das Consequências | U109: Justificativa/Evidências
A110: ='LISTA AMEACAS'!A30 -> At 10 | B110: ='LISTA AMEACAS'!B30 -> Credenciais de acesso (senhas, tokens, chaves API) | D110: ='LISTA AMEACAS'!E30 -> Ataques de phishing | G110: 1 | H110: =VULNERABILIDADES!L110 -> Funcionários podem ser induzidos a compartilhar credenciais por e-mails fraudulentos. | K110: =CONSEQUENCIAS!P110 -> Perda de confidencialidade | O110: =CONS_AV_QUALIT_ATIVO!O110 -> Crítico | R110: Alta | U110: Usuários podem entregar credenciais ao atacante. Evidências: campanhas simuladas com taxa alta de clique/entrega; tentativas reais registradas.
G111: 2 | H111: =VULNERABILIDADES!L111 -> Falta de treinamento dos usuários. | K111: =CONSEQUENCIAS!P111 -> Vazamento de informções | R111: Alta | U111: Falta de treinamento amplia sucesso do phishing. Evidências: trilha de treinamento vencida; indicadores de awareness abaixo da meta.
G112: 3 | H112: =VULNERABILIDADES!L112 -> E-mail sem filtro de segurança. | K112: =CONSEQUENCIAS!P112 -> Danos a reputação | R112: Elevada | U112: E-mail sem filtro aumenta incidentes percebidos pelo cliente. Evidências: SPF/DKIM/DMARC incompletos; aumento de incidentes reportados externamente.
G113: 4 | H113: =VULNERABILIDADES!L113 -> Falta de política formal de credenciais. | K113: =CONSEQUENCIAS!P113 -> Impacto legal | R113: Elevada | U113: Política fraca de credenciais compromete compliance. Evidências: política sem requisitos mínimos (complexidade/rotação/MFA).
D114: ='LISTA AMEACAS'!I30 -> Roubo de credenciais | G114: 5 | H114: =VULNERABILIDADES!L114 -> Senhas fracas ou reutilizadas podem ser comprometidas por invasores. | K114: =CONSEQUENCIAS!P114 -> Perda de confiaça | R114: Elevada | U114: Comprometimento recorrente reduz credibilidade. Evidências: histórico de takeover; recorrência mensal de incidentes.
G115: 6 | H115: =VULNERABILIDADES!L115 -> Senhas fracas ou padrão. | K115: =CONSEQUENCIAS!P115 -> Exposição de dados sensíveis | R115: Alta | U115: Senhas fracas facilitam acesso indevido. Evidências: relatório de senha fraca; ausência de bloqueio por tentativas.
G116: 7 | H116: =VULNERABILIDADES!L116 -> Reutilização de senhas. | K116: =CONSEQUENCIAS!P116 -> Uso indevido da infolrmação | R116: Alta | U116: Reutilização de senha propaga invasão. Evidências: senhas repetidas detectadas; ausência de política de não reutilização.
G117: 8 | H117: =VULNERABILIDADES!L117 -> Armazenamento de senhas em texto simples. | K117: =CONSEQUENCIAS!P117 -> Impacto financeiro | R117: Elevada | U117: Senhas em texto simples aceleram incidentes graves. Evidências: credenciais em planilhas/chat/código; incidentes de fraude associados.
B119: Ativo | D119: Ameaças | G119: Nr. | H119: Vulnerabilidades Encontradas | K119: Consequências | O119: Relevancia do Ativo para o Negócio | R119: Severidade das Consequências | U119: Justificativa/Evidências
A120: ='LISTA AMEACAS'!A31 -> At 11 | B120: ='LISTA AMEACAS'!B31 -> Infraestrutura de rede (firewalls, switches, VPN) | D120: ='LISTA AMEACAS'!E31 -> Falha na infraestrutura | G120: 1 | H120: =VULNERABILIDADES!L120 -> Problemas técnicos podem causar indisponibilidade dos sistemas. | K120: =CONSEQUENCIAS!P120 -> Perda de confidencialidade | O120: =CONS_AV_QUALIT_ATIVO!O120 -> Crítico | R120: Elevada | U120: Queda de controles pode expor tráfego interno. Evidências: regras permissivas; ausência de inspeção em segmentos críticos.
G121: 2 | H121: =VULNERABILIDADES!L121 -> Falta de segmentação de rede. | K121: =CONSEQUENCIAS!P121 -> Parada operacional | R121: Alta | U121: Sem segmentação, incidente afeta múltiplos serviços. Evidências: topologia sem VLAN/ACL adequadas; blast radius elevado em simulado.
G122: 3 | H122: =VULNERABILIDADES!L122 -> Equipamentos sem redundância. | K122: =CONSEQUENCIAS!P122 -> Impacto finacenceiro | R122: Elevada | U122: Sem redundância, indisponibilidade gera perda direta. Evidências: links sem backup; falha única causando parada total em incidente anterior.
G123: 4 | H123: =VULNERABILIDADES!L123 -> Firmware desatualizado. | K123: =CONSEQUENCIAS!P123 -> Atraso em atividades | R123: Média | U123: Firmware antigo provoca falhas e manutenção corretiva. Evidências: boletins do fabricante; backlog de atualização acumulado.
D124: ='LISTA AMEACAS'!I31 -> Ataques cibernéticos e invasões | G124: 5 | H124: =VULNERABILIDADES!L124 -> Sistemas sem proteção adequada podem ser alvo de hackers. | K124: =CONSEQUENCIAS!P124 -> Insatisfação dos usuários | R124: Média | U124: Serviços degradados impactam experiência. Evidências: aumento de latência/perda de pacote; chamados de indisponibilidade parcial.
G125: 6 | H125: =VULNERABILIDADES!L125 -> VPN sem autenticação forte. | K125: =CONSEQUENCIAS!P125 -> Redução de produtividade | R125: Média | U125: VPN sem MFA eleva indisponibilidade por incidente. Evidências: acessos suspeitos por VPN; sessões comprometidas.
G126: 7 | H126: =VULNERABILIDADES!L126 -> Portas abertas sem necessidade. | K126: =CONSEQUENCIAS!P126 -> Dependência de suporte técnico | R126: Média | U126: Portas abertas geram ocorrências recorrentes. Evidências: varreduras com portas desnecessárias; incidentes repetidos.
G127: 8 | H127: =VULNERABILIDADES!L127 -> Falta de IDS/IPS efetivo. | K127: =CONSEQUENCIAS!P127 -> Aumento de custos de manutenção | R127: Média | U127: IDS/IPS ineficiente aumenta resposta corretiva. Evidências: assinaturas desatualizadas; baixa taxa de detecção útil.
...

Sheet SESSAO_6
A1: Gestão de Riscos de TI – NBR 27005
A3: Sessão 6
A6: OBJETIVO: Aplicar num exercício os conhecimentos adquiridos na sessão 6. Compreender, desenvolver a estimativa do risco.
A10: Nas três atividades que fazem parte desta sessão, serão vistos os conceitos apreendidos na sessão 6. | J10: Atividades – Sessão 6
J11: 6.1 Avaliação da Probabilidade
A13: Lembre-se: estas atividades devem ser feitas na sequência e com o acompanhamento da norma 27005 | J13: 6.2 Definição da Estimativa
J15: 6.3 Resultado da Estimativa Qualitativa
A16: Qualquer dúvida pergunte ao instrutor!!

Sheet CONS_AV_QUALIT_PROBAB
A1: Avaliação das Probabilidades
A2: Avaliação das Probabilidades
B19: Ativo | D19: Ameaças | G19: Nr. | H19: Vulnerabilidades Encontradas | K19: Consequências | O19: Relevancia do Ativo para o Negócio | R19: Severidade das Consequências | U19: Probabilidade | X19: Justificativa/Evidências
A20: ='LISTA AMEACAS'!A21 -> At 01 | B20: ='LISTA AMEACAS'!B21 -> Infraestrutura de servidores em nuvem | D20: ='LISTA AMEACAS'!E21 -> Vazamento de informações | G20: 1 | H20: =VULNERABILIDADES!L20 -> Falta de classificação da informação | K20: =CONSEQUENCIAS!P20 -> Perda de Autenticidade | O20: =CONS_AV_QUALIT_ATIVO!O20 -> Crítico | R20: =CONS_AV_QUALIT_SEVER!R20 -> Elevada | U20: Provável | X20: Falta de classificação facilita exposição de dados por erro humano - Política de classificação ausente; arquivos sem rótulo; achado de auditoria.
G21: 2 | H21: =VULNERABILIDADES!L21 -> Dados armazenados sem criptografia. | K21: =CONSEQUENCIAS!P21 -> Perda de Integridade | R21: =CONS_AV_QUALIT_SEVER!R21 -> Alta | U21: Ocasional | X21: Dados sem criptografia aumentam risco de leitura/alteração indevida — Inventário de storage sem criptografia; configuração KMS ausente.
G22: 3 | H22: =VULNERABILIDADES!L22 -> Armazenamento inseguro | K22: =CONSEQUENCIAS!P22 -> Perda de confidencialidade | R22: =CONS_AV_QUALIT_SEVER!R22 -> Alta | U22: Provável | X22: Armazenamento inseguro amplia chance de acesso não autorizado — ACL pública; regras SG/NACL permissivas; scan externo.
G23: 4 | H23: =VULNERABILIDADES!L23 -> Falta de monitoramento de acesso. | K23: =CONSEQUENCIAS!P23 -> Perda de Autenticidade | R23: =CONS_AV_QUALIT_SEVER!R23 -> Elevada | U23: Ocasional | X23: Sem monitoramento, ações indevidas passam sem rastreabilidade imediata — Lacunas de CloudTrail/Logs; alerta SIEM ausente.
D24: ='LISTA AMEACAS'!I21 -> Roubo de dados por concorrentes | G24: 5 | H24: =VULNERABILIDADES!L24 -> Falta de backup adequado | K24: =CONSEQUENCIAS!P24 -> Perda de Disponibilidade | R24: =CONS_AV_QUALIT_SEVER!R24 -> Elevada | U24: Ocasional | X24: Backup inadequado pode falhar em incidente e ampliar impacto — Teste de restore reprovado; RPO/RTO fora da meta.
G25: 6 | H25: =VULNERABILIDADES!L25 -> Logs de auditoria incompletos. | K25: =CONSEQUENCIAS!P25 -> Perda de Autenticidade | R25: =CONS_AV_QUALIT_SEVER!R25 -> Elevada | U25: Ocasional | X25: Logs incompletos reduzem capacidade de investigação — Eventos sem usuário/IP; retenção insuficiente.
G26: 7 | H26: =VULNERABILIDADES!L26 -> Acesso indevido | K26: =CONSEQUENCIAS!P26 -> Perda de Integridade | R26: =CONS_AV_QUALIT_SEVER!R26 -> Alta | U26: Provável | X26: Acesso indevido permite manipulação de dados críticos — Permissões excessivas em IAM; SoD ausente.
G27: 8 | H27: =VULNERABILIDADES!L27 -> Armazenamento de credenciais em texto simples. | K27: =CONSEQUENCIAS!P27 -> Perda de confidencialidade | R27: =CONS_AV_QUALIT_SEVER!R27 -> Alta | U27: Provável | X27: Credenciais em texto simples elevam chance de comprometimento — Secret scanning com achados; cofre de segredo não adotado.
B29: Ativo | D29: Ameaças | G29: Nr. | H29: Vulnerabilidades Encontradas | K29: Consequências | O29: Relevancia do Ativo para o Negócio | R29: Severidade das Consequências | U29: Probabilidade | X29: Justificativa/Evidências
A30: ='LISTA AMEACAS'!A22 -> At 02 | B30: ='LISTA AMEACAS'!B22 -> Plataforma de monitoramento SOC 24/7 | D30: ='LISTA AMEACAS'!E22 -> Perda de inovação por acesso indevido | G30: 1 | H30: =VULNERABILIDADES!L30 -> Documentos técnicos e projetos podem ser acessados sem restrições adequadas. | K30: =CONSEQUENCIAS!P30 -> Perda de confidencialidade | O30: =CONS_AV_QUALIT_ATIVO!O30 -> Crítico | R30: =CONS_AV_QUALIT_SEVER!R30 -> Alta | U30: Ocasional | X30: Exposição de documentos técnicos pode ocorrer via permissões amplas — Compartilhamentos indevidos; histórico de exportações.
G31: 2 | H31: =VULNERABILIDADES!L31 -> Sistemas desatualizados. | K31: =CONSEQUENCIAS!P31 -> Perda de Disponibilidade | R31: =CONS_AV_QUALIT_SEVER!R31 -> Elevada | U31: Provável | X31: Sistemas desatualizados tendem a falhar em ambiente 24/7 — Backlog de patch; versão EOL ativa.
G32: 3 | H32: =VULNERABILIDADES!L32 -> Dependência de tecnologias obsoletas. | K32: =CONSEQUENCIAS!P32 -> Perda de Disponibilidade | R32: =CONS_AV_QUALIT_SEVER!R32 -> Média | U32: Ocasional | X32: Tecnologia obsoleta degrada continuidade gradualmente — KPI de desempenho degradado; incidentes repetitivos.
G33: 4 | H33: =VULNERABILIDADES!L33 -> Falta de capacitação da equipe. | K33: =CONSEQUENCIAS!P33 -> Prejuizo financeiro por retrabalho | R33: =CONS_AV_QUALIT_SEVER!R33 -> Média | U33: Frequente | X33: Falta de capacitação causa retrabalho operacional recorrente — Treinamentos vencidos; chamados reabertos.
D34: ='LISTA AMEACAS'!I22 -> Interferência na produção de novos materiais | G34: 5 | H34: =VULNERABILIDADES!L34 -> Acesso indevido à plataforma. | K34: =CONSEQUENCIAS!P34 -> Perda de Integridade | R34: =CONS_AV_QUALIT_SEVER!R34 -> Alta | U34: Ocasional | X34: Acesso indevido pode alterar parâmetros críticos — Mudança sem aprovação; conta genérica.
G35: 6 | H35: =VULNERABILIDADES!L35 -> Configuração inadequada dos sensores. | K35: =CONSEQUENCIAS!P35 -> Perda de Disponibilidade | R35: =CONS_AV_QUALIT_SEVER!R35 -> Elevada | U35: Ocasional | X35: Sensores mal configurados geram indisponibilidade pontual — Baseline divergente; alertas falsos negativos.
G36: 7 | H36: =VULNERABILIDADES!L36 -> Alertas não tratados adequadamente. | K36: =CONSEQUENCIAS!P36 -> Perda de Disponibilidade | R36: =CONS_AV_QUALIT_SEVER!R36 -> Elevada | U36: Frequente | X36: Alertas ignorados/atrasados ocorrem em rotinas com alto volume — SLA de resposta estourado; backlog de alertas.
G37: 8 | H37: =VULNERABILIDADES!L37 -> Falta de segregação de ambientes | K37: =CONSEQUENCIAS!P37 -> Perda de Disponibilidade | R37: =CONS_AV_QUALIT_SEVER!R37 -> Elevada | U37: Ocasional | X37: Sem segregação, impacto de incidente se propaga entre ambientes — Rede sem segmentação; teste de contenção falho.
B39: Ativo | D39: Ameaças | G39: Nr. | H39: Vulnerabilidades Encontradas | K39: Consequências | O39: Relevancia do Ativo para o Negócio | R39: Severidade das Consequências | U39: Probabilidade | X39: Justificativa/Evidências
A40: ='LISTA AMEACAS'!A23 -> At 03 | B40: ='LISTA AMEACAS'!B23 -> Ferramentas de análise de vulnerabilidades | D40: ='LISTA AMEACAS'!E23 -> Ataques cibernéticos | G40: 1 | H40: =VULNERABILIDADES!L40 -> Falta de proteção robusta contra ameaças externas, como hackers e malware. | K40: =CONSEQUENCIAS!P40 -> Perda de confidencialidade | O40: =CONS_AV_QUALIT_ATIVO!O40 -> Importante | R40: =CONS_AV_QUALIT_SEVER!R40 -> Alta | U40: Ocasional | X40: Falta de hardening expõe ferramenta especializada — CVEs abertas; benchmark não aderente.
G41: 2 | H41: =VULNERABILIDADES!L41 -> Ferramentas desatualizadas. | K41: =CONSEQUENCIAS!P41 -> Perda de Disponibilidade | R41: =CONS_AV_QUALIT_SEVER!R41 -> Elevada | U41: Provável | X41: Desatualização compromete varreduras e cobertura de risco — Assinaturas antigas; scans incompletos.
G42: 3 | H42: =VULNERABILIDADES!L42 -> Execução sem autenticação forte. | K42: =CONSEQUENCIAS!P42 -> Perda de confidencialidade | R42: =CONS_AV_QUALIT_SEVER!R42 -> Alta | U42: Ocasional | X42: Sem autenticação forte, uso indevido é mais provável — MFA ausente; logins suspeitos.
G43: 4 | H43: =VULNERABILIDADES!L43 -> Resultados armazenados sem proteção. | K43: =CONSEQUENCIAS!P43 -> Perda de confidencialidade | R43: =CONS_AV_QUALIT_SEVER!R43 -> Alta | U43: Ocasional | X43: Relatórios sem proteção podem vazar internamente — Pasta aberta; ausência de DLP.
D44: ='LISTA AMEACAS'!I23 -> Interrupção de serviços críticos | G44: 5 | H44: =VULNERABILIDADES!L44 -> Falhas nos servidores podem levar à indisponibilidade dos sistemas empresariais. | K44: =CONSEQUENCIAS!P44 -> Perda de Disponibilidade | R44: =CONS_AV_QUALIT_SEVER!R44 -> Alta | U44: Ocasional | X44: Falha de servidor de scan interrompe rotina de segurança — Servidor sem HA; incidente prévio.
G45: 6 | H45: =VULNERABILIDADES!L45 -> Dependência de único servidor. | K45: =CONSEQUENCIAS!P45 -> Perda de Disponibilidade | R45: =CONS_AV_QUALIT_SEVER!R45 -> Elevada | U45: Ocasional | X45: SPOF aumenta risco de parada total — Arquitetura sem redundância.
G46: 7 | H46: =VULNERABILIDADES!L46 -> Falta de redundância. | K46: =CONSEQUENCIAS!P46 -> Perda de Disponibilidade | R46: =CONS_AV_QUALIT_SEVER!R46 -> Elevada | U46: Ocasional | X46: Falta de redundância prolonga recuperação — DR não testado; MTTR alto.
G47: 8 | H47: =VULNERABILIDADES!L47 -> Acesso administrativo compartilhado. | K47: =CONSEQUENCIAS!P47 -> Perda de Disponibilidade | R47: =CONS_AV_QUALIT_SEVER!R47 -> Média | U47: Frequente | X47: Acesso admin compartilhado gera erro operacional recorrente — Contas coletivas; trilha sem autoria individual.
B49: Ativo | D49: Ameaças | G49: Nr. | H49: Vulnerabilidades Encontradas | K49: Consequências | O49: Relevancia do Ativo para o Negócio | R49: Severidade das Consequências | U49: Probabilidade | X49: Justificativa/Evidências
A50: ='LISTA AMEACAS'!A24 -> At 04 | B50: ='LISTA AMEACAS'!B24 -> Sistemas de backup e recuperação de dados | D50: ='LISTA AMEACAS'!E24 -> Roubo de informações | G50: 1 | H50: =VULNERABILIDADES!L50 -> Acesso não autorizado pode comprometer dados sensíveis dos clientes. | K50: =CONSEQUENCIAS!P50 -> Perda de confidencialidade | O50: =CONS_AV_QUALIT_ATIVO!O50 -> Crítico | R50: =CONS_AV_QUALIT_SEVER!R50 -> Alta | U50: Ocasional | X50: Acesso não autorizado ao backup expõe dados sensíveis — Permissão ampla em repositório de backup.
G51: 2 | H51: =VULNERABILIDADES!L51 -> Falta de logs de acesso. | K51: =CONSEQUENCIAS!P51 -> Perda de confidencialidade | R51: =CONS_AV_QUALIT_SEVER!R51 -> Elevada | U51: Ocasional | X51: Sem logs, vazamento pode não ser detectado rapidamente — Logging de restore/download ausente.
G52: 3 | H52: =VULNERABILIDADES!L52 -> Armazenamento inadequado. | K52: =CONSEQUENCIAS!P52 -> Perda de confidencialidade | R52: =CONS_AV_QUALIT_SEVER!R52 -> Alta | U52: Ocasional | X52: Armazenamento inadequado aumenta risco de exfiltração — Mídia sem proteção física/lógica.
G53: 4 | H53: =VULNERABILIDADES!L53 -> Acesso amplo aos backups. | K53: =CONSEQUENCIAS!P53 -> Perda de confidencialidade | R53: =CONS_AV_QUALIT_SEVER!R53 -> Alta | U53: Provável | X53: Acesso amplo a backup é vetor recorrente de exposição — Revisão de acesso vencida.
D54: ='LISTA AMEACAS'!I24 -> Uso indevido por terceiros | G54: 5 | H54: =VULNERABILIDADES!L54 -> Parceiros ou funcionários podem acessar e utilizar dados de clientes sem autorização adequada. | K54: =CONSEQUENCIAS!P54 -> Perda de confidencialidade | R54: =CONS_AV_QUALIT_SEVER!R54 -> Alta | U54: Ocasional | X54: Terceiros sem controle forte podem acessar indevidamente — Acesso parceiro sem MFA.
G55: 6 | H55: =VULNERABILIDADES!L55 -> Ausência de trilhas de auditoria sobre restaurações e consultas. | K55: =CONSEQUENCIAS!P55 -> Perda de confidencialidade | R55: =CONS_AV_QUALIT_SEVER!R55 -> Elevada | U55: Ocasional | X55: Falta de auditoria dificulta detectar abuso — Sessão sem trilha detalhada.
G56: 7 | H56: =VULNERABILIDADES!L56 -> Ausência de mecanismos eficazes de autenticação forte (MFA). | K56: =CONSEQUENCIAS!P56 -> Perda de confidencialidade | R56: =CONS_AV_QUALIT_SEVER!R56 -> Alta | U56: Provável | X56: Ausência de MFA eleva sucesso de comprometimento — Política MFA incompleta.
G57: 8 | H57: =VULNERABILIDADES!L57 -> Falta de políticas formais de uso e proteção da informação. | K57: =CONSEQUENCIAS!P57 -> Perda de confidencialidade | R57: =CONS_AV_QUALIT_SEVER!R57 -> Elevada | U57: Ocasional | X57: Política fraca reduz aderência dos controles — Documento não aprovado/divulgado.
B59: Ativo | D59: Ameaças | G59: Nr. | H59: Vulnerabilidades Encontradas | K59: Consequências | O59: Relevancia do Ativo para o Negócio | R59: Severidade das Consequências | U59: Probabilidade | X59: Justificativa/Evidências
A60: ='LISTA AMEACAS'!A25 -> At 05 | B60: ='LISTA AMEACAS'!B25 -> Código-fonte dos sistemas desenvolvidos | D60: ='LISTA AMEACAS'!E25 -> Falhas operacionais | G60: 1 | H60: =VULNERABILIDADES!L60 -> Erros mecânicos ou falhas humanas podem interromper o fluxo produtivo. | K60: =CONSEQUENCIAS!P60 -> Perda de Disponibilidade | O60: =CONS_AV_QUALIT_ATIVO!O60 -> Crítico | R60: =CONS_AV_QUALIT_SEVER!R60 -> Média | U60: Frequente | X60: Erros humanos em entrega são recorrentes sem controle forte — Rollbacks frequentes; postmortems.
G61: 2 | H61: =VULNERABILIDADES!L61 -> Ausência de revisão de código (code review). | K61: =CONSEQUENCIAS!P61 -> Perda de Disponibilidade | R61: =CONS_AV_QUALIT_SEVER!R61 -> Média | U61: Frequente | X61: Sem code review, defeitos chegam à produção — PR sem revisão obrigatória.
G62: 3 | H62: =VULNERABILIDADES!L62 -> Falta de padrões de desenvolvimento. | K62: =CONSEQUENCIAS!P62 -> Perda de Disponibilidade | R62: =CONS_AV_QUALIT_SEVER!R62 -> Média | U62: Frequente | X62: Sem padrão, retrabalho técnico se repete — Divergência de arquitetura/codificação.
G63: 4 | H63: =VULNERABILIDADES!L63 -> Falta de testes automatizados. | K63: =CONSEQUENCIAS!P63 -> Perda de Disponibilidade | R63: =CONS_AV_QUALIT_SEVER!R63 -> Elevada | U63: Provável | X63: Sem testes automatizados, incidente em release é provável — Cobertura baixa; pipeline sem gate.
D64: ='LISTA AMEACAS'!I25 -> Sabotagem industrial | G64: 5 | H64: =VULNERABILIDADES!L64 -> Possibilidade de funcionários ou terceiros manipularem equipamentos ou processos de produção. | K64: =CONSEQUENCIAS!P64 -> Prejuizo financeiro por retrabalho | R64: =CONS_AV_QUALIT_SEVER!R64 -> Nível | U64: Remoto | X64: Sabotagem é menos comum, mas possível em cenário interno crítico — Alertas de comportamento anômalo interno.
G65: 6 | H65: =VULNERABILIDADES!L65 -> Exposição de credenciais dentro do código. | K65: =CONSEQUENCIAS!P65 -> Perda de confidencialidade | R65: =CONS_AV_QUALIT_SEVER!R65 -> Nível | U65: Provável | X65: Credenciais no código elevam risco de invasão — Achados de secret scanning.
G66: 7 | H66: =VULNERABILIDADES!L66 -> Repositório com acesso permissivo. | K66: =CONSEQUENCIAS!P66 -> Perda de Integridade | R66: =CONS_AV_QUALIT_SEVER!R66 -> Nível | U66: Ocasional | X66: Repositório permissivo facilita alteração indevida — Write amplo em branch principal.
G67: 8 | H67: =VULNERABILIDADES!L67 -> Histórico de commits não auditado. | K67: =CONSEQUENCIAS!P67 -> Perda de Integridade | R67: =CONS_AV_QUALIT_SEVER!R67 -> Nível | U67: Ocasional | X67: Commits sem auditoria reduzem rastreabilidade confiável — Sem assinatura de commit; revisão incompleta.
B69: Ativo | D69: Ameaças | G69: Nr. | H69: Vulnerabilidades Encontradas | K69: Consequências | O69: Relevancia do Ativo para o Negócio | R69: Severidade das Consequências | U69: Probabilidade | X69: Justificativa/Evidências
A70: ='LISTA AMEACAS'!A26 -> At 06 | B70: ='LISTA AMEACAS'!B26 -> Ambientes de desenvolvimento (Dev/Test/Prod) | D70: ='LISTA AMEACAS'!E26 -> Interrupção na cadeia logística | G70: 1 | H70: =VULNERABILIDADES!L70 -> Problemas com fornecedores podem atrasar ou interromper entregas essenciais. | K70: =CONSEQUENCIAS!P70 -> Perda de Disponibilidade | O70: =CONS_AV_QUALIT_ATIVO!O70 -> Importante | R70: =CONS_AV_QUALIT_SEVER!R70 -> Média | U70: Ocasional | X70: Dependência de fornecedor afeta cronograma em eventos pontuais — SLA de terceiros violado.
G71: 2 | H71: =VULNERABILIDADES!L71 -> Falta de segregação entre ambientes (DEV/TEST/PROD). | K71: =CONSEQUENCIAS!P71 -> Interrupção de serviços | R71: =CONS_AV_QUALIT_SEVER!R71 -> Elevada | U71: Ocasional | X71: Falta de segregação cria risco de impacto cruzado — Acesso Dev em Prod identificado.
G72: 3 | H72: =VULNERABILIDADES!L72 -> Ausência de redundância de servidores de desenvolvimento. | K72: =CONSEQUENCIAS!P72 -> Impacto operacional | R72: =CONS_AV_QUALIT_SEVER!R72 -> Média | U72: Ocasional | X72: Ausência de redundância paralisa pipeline em falha — Nó único crítico.
G73: 4 | H73: =VULNERABILIDADES!L73 -> Falta de monitoramento do ambiente. | K73: =CONSEQUENCIAS!P73 -> Atrasos em processos internos | R73: =CONS_AV_QUALIT_SEVER!R73 -> Média | U73: Frequente | X73: Sem monitoramento, atrasos operacionais se repetem — MTTD alto recorrente.
D74: ='LISTA AMEACAS'!I26 -> Manipulação indevida de entregas | G74: 5 | H74: =VULNERABILIDADES!L74 -> Possibilidade de adulteração ou redirecionamento não autorizado de produtos. | K74: =CONSEQUENCIAS!P74 -> Insatisfação de usuários | R74: =CONS_AV_QUALIT_SEVER!R74 -> Média | U74: Ocasional | X74: Entrega manipulada gera falha percebida por usuário — Tickets por divergência de versão.
G75: 6 | H75: =VULNERABILIDADES!L75 -> Versionamento sem controle adequado. | K75: =CONSEQUENCIAS!P75 -> Perda de produtividade | R75: =CONS_AV_QUALIT_SEVER!R75 -> Média | U75: Frequente | X75: Versionamento fraco causa retrabalho constante — Conflito de merge recorrente.
G76: 7 | H76: =VULNERABILIDADES!L76 -> Uso de dados reais em testes. | K76: =CONSEQUENCIAS!P76 -> Impacto financeiro | R76: =CONS_AV_QUALIT_SEVER!R76 -> Alta | U76: Remoto | X76: Uso de dados reais em teste ocorre pontualmente, mas é grave — Base de teste com PII detectada.
G77: 8 | H77: =VULNERABILIDADES!L77 -> Ausência de trilhas de auditoria. | K77: =CONSEQUENCIAS!P77 -> Dependência de suporte emergencial | R77: =CONS_AV_QUALIT_SEVER!R77 -> Elevada | U77: Ocasional | X77: Sem trilha de auditoria, suporte emergencial aumenta — Incidentes sem causa raiz conclusiva.
B79: Ativo | D79: Ameaças | G79: Nr. | H79: Vulnerabilidades Encontradas | K79: Consequências | O79: Relevancia do Ativo para o Negócio | R79: Severidade das Consequências | U79: Probabilidade | X79: Justificativa/Evidências
A80: ='LISTA AMEACAS'!A27 -> At 07 | B80: ='LISTA AMEACAS'!B27 -> Banco de dados de clientes corporativos | D80: ='LISTA AMEACAS'!E27 -> Fraudes financeiras | G80: 1 | H80: =VULNERABILIDADES!L80 -> Possibilidade de manipulação indevida de transações financeiras. | K80: =CONSEQUENCIAS!P80 -> Perda de confidenciabilidade | O80: =CONS_AV_QUALIT_ATIVO!O80 -> Crítico | R80: =CONS_AV_QUALIT_SEVER!R80 -> Alta | U80: Ocasional | X80: Manipulação de transação exige acesso privilegiado específico — Log de alteração sensível.
G81: 2 | H81: =VULNERABILIDADES!L81 -> Controle de acesso insuficiente. | K81: =CONSEQUENCIAS!P81 -> Vazamento dec dados | R81: =CONS_AV_QUALIT_SEVER!R81 -> Alta | U81: Provável | X81: Controle insuficiente facilita exfiltração — Exportações sem justificativa.
G82: 3 | H82: =VULNERABILIDADES!L82 -> Ausência de segregação de contas privilegiadas. | K82: =CONSEQUENCIAS!P82 -> Impacto legal ( LGPD) | R82: =CONS_AV_QUALIT_SEVER!R82 -> Alta | U82: Ocasional | X82: Risco LGPD materializa com falha + exposição — Gap de segregação privilegiada.
G83: 4 | H83: =VULNERABILIDADES!L83 -> Falta de validação transacional. | K83: =CONSEQUENCIAS!P83 -> Danos a reputação | R83: =CONS_AV_QUALIT_SEVER!R83 -> Elevada | U83: Ocasional | X83: Dano reputacional depende de visibilidade externa — Reclamações e churn pós-incidente.
D84: ='LISTA AMEACAS'!I27 -> Alteração não autorizada de registros | G84: 5 | H84: =VULNERABILIDADES!L84 -> Dados financeiros podem ser alterados indevidamente por usuários sem permissão adequada. | K84: =CONSEQUENCIAS!P84 -> Perda da confiança | R84: =CONS_AV_QUALIT_SEVER!R84 -> Elevada | U84: Ocasional | X84: Alteração não autorizada afeta confiança de dados — Divergência entre bases.
G85: 6 | H85: =VULNERABILIDADES!L85 -> Vulnerabilidade de SQL Injection. | K85: =CONSEQUENCIAS!P85 -> Multas e penalidades | R85: =CONS_AV_QUALIT_SEVER!R85 -> Alta | U85: Ocasional | X85: SQLi depende de vetor explorável, mas possível — Pentest com finding alto.
G86: 7 | H86: =VULNERABILIDADES!L86 -> Falta de logs de integridade. | K86: =CONSEQUENCIAS!P86 -> Uso indevido de dados | R86: =CONS_AV_QUALIT_SEVER!R86 -> Elevada | U86: Ocasional | X86: Sem logs de integridade, abuso pode passar oculto — Auditoria de linha desativada.
G87: 8 | H87: =VULNERABILIDADES!L87 -> Contas de serviço com privilégios excessivos. | K87: =CONSEQUENCIAS!P87 -> Exposição dce informações | R87: =CONS_AV_QUALIT_SEVER!R87 -> Alta | U87: Provável | X87: Conta de serviço excessiva é falha recorrente — Inventário de contas com privilégio alto.
B89: Ativo | D89: Ameaças | G89: Nr. | H89: Vulnerabilidades Encontradas | K89: Consequências | O89: Relevancia do Ativo para o Negócio | R89: Severidade das Consequências | U89: Probabilidade | X89: Justificativa/Evidências
A90: ='LISTA AMEACAS'!A28 -> At 08 | B90: ='LISTA AMEACAS'!B28 -> Logs e registros de segurança (SIEM) | D90: ='LISTA AMEACAS'!E28 -> Falta de conformidade | G90: 1 | H90: =VULNERABILIDADES!L90 -> Falta de adesão às diretrizes de segurança estabelecidas pela empresa e normas externas, como ISO 27001. | K90: =CONSEQUENCIAS!P90 -> Perda de Integridade | O90: =CONS_AV_QUALIT_ATIVO!O90 -> Importante | R90: =CONS_AV_QUALIT_SEVER!R90 -> Elevada | U90: Ocasional | X90: Não conformidade surge por lacunas de processo — Auditoria com NC.
G91: 2 | H91: =VULNERABILIDADES!L91 -> Ausência de integridade dos registros. | K91: =CONSEQUENCIAS!P91 -> Dados inconsistentes | R91: =CONS_AV_QUALIT_SEVER!R91 -> Média | U91: Frequente | X91: Inconsistência de logs é comum sem padronização — Eventos duplicados/ausentes.
G92: 3 | H92: =VULNERABILIDADES!L92 -> Falta de retenção mínima exigida. | K92: =CONSEQUENCIAS!P92 -> Retrabalho operacional | R92: =CONS_AV_QUALIT_SEVER!R92 -> Média | U92: Frequente | X92: Retenção inadequada gera retrabalho recorrente — Coleta retroativa manual.
G93: 4 | H93: =VULNERABILIDADES!L93 -> Inconsistência nas fontes de log. | K93: =CONSEQUENCIAS!P93 -> Falhas em relatórios | R93: =CONS_AV_QUALIT_SEVER!R93 -> Média | U93: Frequente | X93: Fontes incoerentes prejudicam relatório com frequência — Erros de parser/conector.
D94: ='LISTA AMEACAS'!I28 -> Desrespeito às normas de segurança | G94: 5 | H94: =VULNERABILIDADES!L94 -> Possibilidade de funcionários ignorarem ou não aplicarem corretamente as políticas de segurança. | K94: =CONSEQUENCIAS!P94 -> Decisões incorretas | R94: =CONS_AV_QUALIT_SEVER!R94 -> Média | U94: Ocasional | X94: Decisão incorreta ocorre com base em dado incompleto — Comitê com decisão revisada.
G95: 6 | H95: =VULNERABILIDADES!L95 -> Falta de controle de acesso aos logs. | K95: =CONSEQUENCIAS!P95 -> Atrasos em processos | R95: =CONS_AV_QUALIT_SEVER!R95 -> Média | U95: Frequente | X95: Falha de acesso gera incidentes repetitivos — Revisão de acesso vencida.
G96: 7 | H96: =VULNERABILIDADES!L96 -> Ausência de SIEM consolidado. | K96: =CONSEQUENCIAS!P96 -> arga de equipes | R96: =CONS_AV_QUALIT_SEVER!R96 -> Média | U96: Frequente | X96: Ausência de SIEM consolidado sobrecarrega times — Correlação manual contínua.
G97: 8 | H97: =VULNERABILIDADES!L97 -> Armazenamento inadequado. | K97: =CONSEQUENCIAS!P97 -> Perda de confidencialidade | R97: =CONS_AV_QUALIT_SEVER!R97 -> Elevada | U97: Ocasional | X97: Armazenamento inadequado pode expor logs sensíveis — Logs com PII sem mascaramento.
B99: Ativo | D99: Ameaças | G99: Nr. | H99: Vulnerabilidades Encontradas | K99: Consequências | O99: Relevancia do Ativo para o Negócio | R99: Severidade das Consequências | U99: Probabilidade | X99: Justificativa/Evidências
A100: ='LISTA AMEACAS'!A29 -> At 09 | B100: ='LISTA AMEACAS'!B29 -> Ferramentas de pentest (internas e licenciadas) | D100: ='LISTA AMEACAS'!E29 -> Vazamento de dados pessoais | G100: 1 | H100: =VULNERABILIDADES!L100 -> Exposição de dados sensíveis dos funcionários por acessos não autorizados. | K100: =CONSEQUENCIAS!P100 -> Interupção de serviço | O100: =CONS_AV_QUALIT_ATIVO!O100 -> Significante | R100: =CONS_AV_QUALIT_SEVER!R100 -> Média | U100: Remoto | X100: Exposição de dados pode exigir bloqueio em casos pontuais — Plano de contenção acionado raramente.
G101: 2 | H101: =VULNERABILIDADES!L101 -> Armazenamento de resultados em locais públicos. | K101: =CONSEQUENCIAS!P101 -> Perda de Disponibilidade | R101: =CONS_AV_QUALIT_SEVER!R101 -> Média | U101: Ocasional | X101: Resultado público indevido ocorre por erro de processo — Pasta pública identificada em revisão.
G102: 3 | H102: =VULNERABILIDADES!L102 -> Logs de execução não protegidos. | K102: =CONSEQUENCIAS!P102 -> Impacto operacional | R102: =CONS_AV_QUALIT_SEVER!R102 -> Média | U102: Ocasional | X102: Logs sem proteção dificultam investigação quando incidente ocorre — Trilha incompleta em incidente simulado.
G103: 4 | H103: =VULNERABILIDADES!L103 -> Transporte inseguro dos relatórios. | K103: =CONSEQUENCIAS!P103 -> Insatisfação de usuários | R103: =CONS_AV_QUALIT_SEVER!R103 -> Média | U103: Ocasional | X103: Transporte inseguro pode comprometer confiança — Relatório enviado por canal inadequado.
D104: ='LISTA AMEACAS'!I29 -> Uso indevido de informações de colaboradores | G104: 5 | H104: =VULNERABILIDADES!L104 -> Dados de funcionários podem ser acessados e utilizados sem consentimento. | K104: =CONSEQUENCIAS!P104 -> Perda de produtividade | R104: =CONS_AV_QUALIT_SEVER!R104 -> Média | U104: Ocasional | X104: Uso indevido de dados de colaborador afeta produtividade — Chamados de RH/TI relacionados.
G105: 6 | H105: =VULNERABILIDADES!L105 -> Execução sem autorização formal. | K105: =CONSEQUENCIAS!P105 -> Impacto financeiro | R105: =CONS_AV_QUALIT_SEVER!R105 -> Elevada | U105: Remoto | X105: Execução sem autorização é menos comum, mas crítica — Ausência de carta de autorização em exceção.
G106: 7 | H106: =VULNERABILIDADES!L106 -> Ferramentas instaladas em máquinas pessoais. | K106: =CONSEQUENCIAS!P106 -> Sobrecarga de equipe | R106: =CONS_AV_QUALIT_SEVER!R106 -> Média | U106: Ocasional | X106: Uso em máquina pessoal aumenta suporte corretivo — Endpoint não gerenciado com incidente.
G107: 8 | H107: =VULNERABILIDADES!L107 -> Falta de segregação de perfis de pentest. | K107: =CONSEQUENCIAS!P107 -> Queda de desempenho | R107: =CONS_AV_QUALIT_SEVER!R107 -> Média | U107: Frequente | X107: Falta de segregação de perfil causa conflitos operacionais recorrentes — Permissões sobrepostas detectadas.
B109: Ativo | D109: Ameaças | G109: Nr. | H109: Vulnerabilidades Encontradas | K109: Consequências | O109: Relevancia do Ativo para o Negócio | R109: Severidade das Consequências | U109: Probabilidade | X109: Justificativa/Evidências
A110: ='LISTA AMEACAS'!A30 -> At 10 | B110: ='LISTA AMEACAS'!B30 -> Credenciais de acesso (senhas, tokens, chaves API) | D110: ='LISTA AMEACAS'!E30 -> Ataques de phishing | G110: 1 | H110: =VULNERABILIDADES!L110 -> Funcionários podem ser induzidos a compartilhar credenciais por e-mails fraudulentos. | K110: =CONSEQUENCIAS!P110 -> Perda de confidencialidade | O110: =CONS_AV_QUALIT_ATIVO!O110 -> Crítico | R110: =CONS_AV_QUALIT_SEVER!R110 -> Alta | U110: Frequente | X110: Phishing é vetor recorrente e contínuo — Simulações com alta taxa de clique.
G111: 2 | H111: =VULNERABILIDADES!L111 -> Falta de treinamento dos usuários. | K111: =CONSEQUENCIAS!P111 -> Vazamento de informções | R111: =CONS_AV_QUALIT_SEVER!R111 -> Alta | U111: Frequente | X111: Sem treinamento, taxa de sucesso de phishing aumenta — Trilha de awareness vencida.
G112: 3 | H112: =VULNERABILIDADES!L112 -> E-mail sem filtro de segurança. | K112: =CONSEQUENCIAS!P112 -> Danos a reputação | R112: =CONS_AV_QUALIT_SEVER!R112 -> Elevada | U112: Ocasional | X112: Dano reputacional depende de incidente público — Registro de reclamação externa.
G113: 4 | H113: =VULNERABILIDADES!L113 -> Falta de política formal de credenciais. | K113: =CONSEQUENCIAS!P113 -> Impacto legal | R113: =CONS_AV_QUALIT_SEVER!R113 -> Elevada | U113: Ocasional | X113: Falha de política pode gerar não conformidade — Política sem requisitos mínimos.
D114: ='LISTA AMEACAS'!I30 -> Roubo de credenciais | G114: 5 | H114: =VULNERABILIDADES!L114 -> Senhas fracas ou reutilizadas podem ser comprometidas por invasores. | K114: =CONSEQUENCIAS!P114 -> Perda de confiaça | R114: =CONS_AV_QUALIT_SEVER!R114 -> Elevada | U114: Ocasional | X114: Perda de confiança cresce com recorrência de contas comprometidas — Histórico de takeover.
G115: 6 | H115: =VULNERABILIDADES!L115 -> Senhas fracas ou padrão. | K115: =CONSEQUENCIAS!P115 -> Exposição de dados sensíveis | R115: =CONS_AV_QUALIT_SEVER!R115 -> Alta | U115: Provável | X115: Senha fraca aumenta chance de acesso indevido — Auditoria de senha fraca.
G116: 7 | H116: =VULNERABILIDADES!L116 -> Reutilização de senhas. | K116: =CONSEQUENCIAS!P116 -> Uso indevido da infolrmação | R116: =CONS_AV_QUALIT_SEVER!R116 -> Alta | U116: Provável | X116: Reutilização propaga comprometimento entre sistemas — Detecção de senha repetida.
G117: 8 | H117: =VULNERABILIDADES!L117 -> Armazenamento de senhas em texto simples. | K117: =CONSEQUENCIAS!P117 -> Impacto financeiro | R117: =CONS_AV_QUALIT_SEVER!R117 -> Elevada | U117: Ocasional | X117: Texto simples acelera incidente grave quando explorado — Credenciais em planilha/código.
B119: Ativo | D119: Ameaças | G119: Nr. | H119: Vulnerabilidades Encontradas | K119: Consequências | O119: Relevancia do Ativo para o Negócio | R119: Severidade das Consequências | U119: Probabilidade | X119: Justificativa/Evidências
A120: ='LISTA AMEACAS'!A31 -> At 11 | B120: ='LISTA AMEACAS'!B31 -> Infraestrutura de rede (firewalls, switches, VPN) | D120: ='LISTA AMEACAS'!E31 -> Falha na infraestrutura | G120: 1 | H120: =VULNERABILIDADES!L120 -> Problemas técnicos podem causar indisponibilidade dos sistemas. | K120: =CONSEQUENCIAS!P120 -> Perda de confidencialidade | O120: =CONS_AV_QUALIT_ATIVO!O120 -> Crítico | R120: =CONS_AV_QUALIT_SEVER!R120 -> Elevada | U120: Ocasional | X120: Quebra de controle de rede pode expor tráfego interno — Regras permissivas indevidas.
G121: 2 | H121: =VULNERABILIDADES!L121 -> Falta de segmentação de rede. | K121: =CONSEQUENCIAS!P121 -> Parada operacional | R121: =CONS_AV_QUALIT_SEVER!R121 -> Alta | U121: Ocasional | X121: Falta de segmentação amplia blast radius — Topologia plana sem microsegmentação.
G122: 3 | H122: =VULNERABILIDADES!L122 -> Equipamentos sem redundância. | K122: =CONSEQUENCIAS!P122 -> Impacto finacenceiro | R122: =CONS_AV_QUALIT_SEVER!R122 -> Elevada | U122: Ocasional | X122: Sem redundância, indisponibilidade gera perda direta — Link único em serviço crítico.
G123: 4 | H123: =VULNERABILIDADES!L123 -> Firmware desatualizado. | K123: =CONSEQUENCIAS!P123 -> Atraso em atividades | R123: =CONS_AV_QUALIT_SEVER!R123 -> Média | U123: Frequente | X123: Firmware antigo gera manutenção corretiva recorrente — Patch atrasado em equipamentos.
D124: ='LISTA AMEACAS'!I31 -> Ataques cibernéticos e invasões | G124: 5 | H124: =VULNERABILIDADES!L124 -> Sistemas sem proteção adequada podem ser alvo de hackers. | K124: =CONSEQUENCIAS!P124 -> Insatisfação dos usuários | R124: =CONS_AV_QUALIT_SEVER!R124 -> Média | U124: Frequente | X124: Degradação de serviço impacta usuários com frequência — Chamados de lentidão.
G125: 6 | H125: =VULNERABILIDADES!L125 -> VPN sem autenticação forte. | K125: =CONSEQUENCIAS!P125 -> Redução de produtividade | R125: =CONS_AV_QUALIT_SEVER!R125 -> Média | U125: Ocasional | X125: VPN sem MFA aumenta risco em eventos específicos — Acessos suspeitos por VPN.
G126: 7 | H126: =VULNERABILIDADES!L126 -> Portas abertas sem necessidade. | K126: =CONSEQUENCIAS!P126 -> Dependência de suporte técnico | R126: =CONS_AV_QUALIT_SEVER!R126 -> Média | U126: Frequente | X126: Portas abertas geram ocorrências repetitivas — Scan com portas desnecessárias.
...

Sheet ESTIMATIVA
A1: Definição das Estimativas (Pesos)
A2: Avaliação das Probabilidades
C19: Defina aqui os pesos para cada item
C21: Critério de Probabilidade
C22: Nível | G22: Definição | O22: Peso
C23: =CRITÉRIOS!C6 -> Frequente | G23: =CRITÉRIOS!F6 -> Tem ocorrido pelo menos uma vez a cada mês | O23: 5 | S23: Atenção! Preencha apenas os pesos
C24: =CRITÉRIOS!C7 -> Provável | G24: =CRITÉRIOS!F7 -> É possível de ocorrer a cada 6 meses ou menos. Nos últimos seis meses já ocorreu | O24: 4
C25: =CRITÉRIOS!C8 -> Ocasional | G25: =CRITÉRIOS!F8 -> Nos último ano já ocorreu pelo menos 1 vezes | O25: 3
C26: =CRITÉRIOS!C9 -> Remoto | G26: =CRITÉRIOS!F9 -> Nos últimos cinco anos já ocorreu pelo menos 3 vezes | O26: 2
C27: =CRITÉRIOS!C10 -> Improvável | G27: =CRITÉRIOS!F10 -> Nunca ocorreu. | O27: 1
C29: Relevância do Ativo
C30: Nível | G30: Definição | O30: Peso
C31: =CRITÉRIOS!C14 -> Insignificante | G31: =CRITÉRIOS!F14 -> Ativo não afeta processos essenciais e sua perda não gera impacto | O31: 1
C32: =CRITÉRIOS!C15 -> Baixo | G32: =CRITÉRIOS!F15 -> Ativo auxilia processos, mas sua causa e impacto são facilmente contornáveis. | O32: 2
C33: =CRITÉRIOS!C16 -> Significante | G33: =CRITÉRIOS!F16 -> É importante para o negócio pois todos os processos passam por ele. | O33: 3
C34: =CRITÉRIOS!C17 -> Importante | G34: =CRITÉRIOS!F17 -> Ativo essencial para o funcionamento de áreas relevantes; sua perda provoca prejuízo operacional considerável | O34: 4
C35: =CRITÉRIOS!C18 -> Crítico | G35: =CRITÉRIOS!F18 -> Ativo funcamental para continuidade do negócio; sua indisponibilidade gera paralisação, perdas financeiras e riscos legais. | O35: 5
C37: Severidade das Consequências
C38: Nível | G38: Definição | O38: Peso
C39: =CRITÉRIOS!C22 -> Insignificante | G39: =CRITÉRIOS!F22 -> Pequena interrupção sem impacto financeiro ou operacional. | O39: 1
C40: =CRITÉRIOS!C23 -> Baixa | G40: =CRITÉRIOS!F23 -> Impacto limitado e com recuperação rápida; custos pequenos. | O40: 2
C41: =CRITÉRIOS!C24 -> Média | G41: =CRITÉRIOS!F24 -> Interrupção moderada; pode gerar retrabalho, atrasos e custos notáveis. | O41: 3
C42: =CRITÉRIOS!C25 -> Alta | G42: =CRITÉRIOS!F25 -> Prejuízo elevado; conpromete operações principais e gera impacto significativo. | O42: 4
C43: =CRITÉRIOS!C26 -> Elevada | G43: =CRITÉRIOS!F26 -> Prejuízo extremo, paralisação total, danos legais, perda de clientes e reputação. | O43: 5
C45: Impacto
C46: Nível | G46: Definição | O46: Peso
C47: =CRITÉRIOS!C30 -> Desprezível | G47: =CRITÉRIOS!F30 -> Impacto mínimo, quase imperceptível; sem prejuízo operacional ou financeiro. | O47: 1 | R47: =O47*$O$51 -> 5
C48: =CRITÉRIOS!C31 -> Baixo | G48: =CRITÉRIOS!F31 -> Pequeno incômodo operacional; custos pequenos; não afeta processos principais. | O48: 2 | R48: =O48*$O$51 -> 10
C49: =CRITÉRIOS!C32 -> Significativo | G49: =CRITÉRIOS!F32 -> Gera interrupções moderadas, retrabalho, atrasos e impacto financeiro notável. | O49: 3 | R49: =O49*$O$51 -> 15
C50: =CRITÉRIOS!C33 -> Importante | G50: =CRITÉRIOS!F33 -> Afetam a imagem da organização e causam interrupção de 12 horas nos negócios. A empresa deixa de funcionar/produzir por 12 horas | O50: 4 | R50: =O50*$O$51 -> 20
C51: =CRITÉRIOS!C34 -> Desastre | G51: =CRITÉRIOS!F34 -> Grande prejuízo financeiro; paralisação total; danos legais severos e fortes crise de reputação. | O51: 5 | R51: =O51*$O$51 -> 25
C53: Critério de Risco | S53: Aceitação
C54: Nível | G54: Definição | O54: De | P54: Até | S54: Prioridade
C55: =CRITÉRIOS!C38 -> Extremo | G55: =CRITÉRIOS!F38 -> A organização pára totalmente seus serviços por mais de 48 horas, impedindo de executar serviços e produzir, afetando sua imagem pública de forma significativa. Prejuízos finaceiros elevados, ações na justiça. | O55: =P56+1 -> 101 | P55: =O23*O35*O43 -> 125 | S55: 1
C56: =CRITÉRIOS!C39 -> Alto | G56: =CRITÉRIOS!F39 -> Risco grave; exige tratamento prioritário e implementação de controles. | O56: =P57+1 -> 65 | P56: =O34*O43*O23 -> 100 | S56: 2
C57: =CRITÉRIOS!C40 -> Médio | G57: =CRITÉRIOS!F40 -> Risco moderado; requer mitigação planejada e monitoramento contínuo. | O57: =P58+1 -> 28 | P57: =O34*O42*O24 -> 64 | S57: 3
C58: =CRITÉRIOS!C41 -> Baixo | G58: =CRITÉRIOS!F41 -> Risco aceitável; manter controles existentes e monitorar periodicamente | O58: =P59+1 -> 9 | P58: =O33*O41*O25 -> 27 | S58: 4
C59: =CRITÉRIOS!C42 -> Irrelevante | G59: =CRITÉRIOS!F42 -> Risco não crítico, porém importante de ser acompanhado; pode exigir ações leves. | O59: 1 | P59: =O32*O40*O26 -> 8 | S59: 5
S60: Nenhuma
S61: Estudo futuro

Sheet RESULT_ESTIMAT_QUALIT
A1: Resultado das Estimativas
V18: IMPACTO= RELEVÂNCIA DO ATIVO * SEVERIDADE
B19: Ativo | D19: Ameaças | G19: Nr. | H19: Vulnerabilidades Encontradas | K19: Consequências | O19: Relevancia do Ativo para o Negócio | R19: Severidade Consequências | V19: Impacto | Z19: Probabilidade | AD19: Justificativa/Evidências
A20: ='LISTA AMEACAS'!A21 -> At 01 | B20: ='LISTA AMEACAS'!B21 -> Infraestrutura de servidores em nuvem | D20: ='LISTA AMEACAS'!E21 -> Vazamento de informações | G20: 1 | H20: =VULNERABILIDADES!L20 -> Falta de classificação da informação | K20: =CONSEQUENCIAS!P20 -> Perda de Autenticidade | O20: =CONS_AV_QUALIT_ATIVO!O20 -> Crítico | Q20: =IF(ISERROR(IF(O20=ESTIMATIVA!$C$31,ESTIMATIVA!$O$31,IF(O20=ESTIMATIVA!$C$32,ESTIMATIVA!$O$32,IF(O20=ESTIMATIVA!$C$33,ESTIMATIVA!$O$33,IF(O20=ESTIMATIVA!$C$34,ESTIMATIVA!$O$34,IF(O20=ESTIMATIVA!$C$35,"$ESTIMATIVA!$O$35"," ")))))),"",IF(O20=ESTIMATIVA!$C$31,ESTIMATIVA!$O$31,IF(O20=ESTIMATIVA!$C$32,ESTIMATIVA!$O$32,IF(O20=ESTIMATIVA!$C$33,ESTIMATIVA!$O$33,IF(O20=ESTIMATIVA!$C$34,ESTIMATIVA!$O$34,IF(O20=ESTIMATIVA!$C$35,ESTIMATIVA!$O$35," ")))))) -> 5 | R20: =CONS_AV_QUALIT_SEVER!R20 -> Elevada | U20: =IF(ISERROR(IF(R20=ESTIMATIVA!$C$39,ESTIMATIVA!$O$39,IF(R20=ESTIMATIVA!$C$40,ESTIMATIVA!$O$40,IF(R20=ESTIMATIVA!$C$41,ESTIMATIVA!$O$41,IF(R20=ESTIMATIVA!$C$42,ESTIMATIVA!$O$42,IF(R20=ESTIMATIVA!$C$43,ESTIMATIVA!$O$43,"")))))),"",IF(R20=ESTIMATIVA!$C$39,ESTIMATIVA!$O$39,IF(R20=ESTIMATIVA!$C$40,ESTIMATIVA!$O$40,IF(R20=ESTIMATIVA!$C$41,ESTIMATIVA!$O$41,IF(R20=ESTIMATIVA!$C$42,ESTIMATIVA!$O$42,IF(R20=ESTIMATIVA!$C$43,ESTIMATIVA!$O$43,"")))))) -> 5 | V20: =IF(ISERROR($Q$20*U20),"",$Q$20*U20) -> 25 | W20: =IF(ISERROR(IF(V20>ESTIMATIVA!$R$50,ESTIMATIVA!$C$51,IF(V20>ESTIMATIVA!$R$49,ESTIMATIVA!$C$50,IF(V20>ESTIMATIVA!$R$48,ESTIMATIVA!$C$49,IF(V20>ESTIMATIVA!$R$47,ESTIMATIVA!$C$48,ESTIMATIVA!$C$47))))),"",IF(V20>ESTIMATIVA!$R$50,ESTIMATIVA!$C$51,IF(V20>ESTIMATIVA!$R$49,ESTIMATIVA!$C$50,IF(V20>ESTIMATIVA!$R$48,ESTIMATIVA!$C$49,IF(V20>ESTIMATIVA!$R$47,ESTIMATIVA!$C$48,ESTIMATIVA!$C$47))))) -> Desastre | Z20: =CONS_AV_QUALIT_PROBAB!U20 -> Provável | AC20: =IF(ISERROR(IF(Z20=ESTIMATIVA!$C$23,ESTIMATIVA!$O$23,IF(Z20=ESTIMATIVA!$C$24,ESTIMATIVA!$O$24,IF(Z20=ESTIMATIVA!$C$25,ESTIMATIVA!$O$25,IF(Z20=ESTIMATIVA!$C$26,ESTIMATIVA!$O$26,IF(Z20=ESTIMATIVA!$C$27,ESTIMATIVA!$O$27,"")))))),"",IF(Z20=ESTIMATIVA!$C$23,ESTIMATIVA!$O$23,IF(Z20=ESTIMATIVA!$C$24,ESTIMATIVA!$O$24,IF(Z20=ESTIMATIVA!$C$25,ESTIMATIVA!$O$25,IF(Z20=ESTIMATIVA!$C$26,ESTIMATIVA!$O$26,IF(Z20=ESTIMATIVA!$C$27,ESTIMATIVA!$O$27,"")))))) -> 4
